Workbook

Sheet Total 
B5: Total Per Community | G5: Total Per 8 Communities
B6: OVERHEADS | C6: TOTAL | G6: OVERHEADS | H6: TOTAL
B7: ='Break Down Per Community'!B2 -> Personnel Expenses | C7: ='Break Down Per Community'!E11 -> 420000 | G7: =B7 -> Personnel Expenses | H7: ='Total Breakdown'!AC36 -> 3360000
B8: ='Break Down Per Community'!B13 -> Equipment and Supplies | C8: ='Break Down Per Community'!E20 -> 61645000 | G8: =B8 -> Equipment and Supplies | H8: ='Total Breakdown'!AC45 -> 365160000
B9: ='Break Down Per Community'!B22 -> Training and Educaton | C9: ='Break Down Per Community'!E29 -> 570000 | G9: =B9 -> Training and Educaton | H9: ='Total Breakdown'!AC54 -> 4560000
B10: ='Break Down Per Community'!B31 -> Outreach and Mobilization | C10: ='Break Down Per Community'!E39 -> 7900000 | G10: =B10 -> Outreach and Mobilization | H10: ='Total Breakdown'!AC64 -> 63200000
B11: ='Break Down Per Community'!B41 -> Facilities and Infrastructure | C11: ='Break Down Per Community'!E48 -> 240000 | G11: =B11 -> Facilities and Infrastructure | H11: ='Total Breakdown'!AC73 -> 1920000
B12: ='Break Down Per Community'!G2 -> Monitoring and Evaluation | C12: ='Break Down Per Community'!J11 -> 1847000 | E12: 1004159407 | G12: =B12 -> Monitoring and Evaluation | H12: ='Total Breakdown'!AC84 -> 14776000
B13: ='Break Down Per Community'!G13 -> Administrative and Overhead Costs | C13: ='Break Down Per Community'!J20 -> 1900000 | G13: =B13 -> Administrative and Overhead Costs | H13: ='Total Breakdown'!AC93 -> 15200000
B14: ='Break Down Per Community'!G22 -> Security | C14: ='Break Down Per Community'!J28 -> 300000 | G14: =B14 -> Security | H14: ='Total Breakdown'!AC101 -> 2400000
B15: ='Break Down Per Community'!G31 -> Contingency Funds | C15: ='Break Down Per Community'!J36 -> 1000000 | G15: =B15 -> Contingency Funds | H15: ='Total Breakdown'!AC108 -> 8000000
C16: 0 | H16: 0
B17: Projected End Balance | C17: =SUM(C7:C16) -> 75822000 | G17: Projected End Balance | H17: =SUM(H7:H16) -> 478576000

Sheet Break Down Per Community
B2: Personnel Expenses | C2: Cost | D2: Frequency | E2: Total | G2: Monitoring and Evaluation | H2: =C13 -> Cost | I2: =D2 -> Frequency | J2: =E2 -> Total
B3: Wages for Medical Doctor | C3: 80000 | D3: 2 | E3: =C3*D3 -> 160000 | G3: Data Collection and Analysis | I3: 1 | J3: =H3*I3 -> 0
B4: Wages for Nurse | C4: 50000 | D4: 2 | E4: =C4*D4 -> 100000 | G4: Evaluation Studies | I4: 1 | J4: =H4*I4 -> 0
B5: Wages for outreach Staff | C5: 40000 | D5: 4 | E5: =C5*D5 -> 160000 | G5: IT Infrastructure and Data Management | I5: 1 | J5: =H5*I5 -> 0
E6: =C6*D6 -> 0 | G6: Portable Tablets | H6: 200000 | I6: 2 | J6: =H6*I6 -> 400000
E7: =C7*D7 -> 0 | G7: Laptop | H7: 300000 | I7: 1 | J7: =H7*I7 -> 300000
E8: =C8*D8 -> 0 | G8: Projector and white screen | H8: 400000 | I8: 1 | J8: =H8*I8 -> 400000
E9: =C9*D9 -> 0 | G9: Internet Routers and Subsription | H9: 30000 | I9: 3 | J9: =H9*I9 -> 90000
E10: =C10*D10 -> 0 | G10: Back Up Power Supply and Mini Inverters | H10: 219000 | I10: 3 | J10: =H10*I10 -> 657000
B11: =B2&" totals" -> Personnel Expenses totals | C11: =SUM(C3:C10) -> 170000 | D11: =SUM(D3:D10) -> 8 | E11: =SUM(E3:E10) -> 420000 | G11: =G2&" totals" -> Monitoring and Evaluation totals | H11: =SUM(H3:H10) -> 1149000 | I11: =SUM(I3:I10) -> 13 | J11: =SUM(J3:J10) -> 1847000
B13: Equipment and Supplies | C13: =C2 -> Cost | D13: Frequency | E13: Total | G13: Administrative and Overhead Costs | H13: =C13 -> Cost | I13: =I2 -> Frequency | J13: =J2 -> Total
B14: Procurement for HPV Sampling | C14: 1500 | D14: 2000 | E14: =C14*D14 -> 3000000 | G14: Rent | H14: 500000 | I14: 1 | J14: =H14*I14 -> 500000
B15: Labotory Analysis | C15: 7822.5 | D15: 2000 | E15: =C15*D15 -> 15645000 | G15: Utilities | H15: 150000 | I15: 1 | J15: =H15*I15 -> 150000
B16: Gynescope | C16: 11250 | D16: 2000 | E16: =C16*D16 -> 22500000 | G16: Inverter Maintenance | I16: 1 | J16: =H16*I16 -> 0
B17: Medical Supply and consumables | C17: 2250 | D17: 2000 | E17: =C17*D17 -> 4500000 | G17: Communication | H17: 150000 | I17: 1 | J17: =H17*I17 -> 150000
B18: Logistics | C18: 8000 | D18: 2000 | E18: =C18*D18 -> 16000000 | G18: Stationeries | H18: 500000 | I18: 1 | J18: =H18*I18 -> 500000
E19: =C19*D19 -> 0 | G19: Insurance and Legal Fees | H19: 37500 | I19: 16 | J19: =H19*I19 -> 600000
B20: =B13&" totals" -> Equipment and Supplies totals | C20: =SUM(C14:C19) -> 30822.5 | D20: =SUM(D14:D19) -> 10000 | E20: =SUM(E14:E19) -> 61645000 | G20: =G13&" totals" -> Administrative and Overhead Costs totals | H20: =SUM(H14:H18) -> 1300000 | I20: =SUM(I14:I19) -> 21 | J20: =SUM(J14:J19) -> 1900000
B22: Training and Educaton | C22: =C13 -> Cost | D22: Frequency | E22: Total | G22: Security | H22: =C31 -> Cost | I22: =I13 -> Frequency | J22: =J13 -> Total
B23: Training Programs | C23: 570000 | D23: 1 | E23: =C23*D23 -> 570000 | G23: Security Personnel | H23: 50000 | I23: 6 | J23: =H23*I23 -> 300000
B24: Education Materials | C24: 0 | D24: 1 | E24: =C24*D24 -> 0 | J24: =H24*I24 -> 0
E25: =C25*D25 -> 0 | J25: =H25*I25 -> 0
E26: =C26*D26 -> 0 | J26: =H26*I26 -> 0
E27: =C27*D27 -> 0 | J27: =H27*I27 -> 0
E28: =C28*D28 -> 0 | G28: =G22&" totals" -> Security totals | H28: =SUM(H23:H27) -> 50000 | I28: =SUM(I23:I27) -> 6 | J28: =SUM(J23:J27) -> 300000
B29: =B22&" totals" -> Training and Educaton totals | C29: =SUM(C23:C28) -> 570000 | D29: =SUM(D23:D28) -> 2 | E29: =SUM(E23:E28) -> 570000
B31: Outreach and Mobilization | C31: =C22 -> Cost | D31: Frequency | E31: =E22 -> Total | G31: Contingency Funds | H31: =C31 -> Cost | I31: =I22 -> Frequency | J31: =J22 -> Total
B32: Community Engagement | C32: 200000 | D32: 10 | E32: =C32*D32 -> 2000000 | G32: Emergency Funds | H32: 1000000 | I32: 1 | J32: =H32*I32 -> 1000000
B33: Transportation and Logistics for the devices | C33: 1000000 | D33: 1 | E33: =C33*D33 -> 1000000 | J33: =H33*I33 -> 0
B34: Radio Ad | C34: 500000 | D34: 1 | E34: =C34*D34 -> 500000 | J34: =H34*I34 -> 0
B35: Content Creation & Social Media Promotions | C35: 400000 | D35: 1 | E35: =C35*D35 -> 400000 | J35: =H35*I35 -> 0
B36: Brochures, Flyers and Posters | C36: 1000000 | D36: 1 | E36: =C36*D36 -> 1000000 | G36: =G31&" totals" -> Contingency Funds totals | H36: =SUM(H32:H35) -> 1000000 | I36: =SUM(I32:I35) -> 1 | J36: =SUM(J32:J35) -> 1000000
B37: Souvenirs | C37: 1500 | D37: 2000 | E37: =C37*D37 -> 3000000
E38: =C38*D38 -> 0
B39: =B31&" totals" -> Outreach and Mobilization totals | C39: =SUM(C32:C38) -> 3101500 | D39: =SUM(D32:D38) -> 2014 | E39: =SUM(E32:E38) -> 7900000
B41: Facilities and Infrastructure | C41: =C31 -> Cost | D41: =D31 -> Frequency | E41: =E31 -> Total
B42: Renovation and Construction | C42: 0 | D42: 1 | E42: =C42*D42 -> 0
B43: Furnitures and Fittings | C43: 120000 | D43: 2 | E43: =C43*D43 -> 240000
E44: =C44*D44 -> 0
E45: =C45*D45 -> 0
E46: =C46*D46 -> 0
E47: =C47*D47 -> 0
B48: =B41&" totals" -> Facilities and Infrastructure totals | C48: =SUM(C42:C47) -> 120000 | D48: =SUM(D42:D47) -> 3 | E48: =SUM(E42:E47) -> 240000

Sheet Total Breakdown
A7: MONTH | G7: Communities | J7: 8
A9: Name of Community | B9: Community 1 | E9: Community 2 | H9: Community 3 | K9: Community 4 | N9: Community 5 | Q9: Community 6 | T9: Community 7 | W9: Community 8 | AA9: MONTH TO DATE
A10: Population
A11: WEEKLY BUDGET SUMMARY | B11: Cost | C11: Frequency | D11: Total | E11: Cost | F11: Frequency | G11: Total | H11: Cost | I11: Frequency | J11: Total | K11: Cost | L11: Frequency | M11: Total | N11: Cost | O11: Frequency | P11: Total | Q11: Cost | R11: Frequency | S11: Total | T11: Cost | U11: Frequency | V11: Total | W11: Cost | X11: Frequency | Y11: Total | AA11: Cost | AB11: Frequency | AC11: Total
A12: Starting Balance | B12: =C12 -> 15 | C12: 15 | D12: =C12*B12 -> 225 | E12: =B16 -> -7520777.5 | F12: =C16 -> -9993 | G12: =F12-E12 -> 7510784.5 | H12: =E16 -> -15041575 | I12: =F16 -> -20026 | J12: =I12-H12 -> 15021549 | K12: =H16 -> -22562372 | L12: =I16 -> -30084 | M12: =L12-K12 -> 22532288 | N12: =IF($J$7=4,0,K16) -> -30083195 | O12: =IF($J$7=4,0,L16) -> -40152 | P12: =O12-N12 -> 30043043 | Q12: =N16 -> -37604018 | R12: =O16 -> -50220 | S12: =R12-Q12 -> 37553798 | T12: =Q16 -> -45124815 | U12: =R16 -> -60278 | V12: =U12-T12 -> 45064537 | W12: =IF($J$7=4,0,T16) -> -52645638 | X12: =IF($J$7=4,0,U16) -> -70346 | Y12: =X12-W12 -> 52575292 | AA12: =SUM(B12,E12,H12,K12,IF($J$7=5,N12,0))-B12-E12-H12-IF($J$7=5,K12,0) -> -22562372 | AB12: =SUM(C12,F12,I12,L12,IF($J$7=5,O12,0))-C12-F12-I12-IF($J$7=5,L12,0) -> -30084 | AC12: =AB12-AA12 -> 22532288
A13: Total Income | B13: =B25 -> 30 | C13: =C25 -> 60 | D13: =C13*B13 -> 1800 | E13: =E25 -> 25 | F13: =F25 -> 35 | G13: =F13-E13 -> 10 | H13: =H25 -> 25 | I13: =I25 -> 10 | J13: =I13-H13 -> -15 | K13: =K25 -> 0 | L13: =L25 -> 0 | M13: =L13-K13 -> 0 | N13: =N25 -> 0 | O13: =O25 -> 0 | P13: =IF($J$7=5,O13-N13,0) -> 0 | Q13: =Q25 -> 25 | R13: =R25 -> 10 | S13: =R13-Q13 -> -15 | T13: =T25 -> 0 | U13: =U25 -> 0 | V13: =U13-T13 -> 0 | W13: =W25 -> 0 | X13: =X25 -> 0 | Y13: =IF($J$7=5,X13-W13,0) -> 0 | AA13: =AA25 -> 80 | AB13: =SUM(C13,F13,I13,L13,IF($J$7=5,O13,0)) -> 105 | AC13: =SUM(C13,F13,I13,L13,IF($J$7=5,O13,0))-SUM(B13,E13,H13,K13,IF($J$7=5,N13,0)) -> 25
A14: Total Expenses | B14: =B36+B45+B54+B64+B73+B84+B93+B101+B108+B115+B123 -> 7520822.5 | C14: =C36+C45+C54+C64+C73+C84+C93+C101+C108+C115+C123 -> 10068 | D14: =C14*B14 -> 75719640930 | E14: =E36+E45+E54+E64+E73+E84+E93+E101+E108+E115+E123 -> 7520822.5 | F14: =F36+F45+F54+F64+F73+F84+F93+F101+F108+F115+F123 -> 10068 | G14: =E14-F14 -> 7510754.5 | H14: =H36+H45+H54+H64+H73+H84+H93+H101+H108+H115+H123 -> 7520822.5 | I14: =I36+I45+I54+I64+I73+I84+I93+I101+I108+I115+I123 -> 10068 | J14: =H14-I14 -> 7510754.5 | K14: =K36+K45+K54+K64+K73+K84+K93+K101+K108+K115+K123 -> 7520822.5 | L14: =L36+L45+L54+L64+L73+L84+L93+L101+L108+L115+L123 -> 10068 | M14: =K14-L14 -> 7510754.5 | N14: =N36+N45+N54+N64+N73+N84+N93+N101+N108+N115+N123 -> 7520822.5 | O14: =O36+O45+O54+O64+O73+O84+O93+O101+O108+O115+O123 -> 10068 | P14: =IF($J$7=5,O14-N14,0) -> 0 | Q14: =Q36+Q45+Q54+Q64+Q73+Q84+Q93+Q101+Q108+Q115+Q123 -> 7520822.5 | R14: =R36+R45+R54+R64+R73+R84+R93+R101+R108+R115+R123 -> 10068 | S14: =Q14-R14 -> 7510754.5 | T14: =T36+T45+T54+T64+T73+T84+T93+T101+T108+T115+T123 -> 7520822.5 | U14: =U36+U45+U54+U64+U73+U84+U93+U101+U108+U115+U123 -> 10068 | V14: =T14-U14 -> 7510754.5 | W14: =W36+W45+W54+W64+W73+W84+W93+W101+W108+W115+W123 -> 7520822.5 | X14: =X36+X45+X54+X64+X73+X84+X93+X101+X108+X115+X123 -> 10068 | Y14: =IF($J$7=5,X14-W14,0) -> 0 | AA14: =AA36+AA45+AA54+AA64+AA73+AA84+AA93+AA101+AA108+AA115+AA123 -> 60166580 | AB14: =SUM(C14,F14,I14,L14,IF($J$7=5,O14,0)) -> 40272 | AC14: =AA14-AB14 -> 60126308
A15: NET (Income - Expenses) | B15: =B13-B14 -> -7520792.5 | C15: =C13-C14 -> -10008 | D15: =C15*B15 -> 75268091340 | E15: =E13-E14 -> -7520797.5 | F15: =F13-F14 -> -10033 | G15: =E15-F15 -> -7510764.5 | H15: =H13-H14 -> -7520797.5 | I15: =I13-I14 -> -10058 | J15: =H15-I15 -> -7510739.5 | K15: =K13-K14 -> -7520822.5 | L15: =L13-L14 -> -10068 | M15: =K15-L15 -> -7510754.5 | N15: =N13-N14 -> -7520822.5 | O15: =O13-O14 -> -10068 | P15: =IF($J$7=5,O15-N15,0) -> 0 | Q15: =Q13-Q14 -> -7520797.5 | R15: =R13-R14 -> -10058 | S15: =Q15-R15 -> -7510739.5 | T15: =T13-T14 -> -7520822.5 | U15: =U13-U14 -> -10068 | V15: =T15-U15 -> -7510754.5 | W15: =W13-W14 -> -7520822.5 | X15: =X13-X14 -> -10068 | Y15: =IF($J$7=5,X15-W15,0) -> 0 | AA15: =AA13-AA14 -> -60166500 | AB15: =SUM(C15,F15,I15,L15,IF($J$7=5,O15,0)) -> -40167 | AC15: =SUM(C15,F15,I15,L15,IF($J$7=5,O15,0))-SUM(B15,E15,H15,K15,IF($J$7=5,N15,0)) -> 30043043
A16: Projected End Balance | B16: =B13-B14+B12 -> -7520777.5 | C16: =C13-C14+C12 -> -9993 | D16: =C16*B16 -> 7.515513e+10 | E16: =E13-E14+E12 -> -15041575 | F16: =F13-F14+F12 -> -20026 | G16: =F16-E16 -> 15021549 | H16: =H13-H14+H12 -> -22562372 | I16: =I13-I14+I12 -> -30084 | J16: =I16-H16 -> 22532288 | K16: =K13-K14+K12 -> -30083195 | L16: =L13-L14+L12 -> -40152 | M16: =L16-K16 -> 30043043 | N16: =N13-N14+N12 -> -37604018 | O16: =O13-O14+O12 -> -50220 | P16: =IF($J$7=5,O16-N16,0) -> 0 | Q16: =Q13-Q14+Q12 -> -45124815 | R16: =R13-R14+R12 -> -60278 | S16: =R16-Q16 -> 45064537 | T16: =T13-T14+T12 -> -52645638 | U16: =U13-U14+U12 -> -70346 | V16: =U16-T16 -> 52575292 | W16: =W13-W14+W12 -> -60166460 | X16: =X13-X14+X12 -> -80414 | Y16: =IF($J$7=5,X16-W16,0) -> 0 | AA16: =AA13-AA14+B12 -> -60166485 | AB16: =AB13-AB14+C12 -> -40152 | AC16: =AB16-AA16 -> 60126333
A18: INCOME | B18: =B11 -> Cost | C18: =C11 -> Frequency | D18: =D11 -> Total | E18: =E11 -> Cost | F18: =F11 -> Frequency | G18: =G11 -> Total | H18: =H11 -> Cost | I18: =I11 -> Frequency | ... Y18: =Y11 -> Total | AA18: =$AA$11 -> Cost | AB18: =$AB$11 -> Frequency | AC18: Difference
B19: 30 | C19: 60 | D19: =C19-B19 -> 30 | E19: 25 | F19: 35 | G19: =F19-E19 -> 10 | H19: 25 | I19: 10 | J19: =I19-H19 -> -15 | M19: =L19-K19 -> 0 | P19: =O19-N19 -> 0 | Q19: 25 | R19: 10 | S19: =R19-Q19 -> -15 | V19: =U19-T19 -> 0 | Y19: =X19-W19 -> 0 | AA19: =SUM(B19,E19,H19,K19,IF($J$7=5,N19,0)) -> 80 | AB19: =SUM(C19,F19,I19,L19,IF($J$7=5,O19,0)) -> 105 | AC19: =SUM(C19,F19,I19,L19,IF($J$7=5,O19,0))-SUM(B19,E19,H19,K19,IF($J$7=5,N19,0)) -> 25
D20: =C20-B20 -> 0 | G20: =F20-E20 -> 0 | J20: =I20-H20 -> 0 | M20: =L20-K20 -> 0 | P20: =O20-N20 -> 0 | S20: =R20-Q20 -> 0 | V20: =U20-T20 -> 0 | Y20: =X20-W20 -> 0 | AA20: =SUM(B20,E20,H20,K20,IF($J$7=5,N20,0)) -> 0 | AB20: =SUM(C20,F20,I20,L20,IF($J$7=5,O20,0)) -> 0 | AC20: =SUM(C20,F20,I20,L20,IF($J$7=5,O20,0))-SUM(B20,E20,H20,K20,IF($J$7=5,N20,0)) -> 0
D21: =C21-B21 -> 0 | G21: =F21-E21 -> 0 | J21: =I21-H21 -> 0 | M21: =L21-K21 -> 0 | P21: =O21-N21 -> 0 | S21: =R21-Q21 -> 0 | V21: =U21-T21 -> 0 | Y21: =X21-W21 -> 0 | AA21: =SUM(B21,E21,H21,K21,IF($J$7=5,N21,0)) -> 0 | AB21: =SUM(C21,F21,I21,L21,IF($J$7=5,O21,0)) -> 0 | AC21: =SUM(C21,F21,I21,L21,IF($J$7=5,O21,0))-SUM(B21,E21,H21,K21,IF($J$7=5,N21,0)) -> 0
D22: =C22-B22 -> 0 | G22: =F22-E22 -> 0 | J22: =I22-H22 -> 0 | M22: =L22-K22 -> 0 | P22: =O22-N22 -> 0 | S22: =R22-Q22 -> 0 | V22: =U22-T22 -> 0 | Y22: =X22-W22 -> 0 | AA22: =SUM(B22,E22,H22,K22,IF($J$7=5,N22,0)) -> 0 | AB22: =SUM(C22,F22,I22,L22,IF($J$7=5,O22,0)) -> 0 | AC22: =SUM(C22,F22,I22,L22,IF($J$7=5,O22,0))-SUM(B22,E22,H22,K22,IF($J$7=5,N22,0)) -> 0
D23: =C23-B23 -> 0 | G23: =F23-E23 -> 0 | J23: =I23-H23 -> 0 | M23: =L23-K23 -> 0 | P23: =O23-N23 -> 0 | S23: =R23-Q23 -> 0 | V23: =U23-T23 -> 0 | Y23: =X23-W23 -> 0 | AA23: =SUM(B23,E23,H23,K23,IF($J$7=5,N23,0)) -> 0 | AB23: =SUM(C23,F23,I23,L23,IF($J$7=5,O23,0)) -> 0 | AC23: =SUM(C23,F23,I23,L23,IF($J$7=5,O23,0))-SUM(B23,E23,H23,K23,IF($J$7=5,N23,0)) -> 0
D24: =C24-B24 -> 0 | G24: =F24-E24 -> 0 | J24: =I24-H24 -> 0 | M24: =L24-K24 -> 0 | P24: =O24-N24 -> 0 | S24: =R24-Q24 -> 0 | V24: =U24-T24 -> 0 | Y24: =X24-W24 -> 0 | AA24: =SUM(B24,E24,H24,K24,IF($J$7=5,N24,0)) -> 0 | AB24: =SUM(C24,F24,I24,L24,IF($J$7=5,O24,0)) -> 0 | AC24: =SUM(C24,F24,I24,L24,IF($J$7=5,O24,0))-SUM(B24,E24,H24,K24,IF($J$7=5,N24,0)) -> 0
A25: ="Total "&A18 -> Total INCOME | B25: =SUM(B19:B24) -> 30 | C25: =SUM(C19:C24) -> 60 | D25: =SUM(D19:D24) -> 30 | E25: =SUM(E19:E24) -> 25 | F25: =SUM(F19:F24) -> 35 | G25: =SUM(G19:G24) -> 10 | H25: =SUM(H19:H24) -> 25 | I25: =SUM(I19:I24) -> 10 | ... Y25: =SUM(Y19:Y24) -> 0 | AA25: =SUM(AA19:AA24) -> 80 | AB25: =SUM(C25,F25,I25,L25,IF($J$7=5,O25,0)) -> 105 | AC25: =SUM(AC19:AC24) -> 25
A27: ='Total '!B7 -> Personnel Expenses | B27: =$B$11 -> Cost | C27: =$C$11 -> Frequency | D27: =$D$11 -> Total | E27: =$E$11 -> Cost | F27: =$F$11 -> Frequency | G27: =$G$11 -> Total | H27: =$H$11 -> Cost | I27: =$I$11 -> Frequency | J27: =$J$11 -> Total | K27: =$K$11 -> Cost | L27: =$L$11 -> Frequency | M27: =$M$11 -> Total | N27: =$K$11 -> Cost | O27: =$L$11 -> Frequency | P27: =$M$11 -> Total | Q27: =$H$11 -> Cost | R27: =$I$11 -> Frequency | S27: =$J$11 -> Total | T27: =$K$11 -> Cost | U27: =$L$11 -> Frequency | V27: =$M$11 -> Total | W27: =$K$11 -> Cost | X27: =$L$11 -> Frequency | Y27: =$M$11 -> Total | AA27: =$AA$11 -> Cost | AB27: =$AB$11 -> Frequency | AC27: =$AC$11 -> Total
A28: ='Break Down Per Community'!B3 -> Wages for Medical Doctor | B28: ='Break Down Per Community'!C3 -> 80000 | C28: 2 | D28: =B28*C28 -> 160000 | E28: ='Break Down Per Community'!C3 -> 80000 | F28: ='Break Down Per Community'!D3 -> 2 | G28: ='Break Down Per Community'!E3 -> 160000 | H28: ='Break Down Per Community'!C3 -> 80000 | I28: ='Break Down Per Community'!D3 -> 2 | J28: ='Break Down Per Community'!E3 -> 160000 | K28: ='Break Down Per Community'!C3 -> 80000 | L28: ='Break Down Per Community'!D3 -> 2 | M28: ='Break Down Per Community'!E3 -> 160000 | N28: ='Break Down Per Community'!C3 -> 80000 | O28: ='Break Down Per Community'!D3 -> 2 | P28: ='Break Down Per Community'!E3 -> 160000 | Q28: ='Break Down Per Community'!C3 -> 80000 | R28: ='Break Down Per Community'!D3 -> 2 | S28: ='Break Down Per Community'!E3 -> 160000 | T28: ='Break Down Per Community'!C3 -> 80000 | U28: ='Break Down Per Community'!D3 -> 2 | V28: ='Break Down Per Community'!E3 -> 160000 | W28: =T28 -> 80000 | X28: =U28 -> 2 | Y28: =V28 -> 160000 | AA28: =SUM(B28,E28,H28,K28,N28,Q28,T28,W28) -> 640000 | AB28: =SUM(C28,F28,I28,L28,O28,R28,U28,X28) -> 16 | AC28: =SUM(D28,G28,J28,M28,P28,S28,V28,Y28) -> 1280000
A29: ='Break Down Per Community'!B4 -> Wages for Nurse | B29: ='Break Down Per Community'!C4 -> 50000 | C29: 2 | D29: =B29*C29 -> 100000 | E29: ='Break Down Per Community'!C4 -> 50000 | F29: ='Break Down Per Community'!D4 -> 2 | G29: ='Break Down Per Community'!E4 -> 100000 | H29: ='Break Down Per Community'!C4 -> 50000 | I29: ='Break Down Per Community'!D4 -> 2 | J29: ='Break Down Per Community'!E4 -> 100000 | K29: ='Break Down Per Community'!C4 -> 50000 | L29: ='Break Down Per Community'!D4 -> 2 | M29: ='Break Down Per Community'!E4 -> 100000 | N29: ='Break Down Per Community'!C4 -> 50000 | O29: ='Break Down Per Community'!D4 -> 2 | P29: ='Break Down Per Community'!E4 -> 100000 | Q29: ='Break Down Per Community'!C4 -> 50000 | R29: ='Break Down Per Community'!D4 -> 2 | S29: ='Break Down Per Community'!E4 -> 100000 | T29: ='Break Down Per Community'!C4 -> 50000 | U29: ='Break Down Per Community'!D4 -> 2 | V29: ='Break Down Per Community'!E4 -> 100000 | W29: =T29 -> 50000 | X29: =U29 -> 2 | Y29: =V29 -> 100000 | AA29: =SUM(B29,E29,H29,K29,N29,Q29,T29,W29) -> 400000 | AB29: =SUM(C29,F29,I29,L29,O29,R29,U29,X29) -> 16 | AC29: =SUM(D29,G29,J29,M29,P29,S29,V29,Y29) -> 800000
A30: ='Break Down Per Community'!B5 -> Wages for outreach Staff | B30: ='Break Down Per Community'!C5 -> 40000 | C30: 4 | D30: =B30*C30 -> 160000 | E30: ='Break Down Per Community'!C5 -> 40000 | F30: ='Break Down Per Community'!D5 -> 4 | G30: ='Break Down Per Community'!E5 -> 160000 | H30: ='Break Down Per Community'!C5 -> 40000 | I30: ='Break Down Per Community'!D5 -> 4 | J30: ='Break Down Per Community'!E5 -> 160000 | K30: ='Break Down Per Community'!C5 -> 40000 | L30: ='Break Down Per Community'!D5 -> 4 | M30: ='Break Down Per Community'!E5 -> 160000 | N30: ='Break Down Per Community'!C5 -> 40000 | O30: ='Break Down Per Community'!D5 -> 4 | P30: ='Break Down Per Community'!E5 -> 160000 | Q30: ='Break Down Per Community'!C5 -> 40000 | R30: ='Break Down Per Community'!D5 -> 4 | S30: ='Break Down Per Community'!E5 -> 160000 | T30: ='Break Down Per Community'!C5 -> 40000 | U30: ='Break Down Per Community'!D5 -> 4 | V30: ='Break Down Per Community'!E5 -> 160000 | W30: =T30 -> 40000 | X30: =U30 -> 4 | Y30: =V30 -> 160000 | AA30: =SUM(B30,E30,H30,K30,N30,Q30,T30,W30) -> 320000 | AB30: =SUM(C30,F30,I30,L30,O30,R30,U30,X30) -> 32 | AC30: =SUM(D30,G30,J30,M30,P30,S30,V30,Y30) -> 1280000
D31: =B31*C31 -> 0 | E31: ='Break Down Per Community'!C6 -> 0 | F31: ='Break Down Per Community'!D6 -> 0 | G31: ='Break Down Per Community'!E6 -> 0 | H31: ='Break Down Per Community'!C6 -> 0 | I31: ='Break Down Per Community'!D6 -> 0 | J31: ='Break Down Per Community'!E6 -> 0 | K31: ='Break Down Per Community'!C6 -> 0 | L31: ='Break Down Per Community'!D6 -> 0 | M31: ='Break Down Per Community'!E6 -> 0 | N31: ='Break Down Per Community'!C6 -> 0 | O31: ='Break Down Per Community'!D6 -> 0 | P31: ='Break Down Per Community'!E6 -> 0 | Q31: ='Break Down Per Community'!C6 -> 0 | R31: ='Break Down Per Community'!D6 -> 0 | S31: ='Break Down Per Community'!E6 -> 0 | T31: ='Break Down Per Community'!C6 -> 0 | U31: ='Break Down Per Community'!D6 -> 0 | V31: ='Break Down Per Community'!E6 -> 0 | W31: =T31 -> 0 | X31: =U31 -> 0 | Y31: =V31 -> 0 | AA31: =SUM(B31,E31,H31,K31,N31,Q31,T31,W31) -> 0 | AB31: =SUM(C31,F31,I31,L31,O31,R31,U31,X31) -> 0 | AC31: =SUM(D31,G31,J31,M31,P31,S31,V31,Y31) -> 0
D32: =B32*C32 -> 0 | E32: ='Break Down Per Community'!C7 -> 0 | F32: ='Break Down Per Community'!D7 -> 0 | G32: ='Break Down Per Community'!E7 -> 0 | H32: ='Break Down Per Community'!C7 -> 0 | I32: ='Break Down Per Community'!D7 -> 0 | J32: ='Break Down Per Community'!E7 -> 0 | K32: ='Break Down Per Community'!C7 -> 0 | L32: ='Break Down Per Community'!D7 -> 0 | M32: ='Break Down Per Community'!E7 -> 0 | N32: ='Break Down Per Community'!C7 -> 0 | O32: ='Break Down Per Community'!D7 -> 0 | P32: ='Break Down Per Community'!E7 -> 0 | Q32: ='Break Down Per Community'!C7 -> 0 | R32: ='Break Down Per Community'!D7 -> 0 | S32: ='Break Down Per Community'!E7 -> 0 | T32: ='Break Down Per Community'!C7 -> 0 | U32: ='Break Down Per Community'!D7 -> 0 | V32: ='Break Down Per Community'!E7 -> 0 | W32: =T32 -> 0 | X32: =U32 -> 0 | Y32: =V32 -> 0 | AA32: =SUM(B32,E32,H32,K32,N32,Q32,T32,W32) -> 0 | AB32: =SUM(C32,F32,I32,L32,O32,R32,U32,X32) -> 0 | AC32: =SUM(D32,G32,J32,M32,P32,S32,V32,Y32) -> 0
D33: =B33*C33 -> 0 | E33: ='Break Down Per Community'!C8 -> 0 | F33: ='Break Down Per Community'!D8 -> 0 | G33: ='Break Down Per Community'!E8 -> 0 | H33: ='Break Down Per Community'!C8 -> 0 | I33: ='Break Down Per Community'!D8 -> 0 | J33: ='Break Down Per Community'!E8 -> 0 | K33: ='Break Down Per Community'!C8 -> 0 | L33: ='Break Down Per Community'!D8 -> 0 | M33: ='Break Down Per Community'!E8 -> 0 | N33: ='Break Down Per Community'!C8 -> 0 | O33: ='Break Down Per Community'!D8 -> 0 | P33: ='Break Down Per Community'!E8 -> 0 | Q33: ='Break Down Per Community'!C8 -> 0 | R33: ='Break Down Per Community'!D8 -> 0 | S33: ='Break Down Per Community'!E8 -> 0 | T33: ='Break Down Per Community'!C8 -> 0 | U33: ='Break Down Per Community'!D8 -> 0 | V33: ='Break Down Per Community'!E8 -> 0 | W33: =T33 -> 0 | X33: =U33 -> 0 | Y33: =V33 -> 0 | AA33: =SUM(B33,E33,H33,K33,N33,Q33,T33,W33) -> 0 | AB33: =SUM(C33,F33,I33,L33,O33,R33,U33,X33) -> 0 | AC33: =SUM(D33,G33,J33,M33,P33,S33,V33,Y33) -> 0
D34: =B34*C34 -> 0 | E34: ='Break Down Per Community'!C9 -> 0 | F34: ='Break Down Per Community'!D9 -> 0 | G34: ='Break Down Per Community'!E9 -> 0 | H34: ='Break Down Per Community'!C9 -> 0 | I34: ='Break Down Per Community'!D9 -> 0 | J34: ='Break Down Per Community'!E9 -> 0 | K34: ='Break Down Per Community'!C9 -> 0 | L34: ='Break Down Per Community'!D9 -> 0 | M34: ='Break Down Per Community'!E9 -> 0 | N34: ='Break Down Per Community'!C9 -> 0 | O34: ='Break Down Per Community'!D9 -> 0 | P34: ='Break Down Per Community'!E9 -> 0 | Q34: ='Break Down Per Community'!C9 -> 0 | R34: ='Break Down Per Community'!D9 -> 0 | S34: ='Break Down Per Community'!E9 -> 0 | T34: ='Break Down Per Community'!C9 -> 0 | U34: ='Break Down Per Community'!D9 -> 0 | V34: ='Break Down Per Community'!E9 -> 0 | W34: =T34 -> 0 | X34: =U34 -> 0 | Y34: =V34 -> 0 | AA34: =SUM(B34,E34,H34,K34,N34,Q34,T34,W34) -> 0 | AB34: =SUM(C34,F34,I34,L34,O34,R34,U34,X34) -> 0 | AC34: =SUM(D34,G34,J34,M34,P34,S34,V34,Y34) -> 0
D35: =B35*C35 -> 0 | E35: ='Break Down Per Community'!C10 -> 0 | F35: ='Break Down Per Community'!D10 -> 0 | G35: ='Break Down Per Community'!E10 -> 0 | H35: ='Break Down Per Community'!C10 -> 0 | I35: ='Break Down Per Community'!D10 -> 0 | J35: ='Break Down Per Community'!E10 -> 0 | K35: ='Break Down Per Community'!C10 -> 0 | L35: ='Break Down Per Community'!D10 -> 0 | M35: ='Break Down Per Community'!E10 -> 0 | N35: ='Break Down Per Community'!C10 -> 0 | O35: ='Break Down Per Community'!D10 -> 0 | P35: ='Break Down Per Community'!E10 -> 0 | Q35: ='Break Down Per Community'!C10 -> 0 | R35: ='Break Down Per Community'!D10 -> 0 | S35: ='Break Down Per Community'!E10 -> 0 | T35: ='Break Down Per Community'!C10 -> 0 | U35: ='Break Down Per Community'!D10 -> 0 | V35: ='Break Down Per Community'!E10 -> 0 | W35: =T35 -> 0 | X35: =U35 -> 0 | Y35: =V35 -> 0 | AA35: =SUM(B35,E35,H35,K35,N35,Q35,T35,W35) -> 0 | AB35: =SUM(C35,F35,I35,L35,O35,R35,U35,X35) -> 0 | AC35: =SUM(D35,G35,J35,M35,P35,S35,V35,Y35) -> 0
A36: ="Total "&A27 -> Total Personnel Expenses | B36: =SUM(B28:B35) -> 170000 | C36: =SUM(C28:C35) -> 8 | D36: =SUM(D28:D35) -> 420000 | E36: =SUM(E28:E35) -> 170000 | F36: =SUM(F28:F35) -> 8 | G36: =SUM(G28:G35) -> 420000 | H36: =SUM(H28:H35) -> 170000 | I36: =SUM(I28:I35) -> 8 | ... Y36: =SUM(Y28:Y35) -> 420000 | AA36: =SUM(AA28:AA35) -> 1360000 | AB36: =SUM(C36,F36,I36,L36,IF($J$7=5,O36,0)) -> 32 | AC36: =SUM(AC28:AC35) -> 3360000
A38: ='Total '!B8 -> Equipment and Supplies | B38: =$B$11 -> Cost | C38: =$C$11 -> Frequency | D38: =$D$11 -> Total | E38: =$E$11 -> Cost | F38: =$F$11 -> Frequency | G38: =$G$11 -> Total | H38: =$H$11 -> Cost | I38: =$I$11 -> Frequency | J38: =$J$11 -> Total | K38: =$K$11 -> Cost | L38: =$L$11 -> Frequency | M38: =$M$11 -> Total | N38: =$K$11 -> Cost | O38: =$L$11 -> Frequency | P38: =$M$11 -> Total | Q38: =$H$11 -> Cost | R38: =$I$11 -> Frequency | S38: =$J$11 -> Total | T38: =$K$11 -> Cost | U38: =$L$11 -> Frequency | V38: =$M$11 -> Total | W38: =$K$11 -> Cost | X38: =$L$11 -> Frequency | Y38: =$M$11 -> Total | AA38: =$AA$11 -> Cost | AB38: =$AB$11 -> Frequency | AC38: =$AC$11 -> Total
A39: ='Break Down Per Community'!B14 -> Procurement for HPV Sampling | B39: ='Break Down Per Community'!C14 -> 1500 | C39: ='Break Down Per Community'!D14 -> 2000 | D39: =B39*C39 -> 3000000 | E39: =B39 -> 1500 | F39: =C39 -> 2000 | G39: =D39 -> 3000000 | H39: =E39 -> 1500 | I39: =F39 -> 2000 | J39: =G39 -> 3000000 | K39: =H39 -> 1500 | L39: =I39 -> 2000 | ... Y39: =V39 -> 3000000 | AA39: =SUM(B39,E39,H39,K39,N39,Q39,T39,W39) -> 12000 | AB39: =SUM(C39,F39,I39,L39,O39,R39,U39,X39) -> 16000 | AC39: =SUM(D39,G39,J39,M39,P39,S39,V39,Y39) -> 24000000
A40: ='Break Down Per Community'!B15 -> Labotory Analysis | B40: ='Break Down Per Community'!C15 -> 7822.5 | C40: ='Break Down Per Community'!D15 -> 2000 | D40: =B40*C40 -> 15645000 | E40: =B40 -> 7822.5 | F40: =C40 -> 2000 | G40: =D40 -> 15645000 | H40: =E40 -> 7822.5 | I40: =F40 -> 2000 | J40: =G40 -> 15645000 | K40: =H40 -> 7822.5 | L40: =I40 -> 2000 | ... Y40: =V40 -> 15645000 | AA40: =SUM(B40,E40,H40,K40,N40,Q40,T40,W40) -> 62580 | AB40: =SUM(C40,F40,I40,L40,O40,R40,U40,X40) -> 16000 | AC40: =SUM(D40,G40,J40,M40,P40,S40,V40,Y40) -> 125160000
A41: ='Break Down Per Community'!B16 -> Gynescope | B41: ='Break Down Per Community'!C16 -> 11250 | C41: ='Break Down Per Community'!D16 -> 2000 | D41: =B41*C41 -> 22500000 | E41: =B41 -> 11250 | F41: =C41 -> 2000 | G41: =D41 -> 22500000 | H41: =E41 -> 11250 | I41: =F41 -> 2000 | J41: =G41 -> 22500000 | K41: =H41 -> 11250 | L41: =I41 -> 2000 | ... Y41: =V41 -> 22500000 | AA41: =SUM(B41,E41,H41,K41,N41,Q41,T41,W41) -> 90000 | AB41: =SUM(C41,F41,I41,L41,O41,R41,U41,X41) -> 16000 | AC41: =SUM(D41,G41,J41,M41,P41,S41,V41,Y41) -> 180000000
A42: ='Break Down Per Community'!B17 -> Medical Supply and consumables | B42: ='Break Down Per Community'!C17 -> 2250 | C42: ='Break Down Per Community'!D17 -> 2000 | D42: =B42*C42 -> 4500000 | E42: =B42 -> 2250 | F42: =C42 -> 2000 | G42: =D42 -> 4500000 | H42: =E42 -> 2250 | I42: =F42 -> 2000 | J42: =G42 -> 4500000 | K42: =H42 -> 2250 | L42: =I42 -> 2000 | ... Y42: =V42 -> 4500000 | AA42: =SUM(B42,E42,H42,K42,N42,Q42,T42,W42) -> 18000 | AB42: =SUM(C42,F42,I42,L42,O42,R42,U42,X42) -> 16000 | AC42: =SUM(D42,G42,J42,M42,P42,S42,V42,Y42) -> 36000000
D43: =B43*C43 -> 0 | E43: =B43 -> 0 | F43: =C43 -> 0 | G43: =D43 -> 0 | H43: =E43 -> 0 | I43: =F43 -> 0 | J43: =G43 -> 0 | K43: =H43 -> 0 | L43: =I43 -> 0 | ... Y43: =V43 -> 0 | AA43: =SUM(B43,E43,H43,K43,N43,Q43,T43,W43) -> 0 | AB43: =SUM(C43,F43,I43,L43,O43,R43,U43,X43) -> 0 | AC43: =SUM(D43,G43,J43,M43,P43,S43,V43,Y43) -> 0
D44: =B44*C44 -> 0 | E44: =B44 -> 0 | F44: =C44 -> 0 | G44: =D44 -> 0 | H44: =E44 -> 0 | I44: =F44 -> 0 | J44: =G44 -> 0 | K44: =H44 -> 0 | L44: =I44 -> 0 | ... Y44: =V44 -> 0 | AA44: =SUM(B44,E44,H44,K44,N44,Q44,T44,W44) -> 0 | AB44: =SUM(C44,F44,I44,L44,O44,R44,U44,X44) -> 0 | AC44: =SUM(D44,G44,J44,M44,P44,S44,V44,Y44) -> 0
A45: ="Total "&A38 -> Total Equipment and Supplies | B45: =SUM(B39:B44) -> 22822.5 | C45: =SUM(C39:C44) -> 8000 | D45: =SUM(D39:D44) -> 45645000 | E45: =SUM(E39:E44) -> 22822.5 | F45: =SUM(F39:F44) -> 8000 | G45: =SUM(G39:G44) -> 45645000 | H45: =SUM(H39:H44) -> 22822.5 | I45: =SUM(I39:I44) -> 8000 | ... Y45: =SUM(Y39:Y44) -> 45645000 | AA45: =SUM(AA39:AA44) -> 182580 | AB45: =SUM(C45,F45,I45,L45,IF($J$7=5,O45,0)) -> 32000 | AC45: =SUM(AC39:AC44) -> 365160000
A47: ='Total '!B9 -> Training and Educaton | B47: =$B$11 -> Cost | C47: =$C$11 -> Frequency | D47: =$D$11 -> Total | E47: =$E$11 -> Cost | F47: =$F$11 -> Frequency | G47: =$G$11 -> Total | H47: =$H$11 -> Cost | I47: =$I$11 -> Frequency | J47: =J38 -> Total | K47: =$K$11 -> Cost | L47: =$L$11 -> Frequency | M47: =M38 -> Total | N47: =$K$11 -> Cost | O47: =$L$11 -> Frequency | P47: =P38 -> Total | Q47: =$H$11 -> Cost | R47: =$I$11 -> Frequency | S47: =S38 -> Total | T47: =$K$11 -> Cost | U47: =$L$11 -> Frequency | V47: =V38 -> Total | W47: =$K$11 -> Cost | X47: =$L$11 -> Frequency | Y47: =Y38 -> Total | AA47: =$AA$11 -> Cost | AB47: =$AB$11 -> Frequency | AC47: =$AC$11 -> Total
A48: ='Break Down Per Community'!B23 -> Training Programs | B48: ='Break Down Per Community'!C23 -> 570000 | C48: ='Break Down Per Community'!D23 -> 1 | D48: =B48*C48 -> 570000 | E48: =B48 -> 570000 | F48: =C48 -> 1 | G48: =D48 -> 570000 | H48: =E48 -> 570000 | I48: =F48 -> 1 | J48: =G48 -> 570000 | K48: =H48 -> 570000 | L48: =I48 -> 1 | ... Y48: =V48 -> 570000 | AA48: =SUM(B48,E48,H48,K48,N48,Q48,T48,W48) -> 4560000 | AB48: =SUM(C48,F48,I48,L48,O48,R48,U48,X48) -> 8 | AC48: =SUM(D48,G48,J48,M48,P48,S48,V48,Y48) -> 4560000
A49: ='Break Down Per Community'!B24 -> Education Materials | B49: ='Break Down Per Community'!C24 -> 0 | C49: ='Break Down Per Community'!D24 -> 1 | D49: =B49*C49 -> 0 | E49: =B49 -> 0 | F49: =C49 -> 1 | G49: =D49 -> 0 | H49: =E49 -> 0 | I49: =F49 -> 1 | J49: =G49 -> 0 | K49: =H49 -> 0 | L49: =I49 -> 1 | ... Y49: =V49 -> 0 | AA49: =SUM(B49,E49,H49,K49,N49,Q49,T49,W49) -> 0 | AB49: =SUM(C49,F49,I49,L49,O49,R49,U49,X49) -> 8 | AC49: =SUM(D49,G49,J49,M49,P49,S49,V49,Y49) -> 0
D50: =B50*C50 -> 0 | E50: =B50 -> 0 | F50: =C50 -> 0 | G50: =D50 -> 0 | H50: =E50 -> 0 | I50: =F50 -> 0 | J50: =G50 -> 0 | K50: =H50 -> 0 | L50: =I50 -> 0 | ... Y50: =V50 -> 0 | AA50: =SUM(B50,E50,H50,K50,N50,Q50,T50,W50) -> 0 | AB50: =SUM(C50,F50,I50,L50,O50,R50,U50,X50) -> 0 | AC50: =SUM(D50,G50,J50,M50,P50,S50,V50,Y50) -> 0
D51: =B51*C51 -> 0 | E51: =B51 -> 0 | F51: =C51 -> 0 | G51: =D51 -> 0 | H51: =E51 -> 0 | I51: =F51 -> 0 | J51: =G51 -> 0 | K51: =H51 -> 0 | L51: =I51 -> 0 | ... Y51: =V51 -> 0 | AA51: =SUM(B51,E51,H51,K51,N51,Q51,T51,W51) -> 0 | AB51: =SUM(C51,F51,I51,L51,O51,R51,U51,X51) -> 0 | AC51: =SUM(D51,G51,J51,M51,P51,S51,V51,Y51) -> 0
D52: =B52*C52 -> 0 | E52: =B52 -> 0 | F52: =C52 -> 0 | G52: =D52 -> 0 | H52: =E52 -> 0 | I52: =F52 -> 0 | J52: =G52 -> 0 | K52: =H52 -> 0 | L52: =I52 -> 0 | ... Y52: =V52 -> 0 | AA52: =SUM(B52,E52,H52,K52,N52,Q52,T52,W52) -> 0 | AB52: =SUM(C52,F52,I52,L52,O52,R52,U52,X52) -> 0 | AC52: =SUM(D52,G52,J52,M52,P52,S52,V52,Y52) -> 0
D53: =B53*C53 -> 0 | E53: =B53 -> 0 | F53: =C53 -> 0 | G53: =D53 -> 0 | H53: =E53 -> 0 | I53: =F53 -> 0 | J53: =G53 -> 0 | K53: =H53 -> 0 | L53: =I53 -> 0 | ... Y53: =V53 -> 0 | AA53: =SUM(B53,E53,H53,K53,N53,Q53,T53,W53) -> 0 | AB53: =SUM(C53,F53,I53,L53,O53,R53,U53,X53) -> 0 | AC53: =SUM(D53,G53,J53,M53,P53,S53,V53,Y53) -> 0
A54: ="Total "&A47 -> Total Training and Educaton | B54: =SUM(B48:B53) -> 570000 | C54: =SUM(C48:C53) -> 2 | D54: =SUM(D48:D53) -> 570000 | E54: =SUM(E48:E53) -> 570000 | F54: =SUM(F48:F53) -> 2 | G54: =SUM(G48:G53) -> 570000 | H54: =SUM(H48:H53) -> 570000 | I54: =SUM(I48:I53) -> 2 | ... Y54: =SUM(Y48:Y53) -> 570000 | AA54: =SUM(AA48:AA53) -> 4560000 | AB54: =SUM(C54,F54,I54,L54,IF($J$7=5,O54,0)) -> 8 | AC54: =SUM(AC48:AC53) -> 4560000
A56: ='Total '!B10 -> Outreach and Mobilization | B56: =$B$11 -> Cost | C56: =$C$11 -> Frequency | D56: =$D$11 -> Total | E56: =$E$11 -> Cost | F56: =$F$11 -> Frequency | G56: Total | H56: =$H$11 -> Cost | I56: =$I$11 -> Frequency | J56: =J47 -> Total | K56: =$K$11 -> Cost | L56: =$L$11 -> Frequency | M56: =M47 -> Total | N56: =$K$11 -> Cost | O56: =$L$11 -> Frequency | P56: =P47 -> Total | Q56: =$H$11 -> Cost | R56: =$I$11 -> Frequency | S56: =S47 -> Total | T56: =$K$11 -> Cost | U56: =$L$11 -> Frequency | V56: =V47 -> Total | W56: =$K$11 -> Cost | X56: =$L$11 -> Frequency | Y56: =Y47 -> Total | AA56: =$AA$11 -> Cost | AB56: =$AB$11 -> Frequency | AC56: =$AC$11 -> Total
A57: ='Break Down Per Community'!B32 -> Community Engagement | B57: ='Break Down Per Community'!C32 -> 200000 | C57: ='Break Down Per Community'!D32 -> 10 | D57: =B57*C57 -> 2000000 | E57: =B57 -> 200000 | F57: =C57 -> 10 | G57: =D57 -> 2000000 | H57: =E57 -> 200000 | I57: =F57 -> 10 | J57: =G57 -> 2000000 | K57: =H57 -> 200000 | L57: =I57 -> 10 | ... Y57: =V57 -> 2000000 | AA57: =SUM(B57,E57,H57,K57,N57,Q57,T57,W57) -> 1600000 | AB57: =SUM(C57,F57,I57,L57,O57,R57,U57,X57) -> 80 | AC57: =SUM(D57,G57,J57,M57,P57,S57,V57,Y57) -> 16000000
A58: ='Break Down Per Community'!B33 -> Transportation and Logistics for the devices | B58: ='Break Down Per Community'!C33 -> 1000000 | C58: ='Break Down Per Community'!D33 -> 1 | D58: =B58*C58 -> 1000000 | E58: =B58 -> 1000000 | F58: =C58 -> 1 | G58: =D58 -> 1000000 | H58: =E58 -> 1000000 | I58: =F58 -> 1 | J58: =G58 -> 1000000 | K58: =H58 -> 1000000 | L58: =I58 -> 1 | ... Y58: =V58 -> 1000000 | AA58: =SUM(B58,E58,H58,K58,N58,Q58,T58,W58) -> 8000000 | AB58: =SUM(C58,F58,I58,L58,O58,R58,U58,X58) -> 8 | AC58: =SUM(D58,G58,J58,M58,P58,S58,V58,Y58) -> 8000000
A59: ='Break Down Per Community'!B34 -> Radio Ad | B59: ='Break Down Per Community'!C34 -> 500000 | C59: ='Break Down Per Community'!D34 -> 1 | D59: =B59*C59 -> 500000 | E59: =B59 -> 500000 | F59: =C59 -> 1 | G59: =D59 -> 500000 | H59: =E59 -> 500000 | I59: =F59 -> 1 | J59: =G59 -> 500000 | K59: =H59 -> 500000 | L59: =I59 -> 1 | ... Y59: =V59 -> 500000 | AA59: =SUM(B59,E59,H59,K59,N59,Q59,T59,W59) -> 4000000 | AB59: =SUM(C59,F59,I59,L59,O59,R59,U59,X59) -> 8 | AC59: =SUM(D59,G59,J59,M59,P59,S59,V59,Y59) -> 4000000
A60: ='Break Down Per Community'!B35 -> Content Creation & Social Media Promotions | B60: ='Break Down Per Community'!C35 -> 400000 | C60: ='Break Down Per Community'!D35 -> 1 | D60: =B60*C60 -> 400000 | E60: =B60 -> 400000 | F60: =C60 -> 1 | G60: =D60 -> 400000 | H60: =E60 -> 400000 | I60: =F60 -> 1 | J60: =G60 -> 400000 | K60: =H60 -> 400000 | L60: =I60 -> 1 | ... Y60: =V60 -> 400000 | AA60: =SUM(B60,E60,H60,K60,N60,Q60,T60,W60) -> 3200000 | AB60: =SUM(C60,F60,I60,L60,O60,R60,U60,X60) -> 8 | AC60: =SUM(D60,G60,J60,M60,P60,S60,V60,Y60) -> 3200000
A61: ='Break Down Per Community'!B36 -> Brochures, Flyers and Posters | B61: ='Break Down Per Community'!C36 -> 1000000 | C61: ='Break Down Per Community'!D36 -> 1 | D61: =B61*C61 -> 1000000 | E61: =B61 -> 1000000 | F61: =C61 -> 1 | G61: =D61 -> 1000000 | H61: =E61 -> 1000000 | I61: =F61 -> 1 | J61: =G61 -> 1000000 | K61: =H61 -> 1000000 | L61: =I61 -> 1 | ... Y61: =V61 -> 1000000 | AA61: =SUM(B61,E61,H61,K61,N61,Q61,T61,W61) -> 8000000 | AB61: =SUM(C61,F61,I61,L61,O61,R61,U61,X61) -> 8 | AC61: =SUM(D61,G61,J61,M61,P61,S61,V61,Y61) -> 8000000
A62: ='Break Down Per Community'!B37 -> Souvenirs | B62: ='Break Down Per Community'!C37 -> 1500 | C62: ='Break Down Per Community'!D37 -> 2000 | D62: =B62*C62 -> 3000000 | E62: =B62 -> 1500 | F62: =C62 -> 2000 | G62: =D62 -> 3000000 | H62: =E62 -> 1500 | I62: =F62 -> 2000 | J62: =G62 -> 3000000 | K62: =H62 -> 1500 | L62: =I62 -> 2000 | ... Y62: =V62 -> 3000000 | AA62: =SUM(B62,E62,H62,K62,N62,Q62,T62,W62) -> 12000 | AB62: =SUM(C62,F62,I62,L62,O62,R62,U62,X62) -> 16000 | AC62: =SUM(D62,G62,J62,M62,P62,S62,V62,Y62) -> 24000000
D63: =B63*C63 -> 0 | E63: =B63 -> 0 | F63: =C63 -> 0 | G63: =D63 -> 0 | H63: =E63 -> 0 | I63: =F63 -> 0 | J63: =G63 -> 0 | K63: =H63 -> 0 | L63: =I63 -> 0 | ... Y63: =V63 -> 0 | AA63: =SUM(B63,E63,H63,K63,N63,Q63,T63,W63) -> 0 | AB63: =SUM(C63,F63,I63,L63,O63,R63,U63,X63) -> 0 | AC63: =SUM(D63,G63,J63,M63,P63,S63,V63,Y63) -> 0
A64: ="Total "&A56 -> Total Outreach and Mobilization | B64: =SUM(B57:B63) -> 3101500 | C64: =SUM(C57:C63) -> 2014 | D64: =SUM(D57:D63) -> 7900000 | E64: =SUM(E57:E63) -> 3101500 | F64: =SUM(F57:F63) -> 2014 | G64: =SUM(G57:G63) -> 7900000 | H64: =SUM(H57:H63) -> 3101500 | I64: =SUM(I57:I63) -> 2014 | ... Y64: =SUM(Y57:Y63) -> 7900000 | AA64: =SUM(AA57:AA63) -> 24812000 | AB64: =SUM(C64,F64,I64,L64,IF($J$7=5,O64,0)) -> 8056 | AC64: =SUM(AC57:AC63) -> 63200000
A66: ='Total '!B11 -> Facilities and Infrastructure | B66: =$B$11 -> Cost | C66: =$C$11 -> Frequency | D66: =$D$11 -> Total | E66: =$E$11 -> Cost | F66: =$F$11 -> Frequency | G66: =$G$11 -> Total | H66: =$H$11 -> Cost | I66: =$I$11 -> Frequency | J66: Total | K66: =$K$11 -> Cost | L66: =$L$11 -> Frequency | M66: =M56 -> Total | N66: =$K$11 -> Cost | O66: =$L$11 -> Frequency | P66: =P56 -> Total | Q66: =$H$11 -> Cost | R66: =$I$11 -> Frequency | S66: =S56 -> Total | T66: =$K$11 -> Cost | U66: =$L$11 -> Frequency | V66: =V56 -> Total | W66: =$K$11 -> Cost | X66: =$L$11 -> Frequency | Y66: =Y56 -> Total | AA66: =$AA$11 -> Cost | AB66: =$AB$11 -> Frequency | AC66: =$AC$11 -> Total
A67: ='Break Down Per Community'!B42 -> Renovation and Construction | B67: ='Break Down Per Community'!C42 -> 0 | C67: ='Break Down Per Community'!D42 -> 1 | D67: =B67*C67 -> 0 | E67: =B67 -> 0 | F67: =C67 -> 1 | G67: =D67 -> 0 | H67: =E67 -> 0 | I67: =F67 -> 1 | J67: =G67 -> 0 | K67: =H67 -> 0 | L67: =I67 -> 1 | ... Y67: =V67 -> 0 | AA67: =SUM(B67,E67,H67,K67,N67,Q67,T67,W67) -> 0 | AB67: =SUM(C67,F67,I67,L67,O67,R67,U67,X67) -> 8 | AC67: =SUM(D67,G67,J67,M67,P67,S67,V67,Y67) -> 0
A68: ='Break Down Per Community'!B43 -> Furnitures and Fittings | B68: ='Break Down Per Community'!C43 -> 120000 | C68: ='Break Down Per Community'!D43 -> 2 | D68: =B68*C68 -> 240000 | E68: =B68 -> 120000 | F68: =C68 -> 2 | G68: =D68 -> 240000 | H68: =E68 -> 120000 | I68: =F68 -> 2 | J68: =G68 -> 240000 | K68: =H68 -> 120000 | L68: =I68 -> 2 | ... Y68: =V68 -> 240000 | AA68: =SUM(B68,E68,H68,K68,N68,Q68,T68,W68) -> 960000 | AB68: =SUM(C68,F68,I68,L68,O68,R68,U68,X68) -> 16 | AC68: =SUM(D68,G68,J68,M68,P68,S68,V68,Y68) -> 1920000
D69: =B69*C69 -> 0 | E69: =B69 -> 0 | F69: =C69 -> 0 | G69: =D69 -> 0 | H69: =E69 -> 0 | I69: =F69 -> 0 | J69: =G69 -> 0 | K69: =H69 -> 0 | L69: =I69 -> 0 | ... Y69: =V69 -> 0 | AA69: =SUM(B69,E69,H69,K69,N69,Q69,T69,W69) -> 0 | AB69: =SUM(C69,F69,I69,L69,O69,R69,U69,X69) -> 0 | AC69: =SUM(D69,G69,J69,M69,P69,S69,V69,Y69) -> 0
D70: =B70*C70 -> 0 | E70: =B70 -> 0 | F70: =C70 -> 0 | G70: =D70 -> 0 | H70: =E70 -> 0 | I70: =F70 -> 0 | J70: =G70 -> 0 | K70: =H70 -> 0 | L70: =I70 -> 0 | ... Y70: =V70 -> 0 | AA70: =SUM(B70,E70,H70,K70,N70,Q70,T70,W70) -> 0 | AB70: =SUM(C70,F70,I70,L70,O70,R70,U70,X70) -> 0 | AC70: =SUM(D70,G70,J70,M70,P70,S70,V70,Y70) -> 0
D71: =B71*C71 -> 0 | E71: =B71 -> 0 | F71: =C71 -> 0 | G71: =D71 -> 0 | H71: =E71 -> 0 | I71: =F71 -> 0 | J71: =G71 -> 0 | K71: =H71 -> 0 | L71: =I71 -> 0 | ... Y71: =V71 -> 0 | AA71: =SUM(B71,E71,H71,K71,N71,Q71,T71,W71) -> 0 | AB71: =SUM(C71,F71,I71,L71,O71,R71,U71,X71) -> 0 | AC71: =SUM(D71,G71,J71,M71,P71,S71,V71,Y71) -> 0
D72: =B72*C72 -> 0 | E72: =B72 -> 0 | F72: =C72 -> 0 | G72: =D72 -> 0 | H72: =E72 -> 0 | I72: =F72 -> 0 | J72: =G72 -> 0 | K72: =H72 -> 0 | L72: =I72 -> 0 | ... Y72: =V72 -> 0 | AA72: =SUM(B72,E72,H72,K72,N72,Q72,T72,W72) -> 0 | AB72: =SUM(C72,F72,I72,L72,O72,R72,U72,X72) -> 0 | AC72: =SUM(D72,G72,J72,M72,P72,S72,V72,Y72) -> 0
A73: ="Total "&A66 -> Total Facilities and Infrastructure | B73: =SUM(B67:B72) -> 120000 | C73: =SUM(C67:C72) -> 3 | D73: =SUM(D67:D72) -> 240000 | E73: =SUM(E67:E72) -> 120000 | F73: =SUM(F67:F72) -> 3 | G73: =SUM(G67:G72) -> 240000 | H73: =SUM(H67:H72) -> 120000 | I73: =SUM(I67:I72) -> 3 | ... Y73: =SUM(Y67:Y72) -> 240000 | AA73: =SUM(AA67:AA72) -> 960000 | AB73: =SUM(C73,F73,I73,L73,IF($J$7=5,O73,0)) -> 12 | AC73: =SUM(AC67:AC72) -> 1920000
A75: ='Total '!B12 -> Monitoring and Evaluation | B75: =$B$11 -> Cost | C75: =$C$11 -> Frequency | D75: =$D$11 -> Total | E75: =$E$11 -> Cost | F75: =$F$11 -> Frequency | G75: =G66 -> Total | H75: =$H$11 -> Cost | I75: =$I$11 -> Frequency | J75: =J66 -> Total | K75: =$K$11 -> Cost | L75: =$L$11 -> Frequency | M75: =M66 -> Total | N75: =$K$11 -> Cost | O75: =$L$11 -> Frequency | P75: =P66 -> Total | Q75: =$H$11 -> Cost | R75: =$I$11 -> Frequency | S75: =S66 -> Total | T75: =$K$11 -> Cost | U75: =$L$11 -> Frequency | V75: =V66 -> Total | W75: =$K$11 -> Cost | X75: =$L$11 -> Frequency | Y75: =Y66 -> Total | AA75: =$AA$11 -> Cost | AB75: =$AB$11 -> Frequency | AC75: =$AC$11 -> Total
A76: ='Break Down Per Community'!G3 -> Data Collection and Analysis | B76: ='Break Down Per Community'!H3 -> 0 | C76: ='Break Down Per Community'!I3 -> 1 | D76: =B76*C76 -> 0 | E76: =B76 -> 0 | F76: =C76 -> 1 | G76: =D76 -> 0 | H76: =E76 -> 0 | I76: =F76 -> 1 | J76: =G76 -> 0 | K76: =H76 -> 0 | L76: =I76 -> 1 | ... Y76: =V76 -> 0 | AA76: =SUM(B76,E76,H76,K76,N76,Q76,T76,W76) -> 0 | AB76: =SUM(C76,F76,I76,L76,O76,R76,U76,X76) -> 8 | AC76: =SUM(D76,G76,J76,M76,P76,S76,V76,Y76) -> 0
A77: ='Break Down Per Community'!G4 -> Evaluation Studies | B77: ='Break Down Per Community'!H4 -> 0 | C77: ='Break Down Per Community'!I4 -> 1 | D77: =B77*C77 -> 0 | E77: =B77 -> 0 | F77: =C77 -> 1 | G77: =D77 -> 0 | H77: =E77 -> 0 | I77: =F77 -> 1 | J77: =G77 -> 0 | K77: =H77 -> 0 | L77: =I77 -> 1 | ... Y77: =V77 -> 0 | AA77: =SUM(B77,E77,H77,K77,N77,Q77,T77,W77) -> 0 | AB77: =SUM(C77,F77,I77,L77,O77,R77,U77,X77) -> 8 | AC77: =SUM(D77,G77,J77,M77,P77,S77,V77,Y77) -> 0
A78: ='Break Down Per Community'!G5 -> IT Infrastructure and Data Management | B78: ='Break Down Per Community'!H5 -> 0 | C78: ='Break Down Per Community'!I5 -> 1 | D78: =B78*C78 -> 0 | E78: =B78 -> 0 | F78: =C78 -> 1 | G78: =D78 -> 0 | H78: =E78 -> 0 | I78: =F78 -> 1 | J78: =G78 -> 0 | K78: =H78 -> 0 | L78: =I78 -> 1 | ... Y78: =V78 -> 0 | AA78: =SUM(B78,E78,H78,K78,N78,Q78,T78,W78) -> 0 | AB78: =SUM(C78,F78,I78,L78,O78,R78,U78,X78) -> 8 | AC78: =SUM(D78,G78,J78,M78,P78,S78,V78,Y78) -> 0
A79: ='Break Down Per Community'!G6 -> Portable Tablets | B79: ='Break Down Per Community'!H6 -> 200000 | C79: ='Break Down Per Community'!I6 -> 2 | D79: =B79*C79 -> 400000 | E79: =B79 -> 200000 | F79: =C79 -> 2 | G79: =D79 -> 400000 | H79: =E79 -> 200000 | I79: =F79 -> 2 | J79: =G79 -> 400000 | K79: =H79 -> 200000 | L79: =I79 -> 2 | ... Y79: =V79 -> 400000 | AA79: =SUM(B79,E79,H79,K79,N79,Q79,T79,W79) -> 1600000 | AB79: =SUM(C79,F79,I79,L79,O79,R79,U79,X79) -> 16 | AC79: =SUM(D79,G79,J79,M79,P79,S79,V79,Y79) -> 3200000
A80: ='Break Down Per Community'!G7 -> Laptop | B80: ='Break Down Per Community'!H7 -> 300000 | C80: ='Break Down Per Community'!I7 -> 1 | D80: =B80*C80 -> 300000 | E80: =B80 -> 300000 | F80: =C80 -> 1 | G80: =D80 -> 300000 | H80: =E80 -> 300000 | I80: =F80 -> 1 | J80: =G80 -> 300000 | K80: =H80 -> 300000 | L80: =I80 -> 1 | ... Y80: =V80 -> 300000 | AA80: =SUM(B80,E80,H80,K80,N80,Q80,T80,W80) -> 2400000 | AB80: =SUM(C80,F80,I80,L80,O80,R80,U80,X80) -> 8 | AC80: =SUM(D80,G80,J80,M80,P80,S80,V80,Y80) -> 2400000
A81: ='Break Down Per Community'!G8 -> Projector and white screen | B81: ='Break Down Per Community'!H8 -> 400000 | C81: ='Break Down Per Community'!I8 -> 1 | D81: =B81*C81 -> 400000 | E81: =B81 -> 400000 | F81: =C81 -> 1 | G81: =D81 -> 400000 | H81: =E81 -> 400000 | I81: =F81 -> 1 | J81: =G81 -> 400000 | K81: =H81 -> 400000 | L81: =I81 -> 1 | ... Y81: =V81 -> 400000 | AA81: =SUM(B81,E81,H81,K81,N81,Q81,T81,W81) -> 3200000 | AB81: =SUM(C81,F81,I81,L81,O81,R81,U81,X81) -> 8 | AC81: =SUM(D81,G81,J81,M81,P81,S81,V81,Y81) -> 3200000
A82: ='Break Down Per Community'!G9 -> Internet Routers and Subsription | B82: ='Break Down Per Community'!H9 -> 30000 | C82: ='Break Down Per Community'!I9 -> 3 | D82: =B82*C82 -> 90000 | E82: =B82 -> 30000 | F82: =C82 -> 3 | G82: =D82 -> 90000 | H82: =E82 -> 30000 | I82: =F82 -> 3 | J82: =G82 -> 90000 | K82: =H82 -> 30000 | L82: =I82 -> 3 | ... Y82: =V82 -> 90000 | AA82: =SUM(B82,E82,H82,K82,N82,Q82,T82,W82) -> 240000 | AB82: =SUM(C82,F82,I82,L82,O82,R82,U82,X82) -> 24 | AC82: =SUM(D82,G82,J82,M82,P82,S82,V82,Y82) -> 720000
A83: ='Break Down Per Community'!G10 -> Back Up Power Supply and Mini Inverters | B83: ='Break Down Per Community'!H10 -> 219000 | C83: ='Break Down Per Community'!I10 -> 3 | D83: =B83*C83 -> 657000 | E83: =B83 -> 219000 | F83: =C83 -> 3 | G83: =D83 -> 657000 | H83: =E83 -> 219000 | I83: =F83 -> 3 | J83: =G83 -> 657000 | K83: =H83 -> 219000 | L83: =I83 -> 3 | ... Y83: =V83 -> 657000 | AA83: =SUM(B83,E83,H83,K83,N83,Q83,T83,W83) -> 1752000 | AB83: =SUM(C83,F83,I83,L83,O83,R83,U83,X83) -> 24 | AC83: =SUM(D83,G83,J83,M83,P83,S83,V83,Y83) -> 5256000
A84: ="Total "&A75 -> Total Monitoring and Evaluation | B84: =SUM(B76:B83) -> 1149000 | C84: =SUM(C76:C83) -> 13 | D84: =SUM(D76:D83) -> 1847000 | E84: =SUM(E76:E83) -> 1149000 | F84: =SUM(F76:F83) -> 13 | G84: =SUM(G76:G83) -> 1847000 | H84: =SUM(H76:H83) -> 1149000 | I84: =SUM(I76:I83) -> 13 | ... Y84: =SUM(Y76:Y83) -> 1847000 | AA84: =SUM(AA76:AA83) -> 9192000 | AB84: =SUM(C84,F84,I84,L84,IF($J$7=5,O84,0)) -> 52 | AC84: =SUM(AC76:AC83) -> 14776000
A86: ='Total '!B13 -> Administrative and Overhead Costs | B86: =$B$11 -> Cost | C86: =$C$11 -> Frequency | D86: =$D$11 -> Total | E86: =$E$11 -> Cost | F86: =$F$11 -> Frequency | G86: =G75 -> Total | H86: =$H$11 -> Cost | I86: =$I$11 -> Frequency | J86: =J75 -> Total | K86: =$K$11 -> Cost | L86: =$L$11 -> Frequency | M86: =M75 -> Total | N86: =$K$11 -> Cost | O86: =$L$11 -> Frequency | P86: =P75 -> Total | Q86: =$H$11 -> Cost | R86: =$I$11 -> Frequency | S86: =S75 -> Total | T86: =$K$11 -> Cost | U86: =$L$11 -> Frequency | V86: =V75 -> Total | W86: =$K$11 -> Cost | X86: =$L$11 -> Frequency | Y86: =Y75 -> Total | AA86: =$AA$11 -> Cost | AB86: =$AB$11 -> Frequency | AC86: =$AC$11 -> Total
A87: ='Break Down Per Community'!G14 -> Rent | B87: ='Break Down Per Community'!H14 -> 500000 | C87: ='Break Down Per Community'!I14 -> 1 | D87: =B87*C87 -> 500000 | E87: =B87 -> 500000 | F87: =C87 -> 1 | G87: =D87 -> 500000 | H87: =E87 -> 500000 | I87: =F87 -> 1 | J87: =G87 -> 500000 | K87: =H87 -> 500000 | L87: =I87 -> 1 | ... Y87: =V87 -> 500000 | AA87: =SUM(B87,E87,H87,K87,N87,Q87,T87,W87) -> 4000000 | AB87: =SUM(C87,F87,I87,L87,O87,R87,U87,X87) -> 8 | AC87: =SUM(D87,G87,J87,M87,P87,S87,V87,Y87) -> 4000000
A88: ='Break Down Per Community'!G15 -> Utilities | B88: ='Break Down Per Community'!H15 -> 150000 | C88: ='Break Down Per Community'!I15 -> 1 | D88: =B88*C88 -> 150000 | E88: =B88 -> 150000 | F88: =C88 -> 1 | G88: =D88 -> 150000 | H88: =E88 -> 150000 | I88: =F88 -> 1 | J88: =G88 -> 150000 | K88: =H88 -> 150000 | L88: =I88 -> 1 | ... Y88: =V88 -> 150000 | AA88: =SUM(B88,E88,H88,K88,N88,Q88,T88,W88) -> 1200000 | AB88: =SUM(C88,F88,I88,L88,O88,R88,U88,X88) -> 8 | AC88: =SUM(D88,G88,J88,M88,P88,S88,V88,Y88) -> 1200000
A89: ='Break Down Per Community'!G16 -> Inverter Maintenance | B89: ='Break Down Per Community'!H16 -> 0 | C89: ='Break Down Per Community'!I16 -> 1 | D89: =B89*C89 -> 0 | E89: =B89 -> 0 | F89: =C89 -> 1 | G89: =D89 -> 0 | H89: =E89 -> 0 | I89: =F89 -> 1 | J89: =G89 -> 0 | K89: =H89 -> 0 | L89: =I89 -> 1 | ... Y89: =V89 -> 0 | AA89: =SUM(B89,E89,H89,K89,N89,Q89,T89,W89) -> 0 | AB89: =SUM(C89,F89,I89,L89,O89,R89,U89,X89) -> 8 | AC89: =SUM(D89,G89,J89,M89,P89,S89,V89,Y89) -> 0
A90: ='Break Down Per Community'!G17 -> Communication | B90: ='Break Down Per Community'!H17 -> 150000 | C90: ='Break Down Per Community'!I17 -> 1 | D90: =B90*C90 -> 150000 | E90: =B90 -> 150000 | F90: =C90 -> 1 | G90: =D90 -> 150000 | H90: =E90 -> 150000 | I90: =F90 -> 1 | J90: =G90 -> 150000 | K90: =H90 -> 150000 | L90: =I90 -> 1 | ... Y90: =V90 -> 150000 | AA90: =SUM(B90,E90,H90,K90,N90,Q90,T90,W90) -> 1200000 | AB90: =SUM(C90,F90,I90,L90,O90,R90,U90,X90) -> 8 | AC90: =SUM(D90,G90,J90,M90,P90,S90,V90,Y90) -> 1200000
A91: ='Break Down Per Community'!G18 -> Stationeries | B91: ='Break Down Per Community'!H18 -> 500000 | C91: ='Break Down Per Community'!I18 -> 1 | D91: =B91*C91 -> 500000 | E91: =B91 -> 500000 | F91: =C91 -> 1 | G91: =D91 -> 500000 | H91: =E91 -> 500000 | I91: =F91 -> 1 | J91: =G91 -> 500000 | K91: =H91 -> 500000 | L91: =I91 -> 1 | ... Y91: =V91 -> 500000 | AA91: =SUM(B91,E91,H91,K91,N91,Q91,T91,W91) -> 4000000 | AB91: =SUM(C91,F91,I91,L91,O91,R91,U91,X91) -> 8 | AC91: =SUM(D91,G91,J91,M91,P91,S91,V91,Y91) -> 4000000
A92: ='Break Down Per Community'!G19 -> Insurance and Legal Fees | B92: ='Break Down Per Community'!H19 -> 37500 | C92: ='Break Down Per Community'!I19 -> 16 | D92: =B92*C92 -> 600000 | E92: =B92 -> 37500 | F92: =C92 -> 16 | G92: =D92 -> 600000 | H92: =E92 -> 37500 | I92: =F92 -> 16 | J92: =G92 -> 600000 | K92: =H92 -> 37500 | L92: =I92 -> 16 | ... Y92: =V92 -> 600000 | AA92: =SUM(B92,E92,H92,K92,N92,Q92,T92,W92) -> 300000 | AB92: =SUM(C92,F92,I92,L92,O92,R92,U92,X92) -> 128 | AC92: =SUM(D92,G92,J92,M92,P92,S92,V92,Y92) -> 4800000
A93: ="Total "&A86 -> Total Administrative and Overhead Costs | B93: =SUM(B87:B92) -> 1337500 | C93: =SUM(C87:C92) -> 21 | D93: =SUM(D87:D92) -> 1900000 | E93: =SUM(E87:E92) -> 1337500 | F93: =SUM(F87:F92) -> 21 | G93: =SUM(G87:G92) -> 1900000 | H93: =SUM(H87:H92) -> 1337500 | I93: =SUM(I87:I92) -> 21 | ... Y93: =SUM(Y87:Y92) -> 1900000 | AA93: =SUM(AA87:AA92) -> 10700000 | AB93: =SUM(C93,F93,I93,L93,IF($J$7=5,O93,0)) -> 84 | AC93: =SUM(AC87:AC92) -> 15200000
A95: ='Total '!B14 -> Security | B95: =$B$11 -> Cost | C95: =$C$11 -> Frequency | D95: =$D$11 -> Total | E95: =$E$11 -> Cost | F95: =$F$11 -> Frequency | G95: =G86 -> Total | H95: =$H$11 -> Cost | I95: =$I$11 -> Frequency | J95: =J86 -> Total | K95: =$K$11 -> Cost | L95: =$L$11 -> Frequency | M95: =M86 -> Total | N95: =$K$11 -> Cost | O95: =$L$11 -> Frequency | P95: =P86 -> Total | Q95: =$H$11 -> Cost | R95: =$I$11 -> Frequency | S95: =S86 -> Total | T95: =$K$11 -> Cost | U95: =$L$11 -> Frequency | V95: =V86 -> Total | W95: =$K$11 -> Cost | X95: =$L$11 -> Frequency | Y95: =Y86 -> Total | AA95: =$AA$11 -> Cost | AB95: =$AB$11 -> Frequency | AC95: =$AC$11 -> Total
A96: ='Break Down Per Community'!G23 -> Security Personnel | B96: ='Break Down Per Community'!H23 -> 50000 | C96: ='Break Down Per Community'!I23 -> 6 | D96: =B96*C96 -> 300000 | E96: =B96 -> 50000 | F96: =C96 -> 6 | G96: =D96 -> 300000 | H96: =E96 -> 50000 | I96: =F96 -> 6 | J96: =G96 -> 300000 | K96: =H96 -> 50000 | L96: =I96 -> 6 | ... Y96: =V96 -> 300000 | AA96: =SUM(B96,E96,H96,K96,N96,Q96,T96,W96) -> 400000 | AB96: =SUM(C96,F96,I96,L96,O96,R96,U96,X96) -> 48 | AC96: =SUM(D96,G96,J96,M96,P96,S96,V96,Y96) -> 2400000
A97: ='Break Down Per Community'!G24 -> 0 | B97: ='Break Down Per Community'!H24 -> 0 | C97: ='Break Down Per Community'!I24 -> 0 | D97: =B97*C97 -> 0 | E97: =B97 -> 0 | F97: =C97 -> 0 | G97: =D97 -> 0 | H97: =E97 -> 0 | I97: =F97 -> 0 | J97: =G97 -> 0 | K97: =H97 -> 0 | L97: =I97 -> 0 | ... Y97: =V97 -> 0 | AA97: =SUM(B97,E97,H97,K97,N97,Q97,T97,W97) -> 0 | AB97: =SUM(C97,F97,I97,L97,O97,R97,U97,X97) -> 0 | AC97: =SUM(D97,G97,J97,M97,P97,S97,V97,Y97) -> 0
A98: ='Break Down Per Community'!G25 -> 0 | B98: ='Break Down Per Community'!H25 -> 0 | C98: ='Break Down Per Community'!I25 -> 0 | D98: =B98*C98 -> 0 | E98: =B98 -> 0 | F98: =C98 -> 0 | G98: =D98 -> 0 | H98: =E98 -> 0 | I98: =F98 -> 0 | J98: =G98 -> 0 | K98: =H98 -> 0 | L98: =I98 -> 0 | ... Y98: =V98 -> 0 | AA98: =SUM(B98,E98,H98,K98,N98,Q98,T98,W98) -> 0 | AB98: =SUM(C98,F98,I98,L98,O98,R98,U98,X98) -> 0 | AC98: =SUM(D98,G98,J98,M98,P98,S98,V98,Y98) -> 0
A99: ='Break Down Per Community'!G26 -> 0 | B99: ='Break Down Per Community'!H26 -> 0 | C99: ='Break Down Per Community'!I26 -> 0 | D99: =B99*C99 -> 0 | E99: =B99 -> 0 | F99: =C99 -> 0 | G99: =D99 -> 0 | H99: =E99 -> 0 | I99: =F99 -> 0 | J99: =G99 -> 0 | K99: =H99 -> 0 | L99: =I99 -> 0 | ... Y99: =V99 -> 0 | AA99: =SUM(B99,E99,H99,K99,N99,Q99,T99,W99) -> 0 | AB99: =SUM(C99,F99,I99,L99,O99,R99,U99,X99) -> 0 | AC99: =SUM(D99,G99,J99,M99,P99,S99,V99,Y99) -> 0
D100: =B100*C100 -> 0 | E100: =B100 -> 0 | F100: =C100 -> 0 | G100: =D100 -> 0 | H100: =E100 -> 0 | I100: =F100 -> 0 | J100: =G100 -> 0 | K100: =H100 -> 0 | L100: =I100 -> 0 | ... Y100: =V100 -> 0 | AA100: =SUM(B100,E100,H100,K100,N100,Q100,T100,W100) -> 0 | AB100: =SUM(C100,F100,I100,L100,O100,R100,U100,X100) -> 0 | AC100: =SUM(D100,G100,J100,M100,P100,S100,V100,Y100) -> 0
A101: ="Total "&A95 -> Total Security | B101: =SUM(B96:B100) -> 50000 | C101: =SUM(C96:C100) -> 6 | D101: =SUM(D96:D100) -> 300000 | E101: =SUM(E96:E100) -> 50000 | F101: =SUM(F96:F100) -> 6 | G101: =SUM(G96:G100) -> 300000 | H101: =SUM(H96:H100) -> 50000 | I101: =SUM(I96:I100) -> 6 | ... Y101: =SUM(Y96:Y100) -> 300000 | AA101: =SUM(AA96:AA100) -> 400000 | AB101: =SUM(C101,F101,I101,L101,IF($J$7=5,O101,0)) -> 24 | AC101: =SUM(AC96:AC100) -> 2400000
A103: ='Total '!B15 -> Contingency Funds | B103: =$B$11 -> Cost | C103: =$C$11 -> Frequency | D103: =$D$11 -> Total | E103: =$E$11 -> Cost | F103: =$F$11 -> Frequency | G103: =G95 -> Total | H103: =$H$11 -> Cost | I103: =$I$11 -> Frequency | J103: =J95 -> Total | K103: =$K$11 -> Cost | L103: =$L$11 -> Frequency | M103: =M95 -> Total | N103: =$K$11 -> Cost | O103: =$L$11 -> Frequency | P103: =P95 -> Total | Q103: =$H$11 -> Cost | R103: =$I$11 -> Frequency | S103: =S95 -> Total | T103: =$K$11 -> Cost | U103: =$L$11 -> Frequency | V103: =V95 -> Total | W103: =$K$11 -> Cost | X103: =$L$11 -> Frequency | Y103: =Y95 -> Total | AA103: =$AA$11 -> Cost | AB103: =$AB$11 -> Frequency | AC103: =$AC$11 -> Total
A104: ='Break Down Per Community'!G32 -> Emergency Funds | B104: ='Break Down Per Community'!H32 -> 1000000 | C104: ='Break Down Per Community'!I32 -> 1 | D104: =B104*C104 -> 1000000 | E104: =B104 -> 1000000 | F104: =C104 -> 1 | G104: =D104 -> 1000000 | H104: =E104 -> 1000000 | I104: =F104 -> 1 | J104: =G104 -> 1000000 | K104: =H104 -> 1000000 | L104: =I104 -> 1 | ... Y104: =V104 -> 1000000 | AA104: =SUM(B104,E104,H104,K104,N104,Q104,T104,W104) -> 8000000 | AB104: =SUM(C104,F104,I104,L104,O104,R104,U104,X104) -> 8 | AC104: =SUM(D104,G104,J104,M104,P104,S104,V104,Y104) -> 8000000
D105: =B105*C105 -> 0 | E105: =B105 -> 0 | F105: =C105 -> 0 | G105: =D105 -> 0 | H105: =E105 -> 0 | I105: =F105 -> 0 | J105: =G105 -> 0 | K105: =H105 -> 0 | L105: =I105 -> 0 | ... Y105: =V105 -> 0 | AA105: =SUM(B105,E105,H105,K105,N105,Q105,T105,W105) -> 0 | AB105: =SUM(C105,F105,I105,L105,O105,R105,U105,X105) -> 0 | AC105: =SUM(D105,G105,J105,M105,P105,S105,V105,Y105) -> 0
D106: =B106*C106 -> 0 | E106: =B106 -> 0 | F106: =C106 -> 0 | G106: =D106 -> 0 | H106: =E106 -> 0 | I106: =F106 -> 0 | J106: =G106 -> 0 | K106: =H106 -> 0 | L106: =I106 -> 0 | ... Y106: =V106 -> 0 | AA106: =SUM(B106,E106,H106,K106,N106,Q106,T106,W106) -> 0 | AB106: =SUM(C106,F106,I106,L106,O106,R106,U106,X106) -> 0 | AC106: =SUM(D106,G106,J106,M106,P106,S106,V106,Y106) -> 0
D107: =B107*C107 -> 0 | E107: =B107 -> 0 | F107: =C107 -> 0 | G107: =D107 -> 0 | H107: =E107 -> 0 | I107: =F107 -> 0 | J107: =G107 -> 0 | K107: =H107 -> 0 | L107: =I107 -> 0 | ... Y107: =V107 -> 0 | AA107: =SUM(B107,E107,H107,K107,N107,Q107,T107,W107) -> 0 | AB107: =SUM(C107,F107,I107,L107,O107,R107,U107,X107) -> 0 | AC107: =SUM(D107,G107,J107,M107,P107,S107,V107,Y107) -> 0
A108: ="Total "&A103 -> Total Contingency Funds | B108: =SUM(B104:B107) -> 1000000 | C108: =SUM(C104:C107) -> 1 | D108: =SUM(D104:D107) -> 1000000 | E108: =SUM(E104:E107) -> 1000000 | F108: =SUM(F104:F107) -> 1 | G108: =SUM(G104:G107) -> 1000000 | H108: =SUM(H104:H107) -> 1000000 | I108: =SUM(I104:I107) -> 1 | ... Y108: =SUM(Y104:Y107) -> 1000000 | AA108: =SUM(AA104:AA107) -> 8000000 | AB108: =SUM(C108,F108,I108,L108,IF($J$7=5,O108,0)) -> 4 | AC108: =SUM(AC104:AC107) -> 8000000
A110: RECREATION | B110: =$B$11 -> Cost | C110: =$C$11 -> Frequency | D110: =$D$11 -> Total | E110: =$E$11 -> Cost | F110: =$F$11 -> Frequency | G110: =$G$11 -> Total | H110: =$H$11 -> Cost | I110: =$I$11 -> Frequency | J110: =$J$11 -> Total | K110: =$K$11 -> Cost | L110: =$L$11 -> Frequency | M110: =$M$11 -> Total | N110: =$N$11 -> Cost | O110: =$O$11 -> Frequency | P110: =$P$11 -> Total | Q110: =$H$11 -> Cost | R110: =$I$11 -> Frequency | S110: =$J$11 -> Total | T110: =$K$11 -> Cost | U110: =$L$11 -> Frequency | V110: =$M$11 -> Total | W110: =$N$11 -> Cost | X110: =$O$11 -> Frequency | Y110: =$P$11 -> Total | AA110: =$AA$11 -> Cost | AB110: =$AB$11 -> Frequency | AC110: =$AC$11 -> Total
A111: Gym fees | D111: =B111-C111 -> 0 | G111: =E111-F111 -> 0 | J111: =H111-I111 -> 0 | M111: =K111-L111 -> 0 | P111: =IF($J$7=5,N111-O111,0) -> 0 | S111: =Q111-R111 -> 0 | V111: =T111-U111 -> 0 | Y111: =IF($J$7=5,W111-X111,0) -> 0 | AA111: =SUM(B111,E111,H111,K111,IF($J$7=5,N111,0)) -> 0 | AB111: =SUM(C111,F111,I111,L111,IF($J$7=5,O111,0)) -> 0 | AC111: =SUM(B111,E111,H111,K111,IF($J$7=5,N111,0))-SUM(C111,F111,I111,L111,IF($J$7=5,O111,0)) -> 0
A112: Sports equipment | D112: =B112-C112 -> 0 | G112: =E112-F112 -> 0 | J112: =H112-I112 -> 0 | M112: =K112-L112 -> 0 | P112: =IF($J$7=5,N112-O112,0) -> 0 | S112: =Q112-R112 -> 0 | V112: =T112-U112 -> 0 | Y112: =IF($J$7=5,W112-X112,0) -> 0 | AA112: =SUM(B112,E112,H112,K112,IF($J$7=5,N112,0)) -> 0 | AB112: =SUM(C112,F112,I112,L112,IF($J$7=5,O112,0)) -> 0 | AC112: =SUM(B112,E112,H112,K112,IF($J$7=5,N112,0))-SUM(C112,F112,I112,L112,IF($J$7=5,O112,0)) -> 0
A113: Team dues | D113: =B113-C113 -> 0 | G113: =E113-F113 -> 0 | J113: =H113-I113 -> 0 | M113: =K113-L113 -> 0 | P113: =IF($J$7=5,N113-O113,0) -> 0 | S113: =Q113-R113 -> 0 | V113: =T113-U113 -> 0 | Y113: =IF($J$7=5,W113-X113,0) -> 0 | AA113: =SUM(B113,E113,H113,K113,IF($J$7=5,N113,0)) -> 0 | AB113: =SUM(C113,F113,I113,L113,IF($J$7=5,O113,0)) -> 0 | AC113: =SUM(B113,E113,H113,K113,IF($J$7=5,N113,0))-SUM(C113,F113,I113,L113,IF($J$7=5,O113,0)) -> 0
A114: Toys/child gear | D114: =B114-C114 -> 0 | G114: =E114-F114 -> 0 | J114: =H114-I114 -> 0 | M114: =K114-L114 -> 0 | P114: =IF($J$7=5,N114-O114,0) -> 0 | S114: =Q114-R114 -> 0 | V114: =T114-U114 -> 0 | Y114: =IF($J$7=5,W114-X114,0) -> 0 | AA114: =SUM(B114,E114,H114,K114,IF($J$7=5,N114,0)) -> 0 | AB114: =SUM(C114,F114,I114,L114,IF($J$7=5,O114,0)) -> 0 | AC114: =SUM(B114,E114,H114,K114,IF($J$7=5,N114,0))-SUM(C114,F114,I114,L114,IF($J$7=5,O114,0)) -> 0
A115: ="Total "&A110 -> Total RECREATION | B115: =SUM(B111:B114) -> 0 | C115: =SUM(C111:C114) -> 0 | D115: =SUM(D111:D114) -> 0 | E115: =SUM(E111:E114) -> 0 | F115: =SUM(F111:F114) -> 0 | G115: =SUM(G111:G114) -> 0 | H115: =SUM(H111:H114) -> 0 | I115: =SUM(I111:I114) -> 0 | ... Y115: =SUM(Y111:Y114) -> 0 | AA115: =SUM(AA111:AA114) -> 0 | AB115: =SUM(C115,F115,I115,L115,IF($J$7=5,O115,0)) -> 0 | AC115: =SUM(AC111:AC114) -> 0
A117: MISCELLANEOUS | B117: =$B$11 -> Cost | C117: =$C$11 -> Frequency | D117: =$D$11 -> Total | E117: =$E$11 -> Cost | F117: =$F$11 -> Frequency | G117: =$G$11 -> Total | H117: =$H$11 -> Cost | I117: =$I$11 -> Frequency | J117: =$J$11 -> Total | K117: =$K$11 -> Cost | L117: =$L$11 -> Frequency | M117: =$M$11 -> Total | N117: =$N$11 -> Cost | O117: =$O$11 -> Frequency | P117: =$P$11 -> Total | Q117: =$H$11 -> Cost | R117: =$I$11 -> Frequency | S117: =$J$11 -> Total | T117: =$K$11 -> Cost | U117: =$L$11 -> Frequency | V117: =$M$11 -> Total | W117: =$N$11 -> Cost | X117: =$O$11 -> Frequency | Y117: =$P$11 -> Total | AA117: =$AA$11 -> Cost | AB117: =$AB$11 -> Frequency | AC117: =$AC$11 -> Total
A118: Other | D118: =B118-C118 -> 0 | G118: =E118-F118 -> 0 | J118: =H118-I118 -> 0 | M118: =K118-L118 -> 0 | P118: =IF($J$7=5,N118-O118,0) -> 0 | S118: =Q118-R118 -> 0 | V118: =T118-U118 -> 0 | Y118: =IF($J$7=5,W118-X118,0) -> 0 | AA118: =SUM(B118,E118,H118,K118,IF($J$7=5,N118,0)) -> 0 | AB118: =SUM(C118,F118,I118,L118,IF($J$7=5,O118,0)) -> 0 | AC118: =SUM(B118,E118,H118,K118,IF($J$7=5,N118,0))-SUM(C118,F118,I118,L118,IF($J$7=5,O118,0)) -> 0
A119: Other | D119: =B119-C119 -> 0 | G119: =E119-F119 -> 0 | J119: =H119-I119 -> 0 | M119: =K119-L119 -> 0 | P119: =IF($J$7=5,N119-O119,0) -> 0 | S119: =Q119-R119 -> 0 | V119: =T119-U119 -> 0 | Y119: =IF($J$7=5,W119-X119,0) -> 0 | AA119: =SUM(B119,E119,H119,K119,IF($J$7=5,N119,0)) -> 0 | AB119: =SUM(C119,F119,I119,L119,IF($J$7=5,O119,0)) -> 0 | AC119: =SUM(B119,E119,H119,K119,IF($J$7=5,N119,0))-SUM(C119,F119,I119,L119,IF($J$7=5,O119,0)) -> 0
...
