Workbook

Sheet categories
B2: Inflow | G2: Department
B3: I | C3: Investors, payment for shares issued | G3: To come later
B4: BI | C4: Bank to bank inflow
B6: Outflow
B7: BO | C7: Bank to bank outflow
B8: IN | C8: Investment
B9: P | C9: Purchasing of Equipment
B10: C | C10: Construction Expenses
B11: M | C11: Maintenenace and Repair
B12: S | C12: Security
B13: F | C13: Fuel for transportation
B14: T | C14: Topographical, Geologica and Survey services
B15: R | C15: Remuneration
B16: A | C16: Admin expenses
B17: BC | C17: Bank fees

Sheet nairaGlobus
A1: # | B1: Post Date | C1: Value Date | D1: Trans. Reference | E1: Narration | F1: Debit | G1: Credit | H1: Balance | K1: Category | L1: Month Number
A2: 1 | B2: 01/1/2026 | C2: 01/1/2026 | E2: Opening Balance | F2: 0 | G2: 0 | H2: 0 | I2: =VALUE(F2) -> 0 | K2: BI | L2: =MONTH(C2) -> 1
A3: 2 | B3: 05-03-2026 | C3: 46086 | D3: 000023260305141110009202297366 | E3: FT/Prov/PERAMARE MINES /PRV To Globus BankPERAM | F3: 0 | G3: 20000 | H3: 20000 | I3: =VALUE(F3) -> 0 | K3: BI | L3: =MONTH(C3) -> 3
A4: 3 | B4: 05-03-2026 | C4: 46086 | D4: 000023260305152305009202310982 | E4: FT/Prov/PERAMARE MINES /PRV To Globus BankPERAM | F4: 0 | G4: 100000000 | H4: 100020000 | I4: =VALUE(F4) -> 0 | K4: BI | L4: =MONTH(C4) -> 3
A5: 4 | B5: 05-03-2026 | C5: 46086 | D5: 000023260305152338009202311086 | E5: FT/Prov/PERAMARE MINES /PRV To Globus BankPERAM | F5: 0 | G5: 100000000 | H5: 200020000 | I5: =VALUE(F5) -> 0 | K5: BI | L5: =MONTH(C5) -> 3
A6: 5 | B6: 05-03-2026 | C6: 46086 | D6: 000023260305152433009202311263 | E6: FT/Prov/PERAMARE MINES /PRV To Globus BankPERAM | F6: 0 | G6: 100000000 | H6: 300020000 | I6: =VALUE(F6) -> 0 | K6: BI | L6: =MONTH(C6) -> 3
A7: 6 | B7: 05-03-2026 | C7: 46086 | D7: 000023260305152505009202311348 | E7: FT/Prov/PERAMARE MINES /PRV To Globus BankPERAM | F7: 0 | G7: 100000000 | H7: 400020000 | I7: =VALUE(F7) -> 0 | K7: BI | L7: =MONTH(C7) -> 3
A8: 7 | B8: 05-03-2026 | C8: 46086 | D8: 000023260305152611009202311563 | E8: FT/Prov/PERAMARE MINES /PRV To Globus BankPERAM | F8: 0 | G8: 100000000 | H8: 500020000 | I8: =VALUE(F8) -> 0 | K8: BI | L8: =MONTH(C8) -> 3
A9: 8 | B9: 05-03-2026 | C9: 46086 | D9: 000023260305152648009202311666 | E9: FT/Prov/PERAMARE MINES /PRV To Globus BankPERAM | F9: 0 | G9: 60000000 | H9: 560020000 | I9: =VALUE(F9) -> 0 | K9: BI | L9: =MONTH(C9) -> 3
A10: 9 | B10: 06-03-2026 | C10: 46087 | E10: CORPORATE SEARCH FEE | F10: 10000 | G10: 0 | H10: 560010000 | I10: =VALUE(F10) -> 10000 | K10: BC | L10: =MONTH(C10) -> 3
A11: 10 | B11: 30-03-2026 | C11: 46108 | E11: TD Booked Ref 035308202603342 | F11: 500000000 | G11: 0 | H11: 60010000 | I11: =VALUE(F11) -> 500000000 | K11: IN | L11: =MONTH(C11) -> 3
A12: 11 | B12: 31-03-2026 | C12: 46112 | D12: 000023260331230956009206748092 | E12: FT/Prov/PERAMARE MINES /PRV To Globus BankPERAM | F12: 0 | G12: 100000000 | H12: 160010000 | I12: =VALUE(F12) -> 0 | K12: BI | L12: =MONTH(C12) -> 3
A13: 12 | B13: 31-03-2026 | C13: 46112 | D13: SMSALERT TXN CHARGES | E13: SMSALERT TXN CHARGES | F13: 48 | G13: 0 | H13: 160009952 | I13: =VALUE(F13) -> 48 | K13: BC | L13: =MONTH(C13) -> 3
A14: 13 | B14: 01-04-2026 | C14: 46113 | D14: 000027260401163129012894472005 | E14: stampdutyFT/GTL/PERAMARE M/PERAMARE MINES LTDgtl | F14: 50 | G14: 0 | H14: 160009902 | I14: =VALUE(F14) -> 50 | K14: BC | L14: =MONTH(C14) -> 4
A15: 14 | B15: 01-04-2026 | C15: 46113 | D15: 000027260401163129012894472005 | E15: /chargeFT/GTL/PERAMARE M/PERAMARE MINES LTDgtl00 | F15: 53.75 | G15: 0 | H15: 1.6000985e+08 | I15: =VALUE(F15) -> 53.75 | K15: BC | L15: =MONTH(C15) -> 4
A16: 15 | B16: 01-04-2026 | C16: 46113 | D16: 000027260401163129012894472005 | E16: FT/GTL/PERAMARE M/PERAMARE MINES LTD | F16: 100000000 | G16: 0 | H16: 60009848 | I16: =VALUE(F16) -> 100000000 | K16: BO | L16: =MONTH(C16) -> 4
I17: =VALUE(F17) -> 0
I18: =VALUE(F18) -> 0
I19: =VALUE(F19) -> 0
I20: =VALUE(F20) -> 0
I21: =VALUE(F21) -> 0
I22: =VALUE(F22) -> 0
I23: =VALUE(F23) -> 0
I24: =VALUE(F24) -> 0
I25: =VALUE(F25) -> 0
I26: =VALUE(F26) -> 0
I27: =VALUE(F27) -> 0
I28: =VALUE(F28) -> 0
... I381: =VALUE(F381) -> 0

Sheet cashflow
B2: All figures in kiloNaira | J2: past | K2: future
B4: Inflow | F4: 1 | G4: 2 | H4: 3 | I4: 4 | J4: 5 | K4: 6 | L4: 7 | M4: 8 | N4: 9 | O4: 10 | P4: 11 | Q4: 12
B5: I | C5: Investors, payment for shares issued | F5: =(SUMIFS(nairaGlobus!$G:$G, nairaGlobus!$K:$K,cashflow!$B$5, nairaGlobus!$L:$L, F4))/1000 -> 0 | G5: =(SUMIFS(nairaGlobus!$G:$G, nairaGlobus!$K:$K,cashflow!$B$5, nairaGlobus!$L:$L, G4))/1000 -> 0 | H5: =(SUMIFS(nairaGlobus!$G:$G, nairaGlobus!$K:$K,cashflow!$B$5, nairaGlobus!$L:$L, H4))/1000 -> 0 | I5: =(SUMIFS(nairaGlobus!$G:$G, nairaGlobus!$K:$K,cashflow!$B$5, nairaGlobus!$L:$L, I4))/1000 -> 0 | J5: =(SUMIFS(nairaGlobus!$G:$G, nairaGlobus!$K:$K,cashflow!$B$5, nairaGlobus!$L:$L, J4))/1000 -> 0
B6: BI | C6: Bank to bank inflow | F6: =(SUMIFS(nairaGlobus!$G:$G, nairaGlobus!$K:$K,cashflow!$B$6, nairaGlobus!$L:$L, F4))/1000 -> 0 | G6: =(SUMIFS(nairaGlobus!$G:$G, nairaGlobus!$K:$K,cashflow!$B$6, nairaGlobus!$L:$L, G4))/1000 -> 0 | H6: =(SUMIFS(nairaGlobus!$G:$G, nairaGlobus!$K:$K,cashflow!$B$6, nairaGlobus!$L:$L, H4))/1000 -> 660020 | I6: =(SUMIFS(nairaGlobus!$G:$G, nairaGlobus!$K:$K,cashflow!$B$6, nairaGlobus!$L:$L, I4))/1000 -> 0 | J6: =(SUMIFS(nairaGlobus!$G:$G, nairaGlobus!$K:$K,cashflow!$B$6, nairaGlobus!$L:$L, J4))/1000 -> 0
B8: Total Inflow | F8: =SUM(F5:F6) -> 0 | G8: =SUM(G5:G6) -> 0 | H8: =SUM(H5:H6) -> 660020 | I8: =SUM(I5:I6) -> 0 | J8: =SUM(J5:J6) -> 0
B10: Outflow
B11: BO | C11: Bank to bank outflow | F11: =(SUMIFS(nairaGlobus!$F:$F, nairaGlobus!$K:$K, $B$11, nairaGlobus!$L:$L, F4))/1000 -> 0 | G11: =(SUMIFS(nairaGlobus!$F:$F, nairaGlobus!$K:$K, $B$11, nairaGlobus!$L:$L, G4))/1000 -> 0 | H11: =(SUMIFS(nairaGlobus!$F:$F, nairaGlobus!$K:$K, $B$11, nairaGlobus!$L:$L, H4))/1000 -> 0 | I11: =(SUMIFS(nairaGlobus!$F:$F, nairaGlobus!$K:$K, $B$11, nairaGlobus!$L:$L, I4))/1000 -> 100000 | J11: =(SUMIFS(nairaGlobus!$F:$F, nairaGlobus!$K:$K, $B$11, nairaGlobus!$L:$L, J4))/1000 -> 0
B12: IN | C12: Investment | F12: =(SUMIFS(nairaGlobus!$F:$F, nairaGlobus!$K:$K, $B$12, nairaGlobus!$L:$L, F4))/1000 -> 0 | G12: =(SUMIFS(nairaGlobus!$F:$F, nairaGlobus!$K:$K, $B$12, nairaGlobus!$L:$L, G4))/1000 -> 0 | H12: =(SUMIFS(nairaGlobus!$F:$F, nairaGlobus!$K:$K, $B$12, nairaGlobus!$L:$L, H4))/1000 -> 500000 | I12: =(SUMIFS(nairaGlobus!$F:$F, nairaGlobus!$K:$K, $B$12, nairaGlobus!$L:$L, I4))/1000 -> 0 | J12: =(SUMIFS(nairaGlobus!$F:$F, nairaGlobus!$K:$K, $B$12, nairaGlobus!$L:$L, J4))/1000 -> 0
B13: P | C13: Purchasing of Equipment | F13: =(SUMIFS(nairaGlobus!$F:$F, nairaGlobus!$K:$K, $B$13, nairaGlobus!$L:$L, F4))/1000 -> 0 | G13: =(SUMIFS(nairaGlobus!$F:$F, nairaGlobus!$K:$K, $B$13, nairaGlobus!$L:$L, G4))/1000 -> 0 | H13: =(SUMIFS(nairaGlobus!$F:$F, nairaGlobus!$K:$K, $B$13, nairaGlobus!$L:$L, H4))/1000 -> 0 | I13: =(SUMIFS(nairaGlobus!$F:$F, nairaGlobus!$K:$K, $B$13, nairaGlobus!$L:$L, I4))/1000 -> 0 | J13: =(SUMIFS(nairaGlobus!$F:$F, nairaGlobus!$K:$K, $B$13, nairaGlobus!$L:$L, J4))/1000 -> 0
B14: C | C14: Construction Expenses | F14: =(SUMIFS(nairaGlobus!$F:$F, nairaGlobus!$K:$K, $B$14, nairaGlobus!$L:$L, F4))/1000 -> 0 | G14: =(SUMIFS(nairaGlobus!$F:$F, nairaGlobus!$K:$K, $B$14, nairaGlobus!$L:$L, G4))/1000 -> 0 | H14: =(SUMIFS(nairaGlobus!$F:$F, nairaGlobus!$K:$K, $B$14, nairaGlobus!$L:$L, H4))/1000 -> 0 | I14: =(SUMIFS(nairaGlobus!$F:$F, nairaGlobus!$K:$K, $B$14, nairaGlobus!$L:$L, I4))/1000 -> 0 | J14: =(SUMIFS(nairaGlobus!$F:$F, nairaGlobus!$K:$K, $B$14, nairaGlobus!$L:$L, J4))/1000 -> 0
B15: M | C15: Maintenance and Repair | F15: =(SUMIFS(nairaGlobus!$F:$F, nairaGlobus!$K:$K, $B$15, nairaGlobus!$L:$L, F4))/1000 -> 0 | G15: =(SUMIFS(nairaGlobus!$F:$F, nairaGlobus!$K:$K, $B$15, nairaGlobus!$L:$L, G4))/1000 -> 0 | H15: =(SUMIFS(nairaGlobus!$F:$F, nairaGlobus!$K:$K, $B$15, nairaGlobus!$L:$L, H4))/1000 -> 0 | I15: =(SUMIFS(nairaGlobus!$F:$F, nairaGlobus!$K:$K, $B$15, nairaGlobus!$L:$L, I4))/1000 -> 0 | J15: =(SUMIFS(nairaGlobus!$F:$F, nairaGlobus!$K:$K, $B$15, nairaGlobus!$L:$L, J4))/1000 -> 0
B16: S | C16: Security | F16: =(SUMIFS(nairaGlobus!$F:$F, nairaGlobus!$K:$K, $B$16, nairaGlobus!$L:$L, F4))/1000 -> 0 | G16: =(SUMIFS(nairaGlobus!$F:$F, nairaGlobus!$K:$K, $B$16, nairaGlobus!$L:$L, G4))/1000 -> 0 | H16: =(SUMIFS(nairaGlobus!$F:$F, nairaGlobus!$K:$K, $B$16, nairaGlobus!$L:$L, H4))/1000 -> 0 | I16: =(SUMIFS(nairaGlobus!$F:$F, nairaGlobus!$K:$K, $B$16, nairaGlobus!$L:$L, I4))/1000 -> 0 | J16: =(SUMIFS(nairaGlobus!$F:$F, nairaGlobus!$K:$K, $B$16, nairaGlobus!$L:$L, J4))/1000 -> 0
B17: F | C17: Fuel for transportation | F17: =(SUMIFS(nairaGlobus!$F:$F, nairaGlobus!$K:$K, $B$17, nairaGlobus!$L:$L, F4))/1000 -> 0 | G17: =(SUMIFS(nairaGlobus!$F:$F, nairaGlobus!$K:$K, $B$17, nairaGlobus!$L:$L, G4))/1000 -> 0 | H17: =(SUMIFS(nairaGlobus!$F:$F, nairaGlobus!$K:$K, $B$17, nairaGlobus!$L:$L, H4))/1000 -> 0 | I17: =(SUMIFS(nairaGlobus!$F:$F, nairaGlobus!$K:$K, $B$17, nairaGlobus!$L:$L, I4))/1000 -> 0 | J17: =(SUMIFS(nairaGlobus!$F:$F, nairaGlobus!$K:$K, $B$17, nairaGlobus!$L:$L, J4))/1000 -> 0
B18: T | C18: Topographical, Geologica and Survey services | F18: =(SUMIFS(nairaGlobus!$F:$F, nairaGlobus!$K:$K, $B$18, nairaGlobus!$L:$L, F4))/1000 -> 0 | G18: =(SUMIFS(nairaGlobus!$F:$F, nairaGlobus!$K:$K, $B$18, nairaGlobus!$L:$L, G4))/1000 -> 0 | H18: =(SUMIFS(nairaGlobus!$F:$F, nairaGlobus!$K:$K, $B$18, nairaGlobus!$L:$L, H4))/1000 -> 0 | I18: =(SUMIFS(nairaGlobus!$F:$F, nairaGlobus!$K:$K, $B$18, nairaGlobus!$L:$L, I4))/1000 -> 0 | J18: =(SUMIFS(nairaGlobus!$F:$F, nairaGlobus!$K:$K, $B$18, nairaGlobus!$L:$L, J4))/1000 -> 0
B19: R | C19: Remuneration | F19: =(SUMIFS(nairaGlobus!$F:$F, nairaGlobus!$K:$K, $B$19, nairaGlobus!$L:$L, F4))/1000 -> 0 | G19: =(SUMIFS(nairaGlobus!$F:$F, nairaGlobus!$K:$K, $B$19, nairaGlobus!$L:$L, G4))/1000 -> 0 | H19: =(SUMIFS(nairaGlobus!$F:$F, nairaGlobus!$K:$K, $B$19, nairaGlobus!$L:$L, H4))/1000 -> 0 | I19: =(SUMIFS(nairaGlobus!$F:$F, nairaGlobus!$K:$K, $B$19, nairaGlobus!$L:$L, I4))/1000 -> 0 | J19: =(SUMIFS(nairaGlobus!$F:$F, nairaGlobus!$K:$K, $B$19, nairaGlobus!$L:$L, J4))/1000 -> 0
B20: A | C20: Admin expenses | F20: =(SUMIFS(nairaGlobus!$F:$F, nairaGlobus!$K:$K, $B$20, nairaGlobus!$L:$L, F4))/1000 -> 0 | G20: =(SUMIFS(nairaGlobus!$F:$F, nairaGlobus!$K:$K, $B$20, nairaGlobus!$L:$L, G4))/1000 -> 0 | H20: =(SUMIFS(nairaGlobus!$F:$F, nairaGlobus!$K:$K, $B$20, nairaGlobus!$L:$L, H4))/1000 -> 0 | I20: =(SUMIFS(nairaGlobus!$F:$F, nairaGlobus!$K:$K, $B$20, nairaGlobus!$L:$L, I4))/1000 -> 0 | J20: =(SUMIFS(nairaGlobus!$F:$F, nairaGlobus!$K:$K, $B$20, nairaGlobus!$L:$L, J4))/1000 -> 0
B21: BC | C21: Bank fees | F21: =(SUMIFS(nairaGlobus!$F:$F, nairaGlobus!$K:$K, $B$21, nairaGlobus!$L:$L, F4))/1000 -> 0 | G21: =(SUMIFS(nairaGlobus!$F:$F, nairaGlobus!$K:$K, $B$21, nairaGlobus!$L:$L, G4))/1000 -> 0 | H21: =(SUMIFS(nairaGlobus!$F:$F, nairaGlobus!$K:$K, $B$21, nairaGlobus!$L:$L, H4))/1000 -> 10.048 | I21: =(SUMIFS(nairaGlobus!$F:$F, nairaGlobus!$K:$K, $B$21, nairaGlobus!$L:$L, I4))/1000 -> 0.10375 | J21: =(SUMIFS(nairaGlobus!$F:$F, nairaGlobus!$K:$K, $B$21, nairaGlobus!$L:$L, J4))/1000 -> 0
C23: Total Outflow | F23: =SUM(F11:F21) -> 0 | G23: =SUM(G11:G21) -> 0 | H23: =SUM(H11:H21) -> 500010.05 | I23: =SUM(I11:I21) -> 100000.1 | J23: =SUM(J11:J21) -> 0
C25: Balance | F25: =F8-F23 -> 0 | G25: =G8-G23 -> 0 | H25: =H8-H23 -> 160009.95 | I25: =H25+I8-I23 -> 60009.848 | J25: =J8-J23 -> 0
C27: Bamk balance | F27: 0 | G27: 0 | H27: =(SUM(nairaGlobus!G3:G13)-SUM(nairaGlobus!F3:F13))/1000 -> 160009.95 | I27: =nairaGlobus!H16/1000 -> 60009.848 | J27: 0
