Workbook

Sheet Summary
B12: Description | C12: Total Inflow | D12: Total Outflow (Expenses ) | E12: Balance
C14: N | D14: N | E14: N
B15: Income | C15: 0 | E15: =C15-D15 -> 0
B16: Peramare Medical Bank | C16: 150000000 | D16: ='Bank Schedule__1__'!H592-'Bank Schedule__1__'!G15-'Bank Schedule__1__'!H58 -> 78588749 | E16: =C16-D16 -> 71411251
B17: Peramare Medical Petty Cash | C17: 0 | D17: ='Cash-In-Hand Schedule_'!H590 -> 129000 | E17: =C17-D17 -> -129000
B18: Labell | C18: 112000000 | D18: ='Lanbell Lab'!G590 -> 97502100 | E18: =C18-D18 -> 14497900
B19: Peramare Ghana | C19: 133000000 | D19: ='Peramare Ghana'!G590 -> 0 | E19: =C19-D19 -> 133000000
B20: Others | C20: 0 | D20: =Others!G73 -> 98875916 | E20: =C20-D20 -> -98875916
B21: Current Balance | C21: =SUM(C12:C20) -> 395000000 | D21: =SUM(D12:D20) -> 2.7509576e+08 | E21: =C21-D21 -> 1.1990424e+08

Sheet Bank Schedule__1__
B10: Bank Analysis Schedule
J11: Inflow Breakdown | P11: Outflow Breakdown
B12: Date | C12: Description | D12: Transaction Categorisation | E12: Voucher Number | F12: User Unit/ Department | G12: Total Inflow | H12: Total Outflow (Expenses ) | I12: Balance | P12: Assets | S12: Overheads & Salary | AM12: Others
J13: Directors/ Shareholders Contribution | K13: Revenue | L13: Reversal | M13: Interest | N13: Advance Refund | O13: Intra Bank Transfer | P13: Office Equipment | Q13: Funiture and Fittings | R13: Motor Vehicle | S13: Repairs and Maintenance | T13: Transportation | U13: Travel | V13: Staff Welfare | W13: Security and cleaning services | X13: Volunteer Stipend | Y13: Staff salary and Allowance | Z13: Professional Fees | AA13: Internet & Telecommunication | AB13: Stationary & Office Suplies | AC13: Registration, Fees and Dues | AD13: Petty cash | AE13: Marketing and Advertisement | AF13: Hotel Accommodation | AG13: Fuel & lubricant | AH13: Tax | AI13: Training and Development | AJ13: Utilities | AK13: Product logistics | AL13: Bank Charges | AM13: Intra Bank Transfer | AN13: Reversal
G14: N | H14: N | I14: N | J14: N | K14: N | L14: N | M14: N | N14: N | O14: N | P14: N | Q14: N | R14: N | S14: N | T14: N | V14: N | W14: N | X14: N | Y14: N | Z14: N | AA14: N | AB14: N | AC14: N | AD14: N | AE14: N | AF14: N | AG14: N | AH14: N | AI14: N | AJ14: N | AL14: N | AM14: N | AN14: N
C15: Beginning Balance | G15: 6578462 | I15: =G15-H15 -> 6578462
B16: 44805 | C16: Electricity bill | D16: Utilities | E16: PV/0001 | F16: Admin | G16: 0 | H16: 50000 | I16: =I15+G16-H16 -> 6528462 | J16: 0 | P16: =IF($D16=P$13,$H16, 0) -> 0 | Q16: =IF($D16=Q$13,$H16, 0) -> 0 | R16: =IF($D16=R$13,$H16, 0) -> 0 | S16: =IF($D16=S$13,$H16, 0) -> 0 | T16: =IF($D16=T$13,$H16, 0) -> 0 | U16: =IF($D16=U$13,$H16, 0) -> 0 | V16: =IF($D16=V$13,$H16, 0) -> 0 | W16: =IF($D16=W$13,$H16, 0) -> 0 | ... AN16: =IF($D16=AN$13,$H16, 0) -> 0
B17: 44811 | C17: Shipping cost for illumigyn genescope | D17: Product logistics | E17: PV/0002 | F17: Logistics | H17: 58500 | I17: =I16+G17-H17 -> 6469962 | P17: =IF($D17=P$13,$H17, 0) -> 0 | Q17: =IF($D17=Q$13,$H17, 0) -> 0 | R17: =IF($D17=R$13,$H17, 0) -> 0 | S17: =IF($D17=S$13,$H17, 0) -> 0 | T17: =IF($D17=T$13,$H17, 0) -> 0 | U17: =IF($D17=U$13,$H17, 0) -> 0 | V17: =IF($D17=V$13,$H17, 0) -> 0 | W17: =IF($D17=W$13,$H17, 0) -> 0 | ... AN17: =IF($D17=AN$13,$H17, 0) -> 0
B18: 44812 | C18: Marriage allowance | D18: Staff Welfare | E18: PV/0003 | F18: Admin | H18: 50000 | I18: =I17+G18-H18 -> 6419962 | P18: =IF($D18=P$13,$H18, 0) -> 0 | Q18: =IF($D18=Q$13,$H18, 0) -> 0 | R18: =IF($D18=R$13,$H18, 0) -> 0 | S18: =IF($D18=S$13,$H18, 0) -> 0 | T18: =IF($D18=T$13,$H18, 0) -> 0 | U18: =IF($D18=U$13,$H18, 0) -> 0 | V18: =IF($D18=V$13,$H18, 0) -> 50000 | W18: =IF($D18=W$13,$H18, 0) -> 0 | ... AN18: =IF($D18=AN$13,$H18, 0) -> 0
B19: 44812 | C19: Childbirth allowance | D19: Staff Welfare | E19: PV/0003 | F19: Admin | H19: 50000 | I19: =I18+G19-H19 -> 6369962 | P19: =IF($D19=P$13,$H19, 0) -> 0 | Q19: =IF($D19=Q$13,$H19, 0) -> 0 | R19: =IF($D19=R$13,$H19, 0) -> 0 | S19: =IF($D19=S$13,$H19, 0) -> 0 | T19: =IF($D19=T$13,$H19, 0) -> 0 | U19: =IF($D19=U$13,$H19, 0) -> 0 | V19: =IF($D19=V$13,$H19, 0) -> 50000 | W19: =IF($D19=W$13,$H19, 0) -> 0 | ... AN19: =IF($D19=AN$13,$H19, 0) -> 0
B20: 44812 | C20: Repairs and Maintenance: Motor vehicle | D20: Repairs and Maintenance | E20: PV/0004 | F20: Admin | H20: 30000 | I20: =I19+G20-H20 -> 6339962 | P20: =IF($D20=P$13,$H20, 0) -> 0 | Q20: =IF($D20=Q$13,$H20, 0) -> 0 | R20: =IF($D20=R$13,$H20, 0) -> 0 | S20: =IF($D20=S$13,$H20, 0) -> 30000 | T20: =IF($D20=T$13,$H20, 0) -> 0 | U20: =IF($D20=U$13,$H20, 0) -> 0 | V20: =IF($D20=V$13,$H20, 0) -> 0 | W20: =IF($D20=W$13,$H20, 0) -> 0 | ... AN20: =IF($D20=AN$13,$H20, 0) -> 0
B21: 44812 | C21: Airplane Tickets and accommodation for guests | D21: Transportation | E21: PV/0005 | F21: Sales Department | H21: 130000 | I21: =I20+G21-H21 -> 6209962 | T21: 307000 | U21: 307000
B22: 44812 | C22: Airplane Tickets and accommodation Refunded From Staff | D22: Transportation | F22: Sales Department | G22: 4200 | H22: 0 | I22: =I21+G22-H22 -> 6214162 | AC22: 10000
B23: 44812 | C23: Airplane Tickets and accommodation for guests | D23: Transportation | E23: PV/0006 | F23: Sales Department | H23: 207000 | I23: =I22+G23-H23 -> 6007162 | T23: 207000 | U23: 207000
B24: 44813 | C24: Nanox Importation license | D24: Registration, Fees and Dues | E24: PV/0007 | F24: Logistics | H24: 100000 | I24: =I23+G24-H24 -> 5907162 | P24: =IF($D24=P$13,$H24, 0) -> 0 | Q24: =IF($D24=Q$13,$H24, 0) -> 0 | R24: =IF($D24=R$13,$H24, 0) -> 0 | S24: =IF($D24=S$13,$H24, 0) -> 0 | T24: =IF($D24=T$13,$H24, 0) -> 0 | U24: =IF($D24=U$13,$H24, 0) -> 0 | V24: =IF($D24=V$13,$H24, 0) -> 0 | W24: =IF($D24=W$13,$H24, 0) -> 0 | ... AN24: =IF($D24=AN$13,$H24, 0) -> 0
B25: 44816 | C25: Maintenance and repairs: Laptop Reimbursement | D25: Repairs and Maintenance | E25: PV/0008 | F25: Admin | H25: 80000 | I25: =I24+G25-H25 -> 5827162 | P25: =IF($D25=P$13,$H25, 0) -> 0 | Q25: =IF($D25=Q$13,$H25, 0) -> 0 | R25: =IF($D25=R$13,$H25, 0) -> 0 | S25: =IF($D25=S$13,$H25, 0) -> 80000 | T25: =IF($D25=T$13,$H25, 0) -> 0 | U25: =IF($D25=U$13,$H25, 0) -> 0 | V25: =IF($D25=V$13,$H25, 0) -> 0 | W25: =IF($D25=W$13,$H25, 0) -> 0 | ... AN25: =IF($D25=AN$13,$H25, 0) -> 0
B26: 44816 | C26: Maintenance and repairs: AC installations | D26: Repairs and Maintenance | E26: PV/0009 | F26: Admin | H26: 175000 | I26: =I25+G26-H26 -> 5652162 | P26: =IF($D26=P$13,$H26, 0) -> 0 | Q26: =IF($D26=Q$13,$H26, 0) -> 0 | R26: =IF($D26=R$13,$H26, 0) -> 0 | S26: =IF($D26=S$13,$H26, 0) -> 175000 | T26: =IF($D26=T$13,$H26, 0) -> 0 | U26: =IF($D26=U$13,$H26, 0) -> 0 | V26: =IF($D26=V$13,$H26, 0) -> 0 | W26: =IF($D26=W$13,$H26, 0) -> 0 | ... AN26: =IF($D26=AN$13,$H26, 0) -> 0
B27: 44816 | C27: Electricity bill | D27: Utilities | E27: PV/0010 | F27: Admin | H27: 50000 | I27: =I26+G27-H27 -> 5602162 | P27: =IF($D27=P$13,$H27, 0) -> 0 | Q27: =IF($D27=Q$13,$H27, 0) -> 0 | R27: =IF($D27=R$13,$H27, 0) -> 0 | S27: =IF($D27=S$13,$H27, 0) -> 0 | T27: =IF($D27=T$13,$H27, 0) -> 0 | U27: =IF($D27=U$13,$H27, 0) -> 0 | V27: =IF($D27=V$13,$H27, 0) -> 0 | W27: =IF($D27=W$13,$H27, 0) -> 0 | ... AN27: =IF($D27=AN$13,$H27, 0) -> 0
B28: 44816 | C28: Payment for the transfer and activation of domain | D28: Internet and telecommunication | E28: PV/0011 | F28: IT | H28: 20000 | I28: =I27+G28-H28 -> 5582162 | AA28: 20000
B29: 44818 | C29: Web hosting subscription and email service | D29: Internet and telecommunication | E29: PV/0012 | F29: IT | H29: 71000 | I29: =I28+G29-H29 -> 5511162 | AA29: 71000
B30: 44818 | C30: Staff Travel Expenses | D30: Training and Development | E30: PV/0013 | F30: Sales Department | H30: 308000 | I30: =I29+G30-H30 -> 5203162 | AI30: 308000
B31: 44819 | C31: Office Supplies | D31: Stationary & Office Suplies | E31: PV/0014 | F31: Admin | H31: 212000 | I31: =I30+G31-H31 -> 4991162 | P31: =IF($D31=P$13,$H31, 0) -> 0 | Q31: =IF($D31=Q$13,$H31, 0) -> 0 | R31: =IF($D31=R$13,$H31, 0) -> 0 | S31: =IF($D31=S$13,$H31, 0) -> 0 | T31: =IF($D31=T$13,$H31, 0) -> 0 | U31: =IF($D31=U$13,$H31, 0) -> 0 | V31: =IF($D31=V$13,$H31, 0) -> 0 | W31: =IF($D31=W$13,$H31, 0) -> 0 | ... AN31: =IF($D31=AN$13,$H31, 0) -> 0
B32: 44819 | C32: Payment for Business Cards | D32: Printing | E32: PV/0015 | F32: Sales Department | H32: 40000 | I32: =I31+G32-H32 -> 4951162
B33: 44819 | C33: Payment for shipping gynescopes | D33: Product logistics | E33: PV/0016 | F33: Logistics | H33: 516361.63 | I33: =I32+G33-H33 -> 4434800.4 | P33: =IF($D33=P$13,$H33, 0) -> 0 | Q33: =IF($D33=Q$13,$H33, 0) -> 0 | R33: =IF($D33=R$13,$H33, 0) -> 0 | S33: =IF($D33=S$13,$H33, 0) -> 0 | T33: =IF($D33=T$13,$H33, 0) -> 0 | U33: =IF($D33=U$13,$H33, 0) -> 0 | V33: =IF($D33=V$13,$H33, 0) -> 0 | W33: =IF($D33=W$13,$H33, 0) -> 0 | ... AN33: =IF($D33=AN$13,$H33, 0) -> 0
B34: 44819 | C34: Printing of marketing products: brochures | D34: Printing | E34: PV/0017 | F34: Sales Department | H34: 17500 | I34: =I33+G34-H34 -> 4417300.4
B35: 44820 | C35: Repairs and Maintenance: Electrical Appliances | D35: Repairs and Maintenance | E35: PV/0018 | F35: Admin | H35: 35700 | I35: =I34+G35-H35 -> 4381600.4 | P35: =IF($D35=P$13,$H35, 0) -> 0 | Q35: =IF($D35=Q$13,$H35, 0) -> 0 | R35: =IF($D35=R$13,$H35, 0) -> 0 | S35: =IF($D35=S$13,$H35, 0) -> 35700 | T35: =IF($D35=T$13,$H35, 0) -> 0 | U35: =IF($D35=U$13,$H35, 0) -> 0 | V35: =IF($D35=V$13,$H35, 0) -> 0 | W35: =IF($D35=W$13,$H35, 0) -> 0 | ... AN35: =IF($D35=AN$13,$H35, 0) -> 0
B36: 44823 | C36: Payment for SCMUL | D36: Registration, Fees and Dues | E36: PV/0019 | F36: Admin | H36: 80000 | I36: =I35+G36-H36 -> 4301600.4 | P36: =IF($D36=P$13,$H36, 0) -> 0 | Q36: =IF($D36=Q$13,$H36, 0) -> 0 | R36: =IF($D36=R$13,$H36, 0) -> 0 | S36: =IF($D36=S$13,$H36, 0) -> 0 | T36: =IF($D36=T$13,$H36, 0) -> 0 | U36: =IF($D36=U$13,$H36, 0) -> 0 | V36: =IF($D36=V$13,$H36, 0) -> 0 | W36: =IF($D36=W$13,$H36, 0) -> 0 | ... AN36: =IF($D36=AN$13,$H36, 0) -> 0
B37: 44824 | C37: Office supplies | D37: Office equipment | E37: PV/0020 | F37: Admin | H37: 7500 | I37: =I36+G37-H37 -> 4294100.4 | P37: =IF($D37=P$13,$H37, 0) -> 7500 | Q37: =IF($D37=Q$13,$H37, 0) -> 0 | R37: =IF($D37=R$13,$H37, 0) -> 0 | S37: =IF($D37=S$13,$H37, 0) -> 0 | T37: =IF($D37=T$13,$H37, 0) -> 0 | U37: =IF($D37=U$13,$H37, 0) -> 0 | V37: =IF($D37=V$13,$H37, 0) -> 0 | W37: =IF($D37=W$13,$H37, 0) -> 0 | ... AN37: =IF($D37=AN$13,$H37, 0) -> 0
B38: 44826 | C38: Repairs and Maintenance: Electrical Appliances | D38: Repairs and Maintenance | E38: PV/0021 | F38: Admin | H38: 14000 | I38: =I37+G38-H38 -> 4280100.4 | P38: =IF($D38=P$13,$H38, 0) -> 0 | Q38: =IF($D38=Q$13,$H38, 0) -> 0 | R38: =IF($D38=R$13,$H38, 0) -> 0 | S38: =IF($D38=S$13,$H38, 0) -> 14000 | T38: =IF($D38=T$13,$H38, 0) -> 0 | U38: =IF($D38=U$13,$H38, 0) -> 0 | V38: =IF($D38=V$13,$H38, 0) -> 0 | W38: =IF($D38=W$13,$H38, 0) -> 0 | ... AN38: =IF($D38=AN$13,$H38, 0) -> 0
B39: 44826 | C39: Salary For The Month of September | D39: Staff Salary and Allowance | E39: PV/0022 | F39: HR | H39: 3540000 | I39: =I38+G39-H39 -> 740100.37 | P39: =IF($D39=P$13,$H39, 0) -> 0 | Q39: =IF($D39=Q$13,$H39, 0) -> 0 | R39: =IF($D39=R$13,$H39, 0) -> 0 | S39: =IF($D39=S$13,$H39, 0) -> 0 | T39: =IF($D39=T$13,$H39, 0) -> 0 | U39: =IF($D39=U$13,$H39, 0) -> 0 | V39: =IF($D39=V$13,$H39, 0) -> 0 | W39: =IF($D39=W$13,$H39, 0) -> 0 | ... AN39: =IF($D39=AN$13,$H39, 0) -> 0
B40: 44826 | C40: Webcam and dungle | D40: Office equipment | E40: PV/0023 | F40: IT | H40: 28000 | I40: =I39+G40-H40 -> 712100.37
B41: 44827 | C41: Electricity bill | D41: Utilities | E41: PV/0024 | F41: Admin | H41: 50000 | I41: =I40+G41-H41 -> 662100.37 | P41: =IF($D41=P$13,$H41, 0) -> 0 | Q41: =IF($D41=Q$13,$H41, 0) -> 0 | R41: =IF($D41=R$13,$H41, 0) -> 0 | S41: =IF($D41=S$13,$H41, 0) -> 0 | T41: =IF($D41=T$13,$H41, 0) -> 0 | U41: =IF($D41=U$13,$H41, 0) -> 0 | V41: =IF($D41=V$13,$H41, 0) -> 0 | W41: =IF($D41=W$13,$H41, 0) -> 0 | ... AN41: =IF($D41=AN$13,$H41, 0) -> 0
B42: 44830 | C42: Repairs and Maintenance: Electrical Appliances | D42: Repairs and Maintenance | E42: PV/0025 | F42: Admin | H42: 139400 | I42: =I41+G42-H42 -> 522700.37 | P42: =IF($D42=P$13,$H42, 0) -> 0 | Q42: =IF($D42=Q$13,$H42, 0) -> 0 | R42: =IF($D42=R$13,$H42, 0) -> 0 | S42: =IF($D42=S$13,$H42, 0) -> 139400 | T42: =IF($D42=T$13,$H42, 0) -> 0 | U42: =IF($D42=U$13,$H42, 0) -> 0 | V42: =IF($D42=V$13,$H42, 0) -> 0 | W42: =IF($D42=W$13,$H42, 0) -> 0 | ... AN42: =IF($D42=AN$13,$H42, 0) -> 0
B43: 44832 | C43: Repairs and Maintenance: Plumbing | D43: Repairs and Maintenance | E43: PV/0026 | F43: Admin | H43: 14500 | I43: =I42+G43-H43 -> 508200.37 | P43: =IF($D43=P$13,$H43, 0) -> 0 | Q43: =IF($D43=Q$13,$H43, 0) -> 0 | R43: =IF($D43=R$13,$H43, 0) -> 0 | S43: =IF($D43=S$13,$H43, 0) -> 14500 | T43: =IF($D43=T$13,$H43, 0) -> 0 | U43: =IF($D43=U$13,$H43, 0) -> 0 | V43: =IF($D43=V$13,$H43, 0) -> 0 | W43: =IF($D43=W$13,$H43, 0) -> 0 | ... AN43: =IF($D43=AN$13,$H43, 0) -> 0
B44: 44833 | C44: Payment for Fire service registration | D44: Registration, Fees and Dues | E44: PV/0027 | F44: Admin | H44: 254000 | I44: =I43+G44-H44 -> 254200.37 | P44: =IF($D44=P$13,$H44, 0) -> 0 | Q44: =IF($D44=Q$13,$H44, 0) -> 0 | R44: =IF($D44=R$13,$H44, 0) -> 0 | S44: =IF($D44=S$13,$H44, 0) -> 0 | T44: =IF($D44=T$13,$H44, 0) -> 0 | U44: =IF($D44=U$13,$H44, 0) -> 0 | V44: =IF($D44=V$13,$H44, 0) -> 0 | W44: =IF($D44=W$13,$H44, 0) -> 0 | ... AN44: =IF($D44=AN$13,$H44, 0) -> 0
B45: 44833 | C45: Payment for the purchase of diesel | D45: Fuel & lubricant | E45: PV/0028 | F45: Admin | H45: 200000 | I45: =I44+G45-H45 -> 54200.37 | P45: =IF($D45=P$13,$H45, 0) -> 0 | Q45: =IF($D45=Q$13,$H45, 0) -> 0 | R45: =IF($D45=R$13,$H45, 0) -> 0 | S45: =IF($D45=S$13,$H45, 0) -> 0 | T45: =IF($D45=T$13,$H45, 0) -> 0 | U45: =IF($D45=U$13,$H45, 0) -> 0 | V45: =IF($D45=V$13,$H45, 0) -> 0 | W45: =IF($D45=W$13,$H45, 0) -> 0 | ... AN45: =IF($D45=AN$13,$H45, 0) -> 0
B46: 44839 | C46: Electricity bill | D46: Utilities | E46: PV/0029 | F46: Admin | H46: 50000 | I46: =I45+G46-H46 -> 4200.37 | P46: =IF($D46=P$13,$H46, 0) -> 0 | Q46: =IF($D46=Q$13,$H46, 0) -> 0 | R46: =IF($D46=R$13,$H46, 0) -> 0 | S46: =IF($D46=S$13,$H46, 0) -> 0 | T46: =IF($D46=T$13,$H46, 0) -> 0 | U46: =IF($D46=U$13,$H46, 0) -> 0 | V46: =IF($D46=V$13,$H46, 0) -> 0 | W46: =IF($D46=W$13,$H46, 0) -> 0 | ... AN46: =IF($D46=AN$13,$H46, 0) -> 0
B47: 44839 | C47: income | G47: 150000000 | I47: =I46+G47-H47 -> 1.500042e+08
B48: 44840 | C48: Staff Renumeration | D48: Staff Salary and allowance | E48: PV/0030 | F48: HR | H48: 150000 | I48: =I47+G48-H48 -> 1.498542e+08 | P48: =IF($D48=P$13,$H48, 0) -> 0 | Q48: =IF($D48=Q$13,$H48, 0) -> 0 | R48: =IF($D48=R$13,$H48, 0) -> 0 | S48: =IF($D48=S$13,$H48, 0) -> 0 | T48: =IF($D48=T$13,$H48, 0) -> 0 | U48: =IF($D48=U$13,$H48, 0) -> 0 | V48: =IF($D48=V$13,$H48, 0) -> 0 | W48: =IF($D48=W$13,$H48, 0) -> 0 | ... AN48: =IF($D48=AN$13,$H48, 0) -> 0
B49: 44840 | C49: Purchase of TVs | D49: Office equipment | E49: PV/0031 | F49: Admin | H49: 1994000 | I49: =I48+G49-H49 -> 1.478602e+08 | P49: =IF($D49=P$13,$H49, 0) -> 1994000 | Q49: =IF($D49=Q$13,$H49, 0) -> 0 | R49: =IF($D49=R$13,$H49, 0) -> 0 | S49: =IF($D49=S$13,$H49, 0) -> 0 | T49: =IF($D49=T$13,$H49, 0) -> 0 | U49: =IF($D49=U$13,$H49, 0) -> 0 | V49: =IF($D49=V$13,$H49, 0) -> 0 | W49: =IF($D49=W$13,$H49, 0) -> 0 | ... AN49: =IF($D49=AN$13,$H49, 0) -> 0
B50: 44840 | C50: Purchase of IT Supplies | D50: Office equipment | E50: PV/0032 | F50: IT | H50: 109580 | I50: =I49+G50-H50 -> 1.4775062e+08
B51: 44845 | C51: Electricity bill | D51: Utilities | E51: PV/0033 | F51: Admin | H51: 20000 | I51: =I50+G51-H51 -> 1.4773062e+08 | P51: =IF($D51=P$13,$H51, 0) -> 0 | Q51: =IF($D51=Q$13,$H51, 0) -> 0 | R51: =IF($D51=R$13,$H51, 0) -> 0 | S51: =IF($D51=S$13,$H51, 0) -> 0 | T51: =IF($D51=T$13,$H51, 0) -> 0 | U51: =IF($D51=U$13,$H51, 0) -> 0 | V51: =IF($D51=V$13,$H51, 0) -> 0 | W51: =IF($D51=W$13,$H51, 0) -> 0 | ... AN51: =IF($D51=AN$13,$H51, 0) -> 0
B52: 44846 | C52: For the purchase of generator | D52: Office equipment | E52: PV/0034 | F52: Admin | H52: 10490240 | I52: =I51+G52-H52 -> 1.3724038e+08 | P52: =IF($D52=P$13,$H52, 0) -> 10490240 | Q52: =IF($D52=Q$13,$H52, 0) -> 0 | R52: =IF($D52=R$13,$H52, 0) -> 0 | S52: =IF($D52=S$13,$H52, 0) -> 0 | T52: =IF($D52=T$13,$H52, 0) -> 0 | U52: =IF($D52=U$13,$H52, 0) -> 0 | V52: =IF($D52=V$13,$H52, 0) -> 0 | W52: =IF($D52=W$13,$H52, 0) -> 0 | ... AN52: =IF($D52=AN$13,$H52, 0) -> 0
B53: 44847 | C53: For the purchase of dispensers and letterheads | D53: Office equipment | E53: PV/0035 | F53: Admin | H53: 191000 | I53: =I52+G53-H53 -> 1.3704938e+08 | P53: =IF($D53=P$13,$H53, 0) -> 191000 | Q53: =IF($D53=Q$13,$H53, 0) -> 0 | R53: =IF($D53=R$13,$H53, 0) -> 0 | S53: =IF($D53=S$13,$H53, 0) -> 0 | T53: =IF($D53=T$13,$H53, 0) -> 0 | U53: =IF($D53=U$13,$H53, 0) -> 0 | V53: =IF($D53=V$13,$H53, 0) -> 0 | W53: =IF($D53=W$13,$H53, 0) -> 0 | ... AN53: =IF($D53=AN$13,$H53, 0) -> 0
B54: 44847 | C54: Surge extension wires | D54: Stationary & Office Suplies | E54: PV/0036 | F54: Admin | H54: 60000 | I54: =I53+G54-H54 -> 1.3698938e+08 | P54: =IF($D54=P$13,$H54, 0) -> 0 | Q54: =IF($D54=Q$13,$H54, 0) -> 0 | R54: =IF($D54=R$13,$H54, 0) -> 0 | S54: =IF($D54=S$13,$H54, 0) -> 0 | T54: =IF($D54=T$13,$H54, 0) -> 0 | U54: =IF($D54=U$13,$H54, 0) -> 0 | V54: =IF($D54=V$13,$H54, 0) -> 0 | W54: =IF($D54=W$13,$H54, 0) -> 0 | ... AN54: =IF($D54=AN$13,$H54, 0) -> 0
B55: 44851 | C55: Electricity bill | D55: Utilities | E55: PV/0037 | F55: Admin | H55: 40000 | I55: =I54+G55-H55 -> 1.3694938e+08 | P55: =IF($D55=P$13,$H55, 0) -> 0 | Q55: =IF($D55=Q$13,$H55, 0) -> 0 | R55: =IF($D55=R$13,$H55, 0) -> 0 | S55: =IF($D55=S$13,$H55, 0) -> 0 | T55: =IF($D55=T$13,$H55, 0) -> 0 | U55: =IF($D55=U$13,$H55, 0) -> 0 | V55: =IF($D55=V$13,$H55, 0) -> 0 | W55: =IF($D55=W$13,$H55, 0) -> 0 | ... AN55: =IF($D55=AN$13,$H55, 0) -> 0
B56: 44852 | C56: AC installation | D56: Repairs and Maintenance | E56: PV/0038 | F56: Admin | H56: 60000 | I56: =I55+G56-H56 -> 1.3688938e+08 | P56: =IF($D56=P$13,$H56, 0) -> 0 | Q56: =IF($D56=Q$13,$H56, 0) -> 0 | R56: =IF($D56=R$13,$H56, 0) -> 0 | S56: =IF($D56=S$13,$H56, 0) -> 60000 | T56: =IF($D56=T$13,$H56, 0) -> 0 | U56: =IF($D56=U$13,$H56, 0) -> 0 | V56: =IF($D56=V$13,$H56, 0) -> 0 | W56: =IF($D56=W$13,$H56, 0) -> 0 | ... AN56: =IF($D56=AN$13,$H56, 0) -> 0
B57: 44854 | C57: Remabursement for dummies | D57: Office equipment | E57: PV/0039 | F57: HR | H57: 1329160 | I57: =I56+G57-H57 -> 1.3556022e+08 | P57: =IF($D57=P$13,$H57, 0) -> 1329160 | Q57: =IF($D57=Q$13,$H57, 0) -> 0 | R57: =IF($D57=R$13,$H57, 0) -> 0 | S57: =IF($D57=S$13,$H57, 0) -> 0 | T57: =IF($D57=T$13,$H57, 0) -> 0 | U57: =IF($D57=U$13,$H57, 0) -> 0 | V57: =IF($D57=V$13,$H57, 0) -> 0 | W57: =IF($D57=W$13,$H57, 0) -> 0 | ... AN57: =IF($D57=AN$13,$H57, 0) -> 0
B58: 44854 | C58: Payment for sponsorship of SOGON conference | D58: Marketing and Advertisement | E58: PV/0040 | F58: Sales Department | H58: 10000000 | I58: =I57+G58-H58 -> 1.2556022e+08
B59: 44854 | C59: Sogon | D59: Marketing and Advertisement | F59: Sales Department | G59: 10000000 | I59: =I58+G59-H59 -> 1.3556022e+08
B60: 44858 | C60: Marketing and Advertisement: Raven and Macau | D60: Marketing and Advertisement | E60: PV/0041 | F60: Sales Department | H60: 2000016 | I60: =I59+G60-H60 -> 1.335602e+08
B61: 44858 | C61: Radiation Caution Sign | D61: Stationary & Office Suplies | E61: PV/0042 | F61: Admin | H61: 10000 | I61: =I60+G61-H61 -> 1.335502e+08 | P61: =IF($D61=P$13,$H61, 0) -> 0 | Q61: =IF($D61=Q$13,$H61, 0) -> 0 | R61: =IF($D61=R$13,$H61, 0) -> 0 | S61: =IF($D61=S$13,$H61, 0) -> 0 | T61: =IF($D61=T$13,$H61, 0) -> 0 | U61: =IF($D61=U$13,$H61, 0) -> 0 | V61: =IF($D61=V$13,$H61, 0) -> 0 | W61: =IF($D61=W$13,$H61, 0) -> 0 | ... AN61: =IF($D61=AN$13,$H61, 0) -> 0
B62: 44858 | C62: Electricity bill | D62: Utilities | E62: PV/0043 | F62: Admin | H62: 50000 | I62: =I61+G62-H62 -> 1.335002e+08 | P62: =IF($D62=P$13,$H62, 0) -> 0 | Q62: =IF($D62=Q$13,$H62, 0) -> 0 | R62: =IF($D62=R$13,$H62, 0) -> 0 | S62: =IF($D62=S$13,$H62, 0) -> 0 | T62: =IF($D62=T$13,$H62, 0) -> 0 | U62: =IF($D62=U$13,$H62, 0) -> 0 | V62: =IF($D62=V$13,$H62, 0) -> 0 | W62: =IF($D62=W$13,$H62, 0) -> 0 | ... AN62: =IF($D62=AN$13,$H62, 0) -> 0
B63: 44858 | C63: DHL shipment | D63: Product logistics | E63: PV/0044 | F63: Logistics | H63: 57200 | I63: =I62+G63-H63 -> 1.33443e+08 | P63: =IF($D63=P$13,$H63, 0) -> 0 | Q63: =IF($D63=Q$13,$H63, 0) -> 0 | R63: =IF($D63=R$13,$H63, 0) -> 0 | S63: =IF($D63=S$13,$H63, 0) -> 0 | T63: =IF($D63=T$13,$H63, 0) -> 0 | U63: =IF($D63=U$13,$H63, 0) -> 0 | V63: =IF($D63=V$13,$H63, 0) -> 0 | W63: =IF($D63=W$13,$H63, 0) -> 0 | ... AN63: =IF($D63=AN$13,$H63, 0) -> 0
B64: 44858 | C64: Salary For The Month of October | D64: Staff Salary and Allowance | E64: PV/0045 | F64: HR | H64: 3540000 | I64: =I63+G64-H64 -> 1.29903e+08 | P64: =IF($D64=P$13,$H64, 0) -> 0 | Q64: =IF($D64=Q$13,$H64, 0) -> 0 | R64: =IF($D64=R$13,$H64, 0) -> 0 | S64: =IF($D64=S$13,$H64, 0) -> 0 | T64: =IF($D64=T$13,$H64, 0) -> 0 | U64: =IF($D64=U$13,$H64, 0) -> 0 | V64: =IF($D64=V$13,$H64, 0) -> 0 | W64: =IF($D64=W$13,$H64, 0) -> 0 | ... AN64: =IF($D64=AN$13,$H64, 0) -> 0
B65: 44859 | C65: Admin office supplies | D65: Stationary & Office Suplies | E65: PV/0046 | F65: Admin | H65: 60700 | I65: =I64+G65-H65 -> 1.298423e+08 | P65: =IF($D65=P$13,$H65, 0) -> 0 | Q65: =IF($D65=Q$13,$H65, 0) -> 0 | R65: =IF($D65=R$13,$H65, 0) -> 0 | S65: =IF($D65=S$13,$H65, 0) -> 0 | T65: =IF($D65=T$13,$H65, 0) -> 0 | U65: =IF($D65=U$13,$H65, 0) -> 0 | V65: =IF($D65=V$13,$H65, 0) -> 0 | W65: =IF($D65=W$13,$H65, 0) -> 0 | ... AN65: =IF($D65=AN$13,$H65, 0) -> 0
B66: 44860 | C66: Repairs and maintenance: AC installation | D66: Repairs and Maintenance | E66: PV/0047 | F66: Admin | H66: 81000 | I66: =I65+G66-H66 -> 1.297613e+08 | P66: =IF($D66=P$13,$H66, 0) -> 0 | Q66: =IF($D66=Q$13,$H66, 0) -> 0 | R66: =IF($D66=R$13,$H66, 0) -> 0 | S66: =IF($D66=S$13,$H66, 0) -> 81000 | T66: =IF($D66=T$13,$H66, 0) -> 0 | U66: =IF($D66=U$13,$H66, 0) -> 0 | V66: =IF($D66=V$13,$H66, 0) -> 0 | W66: =IF($D66=W$13,$H66, 0) -> 0 | ... AN66: =IF($D66=AN$13,$H66, 0) -> 0
B67: 44860 | C67: Business cards | D67: Marketing and Advertisement | E67: PV/0048 | F67: Sales Department | H67: 11000 | I67: =I66+G67-H67 -> 1.297503e+08
B68: 44861 | C68: Stamps | D68: Office equipment | E68: PV/0049 | F68: Admin | H68: 40500 | I68: =I67+G68-H68 -> 1.297098e+08 | P68: =IF($D68=P$13,$H68, 0) -> 40500 | Q68: =IF($D68=Q$13,$H68, 0) -> 0 | R68: =IF($D68=R$13,$H68, 0) -> 0 | S68: =IF($D68=S$13,$H68, 0) -> 0 | T68: =IF($D68=T$13,$H68, 0) -> 0 | U68: =IF($D68=U$13,$H68, 0) -> 0 | V68: =IF($D68=V$13,$H68, 0) -> 0 | W68: =IF($D68=W$13,$H68, 0) -> 0 | ... AN68: =IF($D68=AN$13,$H68, 0) -> 0
B69: 44862 | C69: Electricity wiring | D69: Repairs and Maintenance | E69: PV/0050 | F69: Admin | H69: 50000 | I69: =I68+G69-H69 -> 1.296598e+08 | P69: =IF($D69=P$13,$H69, 0) -> 0 | Q69: =IF($D69=Q$13,$H69, 0) -> 0 | R69: =IF($D69=R$13,$H69, 0) -> 0 | S69: =IF($D69=S$13,$H69, 0) -> 50000 | T69: =IF($D69=T$13,$H69, 0) -> 0 | U69: =IF($D69=U$13,$H69, 0) -> 0 | V69: =IF($D69=V$13,$H69, 0) -> 0 | W69: =IF($D69=W$13,$H69, 0) -> 0 | ... AN69: =IF($D69=AN$13,$H69, 0) -> 0
B70: 44862 | C70: Payment for diesel | D70: Fuel & lubricant | E70: PV/0051 | F70: Admin | H70: 440000 | I70: =I69+G70-H70 -> 1.292198e+08 | P70: =IF($D70=P$13,$H70, 0) -> 0 | Q70: =IF($D70=Q$13,$H70, 0) -> 0 | R70: =IF($D70=R$13,$H70, 0) -> 0 | S70: =IF($D70=S$13,$H70, 0) -> 0 | T70: =IF($D70=T$13,$H70, 0) -> 0 | U70: =IF($D70=U$13,$H70, 0) -> 0 | V70: =IF($D70=V$13,$H70, 0) -> 0 | W70: =IF($D70=W$13,$H70, 0) -> 0 | ... AN70: =IF($D70=AN$13,$H70, 0) -> 0
B71: 44865 | C71: Electricity bill | D71: Utilities | E71: PV/0052 | F71: Admin | H71: 70000 | I71: =I70+G71-H71 -> 1.291498e+08 | P71: =IF($D71=P$13,$H71, 0) -> 0 | Q71: =IF($D71=Q$13,$H71, 0) -> 0 | R71: =IF($D71=R$13,$H71, 0) -> 0 | S71: =IF($D71=S$13,$H71, 0) -> 0 | T71: =IF($D71=T$13,$H71, 0) -> 0 | U71: =IF($D71=U$13,$H71, 0) -> 0 | V71: =IF($D71=V$13,$H71, 0) -> 0 | W71: =IF($D71=W$13,$H71, 0) -> 0 | ... AN71: =IF($D71=AN$13,$H71, 0) -> 0
B72: 44865 | C72: For the purchase of Vacuum cleaner | D72: Office equipment | E72: PV/0053 | F72: Admin | H72: 80000 | I72: =I71+G72-H72 -> 1.290698e+08 | P72: =IF($D72=P$13,$H72, 0) -> 80000 | Q72: =IF($D72=Q$13,$H72, 0) -> 0 | R72: =IF($D72=R$13,$H72, 0) -> 0 | S72: =IF($D72=S$13,$H72, 0) -> 0 | T72: =IF($D72=T$13,$H72, 0) -> 0 | U72: =IF($D72=U$13,$H72, 0) -> 0 | V72: =IF($D72=V$13,$H72, 0) -> 0 | W72: =IF($D72=W$13,$H72, 0) -> 0 | ... AN72: =IF($D72=AN$13,$H72, 0) -> 0
B73: 44866 | C73: Electricity bill | D73: Utilities | E73: PV/0054 | F73: Admin | H73: 20000 | I73: =I72+G73-H73 -> 1.290498e+08 | P73: =IF($D73=P$13,$H73, 0) -> 0 | Q73: =IF($D73=Q$13,$H73, 0) -> 0 | R73: =IF($D73=R$13,$H73, 0) -> 0 | S73: =IF($D73=S$13,$H73, 0) -> 0 | T73: =IF($D73=T$13,$H73, 0) -> 0 | U73: =IF($D73=U$13,$H73, 0) -> 0 | V73: =IF($D73=V$13,$H73, 0) -> 0 | W73: =IF($D73=W$13,$H73, 0) -> 0 | ... AN73: =IF($D73=AN$13,$H73, 0) -> 0
B74: 44868 | C74: Staff Welfare | D74: Staff Welfare | E74: PV/0055 | F74: HR | H74: 330000 | I74: =I73+G74-H74 -> 1.287198e+08 | P74: =IF($D74=P$13,$H74, 0) -> 0 | Q74: =IF($D74=Q$13,$H74, 0) -> 0 | R74: =IF($D74=R$13,$H74, 0) -> 0 | S74: =IF($D74=S$13,$H74, 0) -> 0 | T74: =IF($D74=T$13,$H74, 0) -> 0 | U74: =IF($D74=U$13,$H74, 0) -> 0 | V74: =IF($D74=V$13,$H74, 0) -> 330000 | W74: =IF($D74=W$13,$H74, 0) -> 0 | ... AN74: =IF($D74=AN$13,$H74, 0) -> 0
B75: 44869 | C75: IT supplies | D75: Office supplies | E75: PV/0056 | F75: IT | H75: 13000 | I75: =I74+G75-H75 -> 1.287068e+08
B76: 44873 | C76: Netting of Facility | D76: Repairs and Maintenance | E76: PV/0057 | F76: Admin | H76: 68500 | I76: =I75+G76-H76 -> 1.286383e+08 | P76: =IF($D76=P$13,$H76, 0) -> 0 | Q76: =IF($D76=Q$13,$H76, 0) -> 0 | R76: =IF($D76=R$13,$H76, 0) -> 0 | S76: =IF($D76=S$13,$H76, 0) -> 68500 | T76: =IF($D76=T$13,$H76, 0) -> 0 | U76: =IF($D76=U$13,$H76, 0) -> 0 | V76: =IF($D76=V$13,$H76, 0) -> 0 | W76: =IF($D76=W$13,$H76, 0) -> 0 | ... AN76: =IF($D76=AN$13,$H76, 0) -> 0
B77: 44873 | C77: Registration of motor vehicle | D77: Repairs and Maintenance | E77: PV/0058 | F77: Admin | H77: 44500 | I77: =I76+G77-H77 -> 1.285938e+08 | P77: =IF($D77=P$13,$H77, 0) -> 0 | Q77: =IF($D77=Q$13,$H77, 0) -> 0 | R77: =IF($D77=R$13,$H77, 0) -> 0 | S77: =IF($D77=S$13,$H77, 0) -> 44500 | T77: =IF($D77=T$13,$H77, 0) -> 0 | U77: =IF($D77=U$13,$H77, 0) -> 0 | V77: =IF($D77=V$13,$H77, 0) -> 0 | W77: =IF($D77=W$13,$H77, 0) -> 0 | ... AN77: =IF($D77=AN$13,$H77, 0) -> 0
B78: 44874 | C78: Payment for security services | D78: Security and cleaning services | E78: PV/0059 | F78: Admin | H78: 1501000 | I78: =I77+G78-H78 -> 1.270928e+08 | P78: =IF($D78=P$13,$H78, 0) -> 0 | Q78: =IF($D78=Q$13,$H78, 0) -> 0 | R78: =IF($D78=R$13,$H78, 0) -> 0 | S78: =IF($D78=S$13,$H78, 0) -> 0 | T78: =IF($D78=T$13,$H78, 0) -> 0 | U78: =IF($D78=U$13,$H78, 0) -> 0 | V78: =IF($D78=V$13,$H78, 0) -> 0 | W78: =IF($D78=W$13,$H78, 0) -> 1501000 | ... AN78: =IF($D78=AN$13,$H78, 0) -> 0
B79: 44874 | C79: Repairs and Maintenance: Motor vehicle | D79: Repairs and Maintenance | E79: PV/0060 | F79: Admin | H79: 1300000 | I79: =I78+G79-H79 -> 1.257928e+08 | P79: =IF($D79=P$13,$H79, 0) -> 0 | Q79: =IF($D79=Q$13,$H79, 0) -> 0 | R79: =IF($D79=R$13,$H79, 0) -> 0 | S79: =IF($D79=S$13,$H79, 0) -> 1300000 | T79: =IF($D79=T$13,$H79, 0) -> 0 | U79: =IF($D79=U$13,$H79, 0) -> 0 | V79: =IF($D79=V$13,$H79, 0) -> 0 | W79: =IF($D79=W$13,$H79, 0) -> 0 | ... AN79: =IF($D79=AN$13,$H79, 0) -> 0
B80: 44874 | C80: Balance for Kitchennette | D80: Funiture and Fittings | E80: PV/0061 | F80: Admin | H80: 239800 | I80: =I79+G80-H80 -> 1.25553e+08 | P80: =IF($D80=P$13,$H80, 0) -> 0 | Q80: =IF($D80=Q$13,$H80, 0) -> 239800 | R80: =IF($D80=R$13,$H80, 0) -> 0 | S80: =IF($D80=S$13,$H80, 0) -> 0 | T80: =IF($D80=T$13,$H80, 0) -> 0 | U80: =IF($D80=U$13,$H80, 0) -> 0 | V80: =IF($D80=V$13,$H80, 0) -> 0 | W80: =IF($D80=W$13,$H80, 0) -> 0 | ... AN80: =IF($D80=AN$13,$H80, 0) -> 0
B81: 44874 | C81: Purchase of Motor vehicle fuel | D81: Fuel & lubricant | E81: PV/0062 | F81: Admin | H81: 10000 | I81: =I80+G81-H81 -> 1.25543e+08 | P81: =IF($D81=P$13,$H81, 0) -> 0 | Q81: =IF($D81=Q$13,$H81, 0) -> 0 | R81: =IF($D81=R$13,$H81, 0) -> 0 | S81: =IF($D81=S$13,$H81, 0) -> 0 | T81: =IF($D81=T$13,$H81, 0) -> 0 | U81: =IF($D81=U$13,$H81, 0) -> 0 | V81: =IF($D81=V$13,$H81, 0) -> 0 | W81: =IF($D81=W$13,$H81, 0) -> 0 | ... AN81: =IF($D81=AN$13,$H81, 0) -> 0
B82: 44874 | C82: UPS for demo clinic | D82: Office equipment | E82: PV/0063 | F82: Admin | H82: 409900 | I82: =I81+G82-H82 -> 1.251331e+08 | P82: =IF($D82=P$13,$H82, 0) -> 409900 | Q82: =IF($D82=Q$13,$H82, 0) -> 0 | R82: =IF($D82=R$13,$H82, 0) -> 0 | S82: =IF($D82=S$13,$H82, 0) -> 0 | T82: =IF($D82=T$13,$H82, 0) -> 0 | U82: =IF($D82=U$13,$H82, 0) -> 0 | V82: =IF($D82=V$13,$H82, 0) -> 0 | W82: =IF($D82=W$13,$H82, 0) -> 0 | ... AN82: =IF($D82=AN$13,$H82, 0) -> 0
B83: 44875 | C83: Payment for cleaning services | D83: Security and cleaning services | E83: PV/0064 | F83: Admin | H83: 4000000 | I83: =I82+G83-H83 -> 1.211331e+08 | P83: =IF($D83=P$13,$H83, 0) -> 0 | Q83: =IF($D83=Q$13,$H83, 0) -> 0 | R83: =IF($D83=R$13,$H83, 0) -> 0 | S83: =IF($D83=S$13,$H83, 0) -> 0 | T83: =IF($D83=T$13,$H83, 0) -> 0 | U83: =IF($D83=U$13,$H83, 0) -> 0 | V83: =IF($D83=V$13,$H83, 0) -> 0 | W83: =IF($D83=W$13,$H83, 0) -> 4000000 | ... AN83: =IF($D83=AN$13,$H83, 0) -> 0
B84: 44875 | C84: Roll up balance | D84: Marketing and Advertisement | E84: PV/0065 | F84: Sales Department | H84: 70000 | I84: =I83+G84-H84 -> 1.210631e+08
B85: 44878 | C85: Electricity bill | D85: Utilities | E85: PV/0066 | F85: Admin | H85: 50000 | I85: =I84+G85-H85 -> 1.210131e+08 | P85: =IF($D85=P$13,$H85, 0) -> 0 | Q85: =IF($D85=Q$13,$H85, 0) -> 0 | R85: =IF($D85=R$13,$H85, 0) -> 0 | S85: =IF($D85=S$13,$H85, 0) -> 0 | T85: =IF($D85=T$13,$H85, 0) -> 0 | U85: =IF($D85=U$13,$H85, 0) -> 0 | V85: =IF($D85=V$13,$H85, 0) -> 0 | W85: =IF($D85=W$13,$H85, 0) -> 0 | ... AN85: =IF($D85=AN$13,$H85, 0) -> 0
B86: 44878 | C86: Office supplies | D86: Stationary & Office Suplies | E86: PV/0067 | F86: Admin | H86: 31950 | I86: =I85+G86-H86 -> 1.2098115e+08 | P86: =IF($D86=P$13,$H86, 0) -> 0 | Q86: =IF($D86=Q$13,$H86, 0) -> 0 | R86: =IF($D86=R$13,$H86, 0) -> 0 | S86: =IF($D86=S$13,$H86, 0) -> 0 | T86: =IF($D86=T$13,$H86, 0) -> 0 | U86: =IF($D86=U$13,$H86, 0) -> 0 | V86: =IF($D86=V$13,$H86, 0) -> 0 | W86: =IF($D86=W$13,$H86, 0) -> 0 | ... AN86: =IF($D86=AN$13,$H86, 0) -> 0
B87: 44879 | C87: Marketing and Advertisement: Promotional Items | D87: Marketing and Advertisement | E87: PV/0068 | F87: Sales Department | H87: 2921957 | I87: =I86+G87-H87 -> 1.180592e+08 | P87: =IF($D87=P$13,$H87, 0) -> 0 | Q87: =IF($D87=Q$13,$H87, 0) -> 0 | R87: =IF($D87=R$13,$H87, 0) -> 0 | S87: =IF($D87=S$13,$H87, 0) -> 0 | T87: =IF($D87=T$13,$H87, 0) -> 0 | U87: =IF($D87=U$13,$H87, 0) -> 0 | V87: =IF($D87=V$13,$H87, 0) -> 0 | W87: =IF($D87=W$13,$H87, 0) -> 0 | ... AN87: =IF($D87=AN$13,$H87, 0) -> 0
B88: 44879 | C88: Payment for feeding | D88: Training and Development | E88: PV/0069 | F88: HR | H88: 40000 | I88: =I87+G88-H88 -> 1.180192e+08 | P88: =IF($D88=P$13,$H88, 0) -> 0 | Q88: =IF($D88=Q$13,$H88, 0) -> 0 | R88: =IF($D88=R$13,$H88, 0) -> 0 | S88: =IF($D88=S$13,$H88, 0) -> 0 | T88: =IF($D88=T$13,$H88, 0) -> 0 | U88: =IF($D88=U$13,$H88, 0) -> 0 | V88: =IF($D88=V$13,$H88, 0) -> 0 | W88: =IF($D88=W$13,$H88, 0) -> 0 | ... AN88: =IF($D88=AN$13,$H88, 0) -> 0
B89: 44879 | C89: IT supplies | D89: Office equipment | E89: PV/0070 | F89: IT | H89: 442000 | I89: =I88+G89-H89 -> 1.175772e+08 | P89: =IF($D89=P$13,$H89, 0) -> 442000 | Q89: =IF($D89=Q$13,$H89, 0) -> 0 | R89: =IF($D89=R$13,$H89, 0) -> 0 | S89: =IF($D89=S$13,$H89, 0) -> 0 | T89: =IF($D89=T$13,$H89, 0) -> 0 | U89: =IF($D89=U$13,$H89, 0) -> 0 | V89: =IF($D89=V$13,$H89, 0) -> 0 | W89: =IF($D89=W$13,$H89, 0) -> 0 | ... AN89: =IF($D89=AN$13,$H89, 0) -> 0
B90: 44879 | C90: Balance for cabinet: Caataco Designs | D90: Repairs and Maintenance | E90: PV/0071 | F90: Admin | H90: 4315000 | I90: =I89+G90-H90 -> 1.132622e+08 | P90: =IF($D90=P$13,$H90, 0) -> 0 | Q90: =IF($D90=Q$13,$H90, 0) -> 0 | R90: =IF($D90=R$13,$H90, 0) -> 0 | S90: =IF($D90=S$13,$H90, 0) -> 4315000 | T90: =IF($D90=T$13,$H90, 0) -> 0 | U90: =IF($D90=U$13,$H90, 0) -> 0 | V90: =IF($D90=V$13,$H90, 0) -> 0 | W90: =IF($D90=W$13,$H90, 0) -> 0 | ... AN90: =IF($D90=AN$13,$H90, 0) -> 0
B91: 44879 | C91: Travel Expenses | D91: Travel | E91: PV/0072 | F91: Admin | H91: 5154671 | I91: =I90+G91-H91 -> 1.0810753e+08 | P91: =IF($D91=P$13,$H91, 0) -> 0 | Q91: =IF($D91=Q$13,$H91, 0) -> 0 | R91: =IF($D91=R$13,$H91, 0) -> 0 | S91: =IF($D91=S$13,$H91, 0) -> 0 | T91: =IF($D91=T$13,$H91, 0) -> 0 | U91: =IF($D91=U$13,$H91, 0) -> 5154671 | V91: =IF($D91=V$13,$H91, 0) -> 0 | W91: =IF($D91=W$13,$H91, 0) -> 0 | ... AN91: =IF($D91=AN$13,$H91, 0) -> 0
B92: 44881 | C92: Security Supplies | D92: Office equipment | E92: PV/0073 | F92: Admin | H92: 197950 | I92: =I91+G92-H92 -> 1.0790958e+08 | P92: =IF($D92=P$13,$H92, 0) -> 197950 | Q92: =IF($D92=Q$13,$H92, 0) -> 0 | R92: =IF($D92=R$13,$H92, 0) -> 0 | S92: =IF($D92=S$13,$H92, 0) -> 0 | T92: =IF($D92=T$13,$H92, 0) -> 0 | U92: =IF($D92=U$13,$H92, 0) -> 0 | V92: =IF($D92=V$13,$H92, 0) -> 0 | W92: =IF($D92=W$13,$H92, 0) -> 0 | ... AN92: =IF($D92=AN$13,$H92, 0) -> 0
B93: 44881 | C93: Volunteer stipend: Dr Bilal | D93: Volunteer stipend | E93: PV/0074 | F93: Admin | H93: 50000 | I93: =I92+G93-H93 -> 1.0785958e+08 | P93: =IF($D93=P$13,$H93, 0) -> 0 | Q93: =IF($D93=Q$13,$H93, 0) -> 0 | R93: =IF($D93=R$13,$H93, 0) -> 0 | S93: =IF($D93=S$13,$H93, 0) -> 0 | T93: =IF($D93=T$13,$H93, 0) -> 0 | U93: =IF($D93=U$13,$H93, 0) -> 0 | V93: =IF($D93=V$13,$H93, 0) -> 0 | W93: =IF($D93=W$13,$H93, 0) -> 0 | ... AN93: =IF($D93=AN$13,$H93, 0) -> 0
B94: 44882 | C94: Right Click fee | D94: Registration, Fees and Dues | E94: PV/0075 | F94: Admin | H94: 537500 | I94: =I93+G94-H94 -> 1.0732208e+08 | P94: =IF($D94=P$13,$H94, 0) -> 0 | Q94: =IF($D94=Q$13,$H94, 0) -> 0 | R94: =IF($D94=R$13,$H94, 0) -> 0 | S94: =IF($D94=S$13,$H94, 0) -> 0 | T94: =IF($D94=T$13,$H94, 0) -> 0 | U94: =IF($D94=U$13,$H94, 0) -> 0 | V94: =IF($D94=V$13,$H94, 0) -> 0 | W94: =IF($D94=W$13,$H94, 0) -> 0 | ... AN94: =IF($D94=AN$13,$H94, 0) -> 0
B95: 44882 | C95: Pumping Machine | D95: Repairs and Maintenance | E95: PV/0076 | F95: Admin | H95: 396000 | I95: =I94+G95-H95 -> 1.0692608e+08 | P95: =IF($D95=P$13,$H95, 0) -> 0 | Q95: =IF($D95=Q$13,$H95, 0) -> 0 | R95: =IF($D95=R$13,$H95, 0) -> 0 | S95: =IF($D95=S$13,$H95, 0) -> 396000 | T95: =IF($D95=T$13,$H95, 0) -> 0 | U95: =IF($D95=U$13,$H95, 0) -> 0 | V95: =IF($D95=V$13,$H95, 0) -> 0 | W95: =IF($D95=W$13,$H95, 0) -> 0 | ... AN95: =IF($D95=AN$13,$H95, 0) -> 0
B96: 44882 | C96: Microwave and Office equipments | D96: Office equipment | E96: PV/0077 | F96: Admin | H96: 153700 | I96: =I95+G96-H96 -> 1.0677238e+08 | P96: =IF($D96=P$13,$H96, 0) -> 153700 | Q96: =IF($D96=Q$13,$H96, 0) -> 0 | R96: =IF($D96=R$13,$H96, 0) -> 0 | S96: =IF($D96=S$13,$H96, 0) -> 0 | T96: =IF($D96=T$13,$H96, 0) -> 0 | U96: =IF($D96=U$13,$H96, 0) -> 0 | V96: =IF($D96=V$13,$H96, 0) -> 0 | W96: =IF($D96=W$13,$H96, 0) -> 0 | ... AN96: =IF($D96=AN$13,$H96, 0) -> 0
B97: 44882 | C97: Cold room fees | D97: =P13 -> Office Equipment | E97: PV/0078 | F97: Admin | H97: 21389100 | I97: =I96+G97-H97 -> 85383276 | P97: =IF($D97=P$13,$H97, 0) -> 21389100 | Q97: =IF($D97=Q$13,$H97, 0) -> 0 | R97: =IF($D97=R$13,$H97, 0) -> 0 | S97: =IF($D97=S$13,$H97, 0) -> 0 | T97: =IF($D97=T$13,$H97, 0) -> 0 | U97: =IF($D97=U$13,$H97, 0) -> 0 | V97: =IF($D97=V$13,$H97, 0) -> 0 | W97: =IF($D97=W$13,$H97, 0) -> 0 | ... AN97: =IF($D97=AN$13,$H97, 0) -> 0
B98: 44882 | C98: Volunteer stipend | D98: Volunteer stipend | E98: PV/0079 | F98: Admin | H98: 150000 | I98: =I97+G98-H98 -> 85233276 | P98: =IF($D98=P$13,$H98, 0) -> 0 | Q98: =IF($D98=Q$13,$H98, 0) -> 0 | R98: =IF($D98=R$13,$H98, 0) -> 0 | S98: =IF($D98=S$13,$H98, 0) -> 0 | T98: =IF($D98=T$13,$H98, 0) -> 0 | U98: =IF($D98=U$13,$H98, 0) -> 0 | V98: =IF($D98=V$13,$H98, 0) -> 0 | W98: =IF($D98=W$13,$H98, 0) -> 0 | ... AN98: =IF($D98=AN$13,$H98, 0) -> 0
B99: 44883 | C99: Marketing items | D99: Marketing and Advertisement | E99: PV/0080 | F99: Admin | H99: 49700 | I99: =I98+G99-H99 -> 85183576 | P99: =IF($D99=P$13,$H99, 0) -> 0 | Q99: =IF($D99=Q$13,$H99, 0) -> 0 | R99: =IF($D99=R$13,$H99, 0) -> 0 | S99: =IF($D99=S$13,$H99, 0) -> 0 | T99: =IF($D99=T$13,$H99, 0) -> 0 | U99: =IF($D99=U$13,$H99, 0) -> 0 | V99: =IF($D99=V$13,$H99, 0) -> 0 | W99: =IF($D99=W$13,$H99, 0) -> 0 | ... AN99: =IF($D99=AN$13,$H99, 0) -> 0
B100: 44886 | C100: Electricity bill for main building and Warehouse | D100: Utilities | E100: PV/0081 | F100: Admin | H100: 70000 | I100: =I99+G100-H100 -> 85113576 | P100: =IF($D100=P$13,$H100, 0) -> 0 | Q100: =IF($D100=Q$13,$H100, 0) -> 0 | R100: =IF($D100=R$13,$H100, 0) -> 0 | S100: =IF($D100=S$13,$H100, 0) -> 0 | T100: =IF($D100=T$13,$H100, 0) -> 0 | U100: =IF($D100=U$13,$H100, 0) -> 0 | V100: =IF($D100=V$13,$H100, 0) -> 0 | W100: =IF($D100=W$13,$H100, 0) -> 0 | ... AN100: =IF($D100=AN$13,$H100, 0) -> 0
B101: 44886 | C101: Payment for the Purchase of Fuel | D101: =AG13 -> Fuel & lubricant | E101: PV/0082 | F101: Admin | H101: 10000 | I101: =I100+G101-H101 -> 85103576 | P101: =IF($D101=P$13,$H101, 0) -> 0 | Q101: =IF($D101=Q$13,$H101, 0) -> 0 | R101: =IF($D101=R$13,$H101, 0) -> 0 | S101: =IF($D101=S$13,$H101, 0) -> 0 | T101: =IF($D101=T$13,$H101, 0) -> 0 | U101: =IF($D101=U$13,$H101, 0) -> 0 | V101: =IF($D101=V$13,$H101, 0) -> 0 | W101: =IF($D101=W$13,$H101, 0) -> 0 | ... AN101: =IF($D101=AN$13,$H101, 0) -> 0
B102: 44886 | C102: ID Cards, Certificates and promotional items | D102: Marketing and Advertisement | E102: PV/0083 | F102: Admin | H102: 356600 | I102: =I101+G102-H102 -> 84746976 | P102: =IF($D102=P$13,$H102, 0) -> 0 | Q102: =IF($D102=Q$13,$H102, 0) -> 0 | R102: =IF($D102=R$13,$H102, 0) -> 0 | S102: =IF($D102=S$13,$H102, 0) -> 0 | T102: =IF($D102=T$13,$H102, 0) -> 0 | U102: =IF($D102=U$13,$H102, 0) -> 0 | V102: =IF($D102=V$13,$H102, 0) -> 0 | W102: =IF($D102=W$13,$H102, 0) -> 0 | ... AN102: =IF($D102=AN$13,$H102, 0) -> 0
B103: 44886 | C103: Branded Shirts | D103: Marketing and Advertisement | E103: PV/0084 | F103: Sales Department | H103: 150000 | I103: =I102+G103-H103 -> 84596976
B104: 44886 | C104: Electricity bill | D104: Utilities | E104: PV/0085 | F104: Admin | H104: 50000 | I104: =I103+G104-H104 -> 84546976 | P104: =IF($D104=P$13,$H104, 0) -> 0 | Q104: =IF($D104=Q$13,$H104, 0) -> 0 | R104: =IF($D104=R$13,$H104, 0) -> 0 | S104: =IF($D104=S$13,$H104, 0) -> 0 | T104: =IF($D104=T$13,$H104, 0) -> 0 | U104: =IF($D104=U$13,$H104, 0) -> 0 | V104: =IF($D104=V$13,$H104, 0) -> 0 | W104: =IF($D104=W$13,$H104, 0) -> 0 | ... AN104: =IF($D104=AN$13,$H104, 0) -> 0
B105: 44886 | C105: Plumbing Expenses | D105: Repairs and Maintenance | E105: PV/0086 | F105: Admin | H105: 25000 | I105: =I104+G105-H105 -> 84521976 | P105: =IF($D105=P$13,$H105, 0) -> 0 | Q105: =IF($D105=Q$13,$H105, 0) -> 0 | R105: =IF($D105=R$13,$H105, 0) -> 0 | S105: =IF($D105=S$13,$H105, 0) -> 25000 | T105: =IF($D105=T$13,$H105, 0) -> 0 | U105: =IF($D105=U$13,$H105, 0) -> 0 | V105: =IF($D105=V$13,$H105, 0) -> 0 | W105: =IF($D105=W$13,$H105, 0) -> 0 | ... AN105: =IF($D105=AN$13,$H105, 0) -> 0
B106: 44886 | C106: Marketing and promotions | D106: Marketing and Advertisement | E106: PV/0087 | F106: Sales Department | H106: 49700 | I106: =I105+G106-H106 -> 84472276
B107: 44886 | C107: Surge extension wire | D107: Office Equipment | E107: PV/0088 | F107: Admin | H107: 25000 | I107: =I106+G107-H107 -> 84447276 | P107: =IF($D107=P$13,$H107, 0) -> 25000 | Q107: =IF($D107=Q$13,$H107, 0) -> 0 | R107: =IF($D107=R$13,$H107, 0) -> 0 | S107: =IF($D107=S$13,$H107, 0) -> 0 | T107: =IF($D107=T$13,$H107, 0) -> 0 | U107: =IF($D107=U$13,$H107, 0) -> 0 | V107: =IF($D107=V$13,$H107, 0) -> 0 | W107: =IF($D107=W$13,$H107, 0) -> 0 | ... AN107: =IF($D107=AN$13,$H107, 0) -> 0
B108: 44887 | C108: photography Expenses | D108: Marketing and Advertisement | E108: PV/0089 | F108: Sales Department | H108: 390000 | I108: =I107+G108-H108 -> 84057276
B109: 44887 | C109: Salary Expenses for the month of November | D109: Staff Salary and Allowance | E109: PV/0090 | F109: HR | H109: 3660000 | I109: =I108+G109-H109 -> 80397276 | P109: =IF($D109=P$13,$H109, 0) -> 0 | Q109: =IF($D109=Q$13,$H109, 0) -> 0 | R109: =IF($D109=R$13,$H109, 0) -> 0 | S109: =IF($D109=S$13,$H109, 0) -> 0 | T109: =IF($D109=T$13,$H109, 0) -> 0 | U109: =IF($D109=U$13,$H109, 0) -> 0 | V109: =IF($D109=V$13,$H109, 0) -> 0 | W109: =IF($D109=W$13,$H109, 0) -> 0 | ... AN109: =IF($D109=AN$13,$H109, 0) -> 0
...

Sheet Lanbell Lab
B10: Bank Analysis Schedule
I11: Inflow Breakdown | O11: Outflow Breakdown
B12: Date | C12: Description | D12: Transaction Categorisation | E12: User Unit/ Department | F12: Total Inflow | G12: Total Outflow (Expenses ) | H12: Balance | O12: Assets | R12: Overheads & Salary | AK12: Others
I13: Directors/ Shareholders Contribution | J13: Revenue | K13: Reversal | L13: Interest | M13: Advance Refund | N13: Intra Bank Transfer | O13: Office Equipment | P13: Furnitures & Fittings | Q13: Motor Vehicle | R13: Repairs & Maintenance | S13: Transportation | T13: Staff Welfare, Medicals and Entertainment | U13: Security services | V13: Volunteer Stipend | W13: Staff salary & Allowance | X13: Professional Fees | Y13: Internet & Telecommunication | Z13: Stationery & office supplies | AA13: Registration, Fees and Dues | AB13: Petty cash | AC13: Marketing and Advertisement | AD13: Hotel Accommodation | AE13: Fuel & Lubricant | AF13: Tax | AG13: Training and Development | AH13: Utility | AI13: Product Logistics (Air, Sea, Rail and Land) | AJ13: Bank Charges | AK13: Intra Bank Transfer | AL13: Reversal
F14: N | G14: N | H14: N | I14: N | J14: N | K14: N | L14: N | M14: N | N14: N | O14: N | P14: N | Q14: N | R14: N | S14: N | T14: N | U14: N | V14: N | W14: N | X14: N | Y14: N | Z14: N | AA14: N | AB14: N | AC14: N | AD14: N | AE14: N | AF14: N | AG14: N | AH14: N | AJ14: N | AK14: N | AL14: N
B15: 44824 | C15: Income | F15: 112000000 | H15: =F15-G15 -> 112000000
C16: Lanbell | F16: 0 | G16: 36496350 | H16: =H15+F16-G16 -> 75503650 | AH16: 50000
C17: Lanbell | F17: 0 | G17: 20000000 | H17: =H16+F17-G17 -> 55503650 | AI17: 58500
C18: Lanbell | F18: 0 | G18: 20000000 | H18: =H17+F18-G18 -> 35503650
B19: 44887 | C19: Lanbell | F19: 0 | G19: 20000000 | H19: =H18+F19-G19 -> 15503650
C20: Consultattion fees | D20: 1350 | F20: 0 | G20: 1005750 | H20: =H19+F20-G20 -> 14497900
F21: 0 | H21: =H20+F21-G21 -> 14497900
F22: 0 | H22: =H21+F22-G22 -> 14497900
F23: 0 | H23: =H22+F23-G23 -> 14497900
F24: 0 | H24: =H23+F24-G24 -> 14497900
F25: 0 | H25: =H24+F25-G25 -> 14497900
F26: 0 | H26: =H25+F26-G26 -> 14497900
F27: 0 | H27: =H26+F27-G27 -> 14497900
F28: 0 | H28: =H27+F28-G28 -> 14497900
F29: 0 | H29: =H28+F29-G29 -> 14497900
F30: 0 | H30: =H29+F30-G30 -> 14497900
F31: 0 | H31: =H30+F31-G31 -> 14497900
F32: 0 | H32: =H31+F32-G32 -> 14497900
... F56: 0 | H56: =H55+F56-G56 -> 14497900
H57: =H56+F57-G57 -> 14497900
H58: =H57+F58-G58 -> 14497900
H59: =H58+F59-G59 -> 14497900
H60: =H59+F60-G60 -> 14497900
H61: =H60+F61-G61 -> 14497900
H62: =H61+F62-G62 -> 14497900
H63: =H62+F63-G63 -> 14497900
H64: =H63+F64-G64 -> 14497900
H65: =H64+F65-G65 -> 14497900
H66: =H65+F66-G66 -> 14497900
H67: =H66+F67-G67 -> 14497900
H68: =H67+F68-G68 -> 14497900
... H589: =H588+F589-G589 -> 14497900
F590: =SUM(F12:F589) -> 112000000 | G590: =SUM(G12:G589) -> 97502100 | I590: =SUM(I16:I589) -> 0 | J590: =SUM(J16:J589) -> 0 | K590: =SUM(K16:K589) -> 0 | L590: =SUM(L16:L589) -> 0 | M590: =SUM(M16:M589) -> 0 | N590: =SUM(N16:N589) -> 0 | O590: =SUM(O12:O589) -> 0 | P590: =SUM(P12:P589) -> 0 | Q590: =SUM(Q12:Q589) -> 0 | R590: =SUM(R12:R589) -> 0 | S590: =SUM(S12:S589) -> 0 | T590: =SUM(T12:T589) -> 0 | U590: =SUM(U12:U589) -> 0 | V590: =SUM(V12:V589) -> 0 | ... AH590: =SUM(AH12:AH589) -> 50000 | AJ590: =SUM(AJ12:AJ589) -> 0 | AL590: =SUM(AL12:AL589) -> 0

Sheet Others
B10: Bank Analysis Schedule
B12: Date | C12: Description | D12: Transaction Categorisation | E12: User Unit/ Department | F12: Total Inflow | G12: Total Outflow (Expenses ) | H12: Balance
F14: N | G14: N | H14: N
F15: 0 | G15: 0 | H15: =F15-G15 -> 0
C16: Hadiza September Salary | E16: Agro-Allied | F16: 0 | G16: 250000 | H16: =H15+F16-G16 -> -250000
C17: Aisha September Salary | E17: Agro-Allied | F17: 0 | G17: 250000 | H17: =H16+F17-G17 -> -500000
B18: 44829 | C18: Munadak Nig Limited | F18: 0 | G18: 3590000 | H18: =H17+F18-G18 -> -4090000
B19: 44839 | C19: Rubix Advisors Limited | E19: Rubix | F19: 0 | G19: 10000000 | H19: =H18+F19-G19 -> -14090000
B20: 44841 | C20: Nawa property | E20: Agro-Allied | F20: 0 | G20: 10416300 | H20: =H19+F20-G20 -> -24506300
B21: 44858 | C21: Aisha October Salary | E21: Agro-Allied | F21: 0 | G21: 250000 | H21: =H20+F21-G21 -> -24756300
B22: 44858 | C22: Hadiza October Salary | E22: Agro-Allied | F22: 0 | G22: 250000 | H22: =H21+F22-G22 -> -25006300
B23: 44858 | C23: Emmanuella October salary | F23: 0 | G23: 150000 | H23: =H22+F23-G23 -> -25156300
B24: 44858 | C24: Abdulmalik October salary | F24: 0 | G24: 150000 | H24: =H23+F24-G24 -> -25306300
C25: Walida Export promotions | F25: 0 | G25: 50000 | H25: =H24+F25-G25 -> -25356300
B26: 44887 | C26: HMO Fliers and Checklist | E26: HMO | F26: 0 | G26: 90000 | H26: =H25+F26-G26 -> -25446300
B27: 44887 | C27: Tchill (Agro Allied) | E27: Agro-Allied | F27: 0 | G27: 10000000 | H27: =H26+F27-G27 -> -35446300
B28: 44887 | C28: Zainab Nafdac Reimbursemt | F28: 0 | G28: 300000 | H28: =H27+F28-G28 -> -35746300
B29: 44887 | C29: Hadiza November Salary | E29: Agro-Allied | F29: 0 | G29: 250000 | H29: =H28+F29-G29 -> -35996300
B30: 44887 | C30: Aisha November Salary | E30: Agro-Allied | F30: 0 | G30: 250000 | H30: =H29+F30-G30 -> -36246300
B31: 44887 | C31: Emmanuella November salary | F31: 0 | G31: 150000 | H31: =H30+F31-G31 -> -36396300
B32: 44887 | C32: Abdulmalik November salary | F32: 0 | G32: 150000 | H32: =H31+F32-G32 -> -36546300
B33: 44887 | C33: Abdullahi Nabegu November Salary | F33: 0 | G33: 300000 | H33: =H32+F33-G33 -> -36846300
B34: 44887 | C34: Nura November Salary | F34: 0 | G34: 300000 | H34: =H33+F34-G34 -> -37146300
B35: 44887 | C35: Life Zone Pharmacy and stores | F35: 0 | G35: 10000000 | H35: =H34+F35-G35 -> -47146300
B36: 44887 | C36: Nafisa Ahmad Consultancy | E36: All round | F36: 0 | G36: 2000000 | H36: =H35+F36-G36 -> -49146300
B37: 44887 | C37: Basiru Salisu Consultancy | E37: HMO | F37: 0 | G37: 100000 | H37: =H36+F37-G37 -> -49246300
B38: 44889 | C38: Consultancy | E38: HMO | F38: 0 | G38: 300000 | H38: =H37+F38-G38 -> -49546300
B39: 44889 | C39: Crelio health subscription plan | E39: HMO | F39: 0 | G39: 1045000 | H39: =H38+F39-G39 -> -50591300
B40: 44889 | C40: Health care support systems | E40: HMO | F40: 0 | G40: 2000000 | H40: =H39+F40-G40 -> -52591300
B41: 44889 | C41: Acturial services | E41: HMO | F41: 0 | G41: 2553125 | H41: =H40+F41-G41 -> -55144425
B42: 44889 | C42: HMO Stipends | E42: HMO | F42: 0 | G42: 1300000 | H42: =H41+F42-G42 -> -56444425
B43: 44889 | C43: HMO office documents | E43: HMO | F43: 0 | G43: 170000 | H43: =H42+F43-G43 -> -56614425
B44: 44893 | C44: HMO feeding Allowance | E44: HMO | F44: 0 | G44: 125000 | H44: =H43+F44-G44 -> -56739425
B45: 44895 | C45: IT Subscription | E45: HMO | F45: 0 | G45: 130000 | H45: =H44+F45-G45 -> -56869425
B46: 44896 | C46: Legal Cinsultation fees | D46: 2500 | E46: Peramare Kenya | F46: 0 | G46: 1875000 | H46: =H45+F46-G46 -> -58744425
B47: 44901 | C47: A parcel for the MD | G47: 25000 | H47: =H46+F47-G47 -> -58769425
B48: 44904 | C48: HMO Tea Room | E48: HMO | G48: 42000 | H48: =H47+F48-G48 -> -58811425
B49: 44904 | C49: TV for HMO | E49: HMO | G49: 370000 | H49: =H48+F49-G49 -> -59181425
B50: 44904 | C50: Logistics for IT Sky Solutions Meeting | E50: HMO | G50: 26500 | H50: =H49+F50-G50 -> -59207925
B51: 44904 | C51: Development of Health Care Provider (HCP) Network | E51: HMO | G51: 4914525 | H51: =H50+F51-G51 -> -64122450
B52: 44908 | C52: Tchill (Agro Allied) | E52: Agro Allied | G52: 16115766 | H52: =H51+F52-G52 -> -80238216
B53: 44908 | C53: Consultancy fee for EV | E53: Transport | G53: 2205000 | H53: =H52+F53-G53 -> -82443216
B54: 44909 | C54: Brochures | E54: HMO | G54: 630000 | H54: =H53+F54-G54 -> -83073216
B55: 44909 | C55: 32 Certificates | E55: Agro Allied | G55: 25600 | H55: =H54+F55-G55 -> -83098816
B56: 44909 | C56: Peramare Energy | E56: Energy | G56: 3352500 | H56: =H55+F56-G56 -> -86451316
B57: 44909 | C57: Nura and Abdul December Salary | G57: 600000 | H57: =H56+F57-G57 -> -87051316
B58: 44909 | C58: Hadiza and Aisha December Salary | G58: 500000 | H58: =H57+F58-G58 -> -87551316
B59: 44909 | C59: Emmanuella and Abdul December Salary | G59: 450000 | H59: =H58+F59-G59 -> -88001316
G60: 0 | H60: =H59+F60-G60 -> -88001316
B61: 44914 | C61: Travel expenses for MD | G61: 1000000 | H61: =H60+F61-G61 -> -89001316
B62: 44914 | C62: Feeding Fees for HMO | E62: HMO | G62: 291000 | H62: =H51+F62-G62 -> -64413450
B63: 44918 | C63: IT Sky Solutions | E63: HMO | G63: 2000000 | H63: =H52+F63-G63 -> -82238216
B64: 44918 | C64: Prodution of documents for health care provider and Regional coordinators fees | E64: HMO | G64: 2243800 | H64: =H53+F64-G64 -> -84687016
B65: 44918 | C65: HMO staff stipend | E65: HMO | G65: 2870000 | H65: =H54+F65-G65 -> -85943216
B66: 44918 | C66: Installation of Acs | E66: Agro Allied | G66: 469800 | H66: =H55+F66-G66 -> -83568616
B67: 44918 | C67: MD's request | G67: 2000000 | H67: =H66+F67-G67 -> -85568616
G68: 0 | H68: =H67+F68-G68 -> -85568616
G69: 0 | H69: =H68+F69-G69 -> -85568616
G70: 0 | H70: =H69+F70-G70 -> -85568616
G71: 0 | H71: =H70+F71-G71 -> -85568616
G72: 0 | H72: =H71+F72-G72 -> -85568616
F73: =SUM(F12:F72) -> 0 | G73: =SUM(G12:G72) -> 98875916

Sheet Peramare Ghana
B10: Bank Analysis Schedule
B12: Date | C12: Description | D12: Transaction Categorisation | E12: User Unit/ Department | F12: Total Inflow | G12: Total Outflow (Expenses ) | H12: Balance
F14: N | G14: N | H14: N
B15: 44824 | C15: Income | F15: 133000000 | H15: =F15-G15 -> 133000000
F16: 0 | H16: =H15+F16-G16 -> 133000000
F17: 0 | H17: =H16+F17-G17 -> 133000000
F18: 0 | H18: =H17+F18-G18 -> 133000000
F19: 0 | H19: =H18+F19-G19 -> 133000000
F20: 0 | H20: =H19+F20-G20 -> 133000000
F21: 0 | H21: =H20+F21-G21 -> 133000000
F22: 0 | H22: =H21+F22-G22 -> 133000000
F23: 0 | H23: =H22+F23-G23 -> 133000000
F24: 0 | H24: =H23+F24-G24 -> 133000000
F25: 0 | H25: =H24+F25-G25 -> 133000000
F26: 0 | H26: =H25+F26-G26 -> 133000000
F27: 0 | H27: =H26+F27-G27 -> 133000000
... F56: 0 | H56: =H55+F56-G56 -> 133000000
H57: =H56+F57-G57 -> 133000000
H58: =H57+F58-G58 -> 133000000
H59: =H58+F59-G59 -> 133000000
H60: =H59+F60-G60 -> 133000000
H61: =H60+F61-G61 -> 133000000
H62: =H61+F62-G62 -> 133000000
H63: =H62+F63-G63 -> 133000000
H64: =H63+F64-G64 -> 133000000
H65: =H64+F65-G65 -> 133000000
H66: =H65+F66-G66 -> 133000000
H67: =H66+F67-G67 -> 133000000
H68: =H67+F68-G68 -> 133000000
... H589: =H588+F589-G589 -> 133000000
F590: =SUM(F12:F589) -> 133000000 | G590: =SUM(G12:G589) -> 0

Sheet Other
B10: Bank Analysis Schedule
B12: Date | C12: Description | D12: Transaction Categorisation | E12: User Unit/ Department | F12: Total Inflow | G12: Total Outflow (Expenses ) | H12: Balance
F14: N | G14: N | H14: N
B15: 44829 | C15: Munadak Nig Limited | F15: 0 | G15: 3590000 | H15: -3590000
B16: 44839 | C16: Rubix Advisors Limited | E16: Rubix | F16: 0 | G16: 10000000 | H16: =H15+F16-G16 -> -13590000
B17: 44858 | C17: Emmanuella October salary | F17: 0 | G17: 150000 | H17: =H16+F17-G17 -> -13740000
B18: 44858 | C18: Abdulmalik October salary | F18: 0 | G18: 150000 | H18: =H17+F18-G18 -> -13890000
C19: Walida Export promotions | F19: 0 | G19: 50000 | H19: =H18+F19-G19 -> -13940000
B20: 44887 | C20: Zainab Nafdac Reimbursemt | F20: 0 | G20: 300000 | H20: =H19+F20-G20 -> -14240000
B21: 44887 | C21: Emmanuella November salary | F21: 0 | G21: 150000 | H21: =H20+F21-G21 -> -14390000
B22: 44887 | C22: Abdulmalik November salary | F22: 0 | G22: 150000 | H22: =H21+F22-G22 -> -14540000
B23: 44887 | C23: Abdullahi Nabegu November Salary | F23: 0 | G23: 300000 | H23: =H22+F23-G23 -> -14840000
B24: 44887 | C24: Nura November Salary | F24: 0 | G24: 300000 | H24: =H23+F24-G24 -> -15140000
B25: 44887 | C25: Life Zone Pharmacy and stores | F25: 0 | G25: 10000000 | H25: =H24+F25-G25 -> -25140000
B26: 44887 | C26: Nafisa Ahmad Consultancy | E26: All round | F26: 0 | G26: 200000 | H26: =H25+F26-G26 -> -25340000
B27: 44896 | C27: Legal Cinsultation fees | D27: 2500 | E27: Peramare Kenya | F27: 0 | G27: 1875000 | H27: =H26+F27-G27 -> -27215000
B28: 44901 | C28: A parcel for the MD | G28: 25000 | H28: =H27+F28-G28 -> -27240000
B29: 44908 | C29: Consultancy fee for EV | E29: Transport | G29: 2205000 | H29: =H28+F29-G29 -> -29445000
B30: 44909 | C30: Peramare Energy | E30: Energy | G30: 3352500 | H30: =H29+F30-G30 -> -32797500
B31: 44909 | C31: Nura and Abdul December Salary | G31: 600000 | H31: =H30+F31-G31 -> -33397500
B32: 44909 | C32: Emmanuella and Abdul December Salary | G32: 450000 | H32: =H31+F32-G32 -> -33847500
G33: 0 | H33: =H32+F33-G33 -> -33847500
B34: 44914 | C34: Travel expenses for MD | G34: 1000000 | H34: =H33+F34-G34 -> -34847500
G35: 0 | H35: =H34+F35-G35 -> -34847500
F36: =SUM(F12:F35) -> 0 | G36: =SUM(G12:G35) -> 34847500

Sheet Cash-In-Hand Schedule_
F9: =SUM(H20,H21,H22,H23,H24,H25,H26) -> 33800
B11: Cash-In-Hand/ Imprest Analysis Schedule
J12: Inflow Breakdown | P12: Outflow Breakdown
B13: Date | C13: Description | D13: Transaction Categorisation | E13: Voucher Number | F13: User Unit/ Department | G13: Total Inflow | H13: Total Outflow (Expenses ) | I13: Balance | P13: Assets | S13: Overheads & Salary | AL13: Others
J14: Directors/ Shareholders Contribution | K14: Revenue | L14: Reversal | M14: Interest | N14: Advance Refund | O14: Intra Bank Transfer | P14: Office Equipment | Q14: Furnitures & Fittings | R14: Motor Vehicle | S14: Repairs & Maintenance | T14: Transportation | U14: Staff Welfare, Medicals and Entertainment | V14: Security services | W14: Volunteer Stipend | X14: Staff salary & Allowance | Y14: Professional Fees | Z14: Internet & Telecommunication | AA14: Stationery & office supplies | AB14: Registration, Fees and Dues | AC14: Petty cash | AD14: Printing | AE14: Hotel Accommodation | AF14: Fuel & Lubricant | AG14: Tax | AH14: Training and Development | AI14: Utility | AJ14: Product Logistics (Air, Sea, Rail and Land) | AK14: Bank Charges | AL14: Intra bank transfer | AM14: Reversal
G15: N | H15: N | I15: N | J15: N | K15: N | L15: N | M15: N | N15: N | O15: N | P15: N | Q15: N | R15: N | S15: N | T15: N | U15: N | V15: N | W15: N | X15: N | Y15: N | Z15: N | AA15: N | AB15: N | AC15: N | AD15: N | AE15: N | AF15: N | AG15: N | AH15: N | AI15: N | AK15: N | AL15: N | AM15: N
B16: 44807 | C16: Purchase of bottled water | D16: Staff welfare | E16: PCV/0001 | F16: Admin | H16: 5100 | I16: =G16-H16 -> -5100 | U16: 5100
B17: 44818 | C17: Purchase of bottled water | D17: Staff welfare | E17: PCV/0002 | F17: Admin | H17: 5100 | I17: =I16+G17-H17 -> -10200 | U17: 5100
B18: 44824 | C18: Purchase of bottled water | D18: Staff welfare | E18: PCV/0003 | F18: Admin | H18: 10200 | I18: =I17+G18-H18 -> -20400 | U18: 10200
B19: 44824 | C19: Purchase of dispenser water | D19: Staff welfare | E19: PCV/0004 | F19: Admin | H19: 2500 | I19: =I18+G19-H19 -> -22900 | U19: 2500
B20: 44839 | C20: Reimbursement of staff trasnportation expenses | D20: Transportation | E20: PCV/0005 | F20: HR | H20: 6400 | I20: =I19+G20-H20 -> -29300
B21: 44839 | C21: Tranportation cost for staff | D21: Transportation | E21: PCV/0006 | F21: HR | H21: 5000 | I21: =I20+G21-H21 -> -34300
B22: 44841 | C22: Reimbursement of staff trasnportation expenses | D22: Transportation | E22: PCV/0007 | F22: HR | H22: 3000 | I22: =I21+G22-H22 -> -37300
B23: 44845 | C23: Purchase of bottled water | D23: Staff welfare | E23: PCV/0008 | F23: Admin | H23: 12500 | I23: =I22+G23-H23 -> -49800
B24: 44853 | C24: Cash advance ofr staff transportation | D24: Transportation | E24: PCV/0009 | F24: HR | H24: 2000 | I24: =I23+G24-H24 -> -51800
B25: 44860 | C25: For the purchse of dispenser water | D25: Staff welfare | E25: PCV/0010 | F25: Admin | H25: 2400 | I25: =I24+G25-H25 -> -54200
B26: 44862 | C26: Reimbursement of staff trasnportation expenses | D26: Transportation | E26: PCV/0011 | F26: HR | H26: 2500 | I26: =I25+G26-H26 -> -56700
B27: 44866 | C27: Plumber | D27: Repairs and Maintenance | E27: PCV/0012 | H27: 5000 | I27: =I26+G27-H27 -> -61700
B28: 44874 | C28: Water dispenser | D28: Staff welfare | E28: PCV/0013 | H28: 4000 | I28: =I27+G28-H28 -> -65700
B29: 44881 | C29: Repairs and Maintenance: Motor vehicle clutch | E29: PCV/0014 | H29: 3800 | I29: =I28+G29-H29 -> -69500
B30: 44881 | C30: Staff Welfare: Feeding For Staff | E30: PCV/0015 | H30: 5000 | I30: =I29+G30-H30 -> -74500
B31: 44881 | C31: Purchase of kettles | E31: PCV/0016 | H31: 5000 | I31: =I30+G31-H31 -> -79500
B32: 44882 | C32: Fuel and Lubricants:Fuel for Motor Vehicle | E32: PCV/0017 | H32: 10000 | I32: =I31+G32-H32 -> -89500
B33: 44888 | C33: Staff Welfare: Refreshment for SOGON | E33: PCV/0018 | H33: 15000 | I33: =I32+G33-H33 -> -104500
B34: 44900 | C34: Payment for fuel | D34: Fuel and Lubricants | E34: PCV/0019 | H34: 8000 | I34: =I33+G34-H34 -> -112500
B35: 44903 | C35: Purchase of bottled water | D35: Staff welfare | E35: PCV/0020 | H35: 12500 | I35: =I34+G35-H35 -> -125000
B36: 44911 | C36: Purchase of paper | E36: PCV/0021 | H36: 4000 | I36: =I35+G36-H36 -> -129000
E37: PCV/0022 | I37: =I36+G37-H37 -> -129000
E38: PCV/0023 | I38: =I37+G38-H38 -> -129000
E39: PCV/0024 | I39: =I38+G39-H39 -> -129000
E40: PCV/0025 | I40: =I39+G40-H40 -> -129000
E41: PCV/0026 | I41: =I40+G41-H41 -> -129000
E42: PCV/0027 | I42: =I41+G42-H42 -> -129000
E43: PCV/0028 | I43: =I42+G43-H43 -> -129000
I44: =I43+G44-H44 -> -129000
I45: =I44+G45-H45 -> -129000
I46: =I45+G46-H46 -> -129000
I47: =I46+G47-H47 -> -129000
I48: =I47+G48-H48 -> -129000
I49: =I48+G49-H49 -> -129000
I50: =I49+G50-H50 -> -129000
I51: =I50+G51-H51 -> -129000
I52: =I51+G52-H52 -> -129000
I53: =I52+G53-H53 -> -129000
I54: =I53+G54-H54 -> -129000
I55: =I54+G55-H55 -> -129000
... I589: =I588+G589-H589 -> -129000
G590: =SUM(G13:G589) -> 0 | H590: =SUM(H13:H589) -> 129000 | J590: =SUM(J16:J589) -> 0 | K590: =SUM(K16:K589) -> 0 | L590: =SUM(L16:L589) -> 0 | M590: =SUM(M16:M589) -> 0 | N590: =SUM(N16:N589) -> 0 | O590: =SUM(O16:O589) -> 0 | P590: =SUM(P13:P589) -> 0 | Q590: =SUM(Q13:Q589) -> 0 | R590: =SUM(R13:R589) -> 0 | S590: =SUM(S13:S589) -> 0 | T590: =SUM(T13:T589) -> 0 | U590: =SUM(U13:U589) -> 22900 | V590: =SUM(V13:V589) -> 0 | W590: =SUM(W13:W589) -> 0 | ... AI590: =SUM(AI13:AI589) -> 0 | AK590: =SUM(AK13:AK589) -> 0 | AM590: =SUM(AM13:AM589) -> 0

Sheet HMO
B10: Bank Analysis Schedule
B12: Date | C12: Description | D12: Transaction Categorisation | E12: User Unit/ Department | F12: Total Inflow | G12: Total Outflow (Expenses ) | H12: Balance
B14: 44887 | C14: HMO Fliers and Checklist | E14: HMO | F14: 0 | G14: 90000 | H14: 90000
B15: 44887 | C15: Basiru Salisu Consultancy | E15: HMO | F15: 0 | G15: 100000 | H15: =H14+F15-G15 -> -10000
B16: 44889 | C16: Consultancy | E16: HMO | F16: 0 | G16: 300000 | H16: =H15+F16-G16 -> -310000
B17: 44889 | C17: Crelio health subscription plan | E17: HMO | F17: 0 | G17: 1045000 | H17: =H16+F17-G17 -> -1355000
B18: 44889 | C18: Health care support systems | E18: HMO | F18: 0 | G18: 2000000 | H18: =H17+F18-G18 -> -3355000
B19: 44889 | C19: Acturial services | E19: HMO | F19: 0 | G19: 2553125 | H19: =H18+F19-G19 -> -5908125
B20: 44889 | C20: HMO Stipends | E20: HMO | F20: 0 | G20: 1300000 | H20: =H19+F20-G20 -> -7208125
B21: 44889 | C21: HMO office documents | E21: HMO | F21: 0 | G21: 170000 | H21: =H20+F21-G21 -> -7378125
B22: 44893 | C22: HMO feeding Allowance | E22: HMO | F22: 0 | G22: 125000 | H22: =H21+F22-G22 -> -7503125
B23: 44895 | C23: IT Subscription | E23: HMO | F23: 0 | G23: 130000 | H23: =H22+F23-G23 -> -7633125
B24: 44904 | C24: HMO Tea Room | E24: HMO | G24: 42000 | H24: =H23+F24-G24 -> -7675125
B25: 44904 | C25: TV for HMO | E25: HMO | G25: 370000 | H25: =H24+F25-G25 -> -8045125
B26: 44904 | C26: Logistics for IT Sky Solutions Meeting | E26: HMO | G26: 26500 | H26: =H25+F26-G26 -> -8071625
B27: 44904 | C27: Development of Health Care Provider (HCP) Network | E27: HMO | G27: 4914525 | H27: =H26+F27-G27 -> -12986150
B28: 44909 | C28: Brochures | E28: HMO | G28: 630000 | H28: =H27+F28-G28 -> -13616150
F29: =SUM(F12:F28) -> 0 | G29: =SUM(G12:G28) -> 13796150

Sheet Agro-Allied
B10: Bank Analysis Schedule
B12: Date | C12: Description | D12: Transaction Categorisation | E12: User Unit/ Department | F12: Total Inflow | G12: Total Outflow (Expenses ) | H12: Balance
F14: N | G14: N | H14: N
F15: 0 | G15: 0 | H15: =F15-G15 -> 0
C16: Hadiza September Salary | E16: Agro-Allied | F16: 0 | G16: 250000 | H16: =H15+F16-G16 -> -250000
C17: Aisha September Salary | E17: Agro-Allied | F17: 0 | G17: 250000 | H17: =H16+F17-G17 -> -500000
B18: 44841 | C18: Nawa property | E18: Agro-Allied | F18: 0 | G18: 10416300 | H18: =H17+F18-G18 -> -10916300
B19: 44858 | C19: Aisha October Salary | E19: Agro-Allied | F19: 0 | G19: 250000 | H19: =H18+F19-G19 -> -11166300
B20: 44858 | C20: Hadiza October Salary | E20: Agro-Allied | F20: 0 | G20: 250000 | H20: =H19+F20-G20 -> -11416300
B21: 44887 | C21: Tchill (Agro Allied) | E21: Agro-Allied | F21: 0 | G21: 10000000 | H21: =H20+F21-G21 -> -21416300
B22: 44887 | C22: Hadiza November Salary | E22: Agro-Allied | F22: 0 | G22: 250000 | H22: =H21+F22-G22 -> -21666300
B23: 44887 | C23: Aisha November Salary | E23: Agro-Allied | F23: 0 | G23: 250000 | H23: =H22+F23-G23 -> -21916300
B24: 44908 | C24: Tchill (Agro Allied) | E24: Agro Allied | G24: 16115766 | H24: =H23+F24-G24 -> -38032066
B25: 44909 | C25: 32 Certificates | E25: Agro Allied | G25: 25600 | H25: =H24+F25-G25 -> -38057666
B26: 44909 | C26: Hadiza and Aisha December Salary | E26: Agro Allied | G26: 500000 | H26: =H25+F26-G26 -> -38557666
F27: =SUM(F12:F26) -> 0 | G27: =SUM(G12:G26) -> 38557666
